Workbook

Sheet README
A1: Karni Jewellery — Master Product Database
A2: 8 linked sheets · 474 variants · 163 designs · live analytics
A4: The 8 sheets
A5: DESIGNS — one row per design concept (163). Story, materials, cost, marketing copy, base price live here once.
A6: VARIANTS — your 474 SKUs, enriched. Stock, barcode, channel flags, prices in 4 currencies, auto-margins & sales pulled from Transactions.
A7: TRANSACTIONS — log every sale / restock / return here. This powers all sales & profit analytics.
A8: DASHBOARD — live KPIs: inventory health, sales, profit, channel split, catalog breakdown.
A9: SHOPIFY EXPORT — auto-built, Shopify CSV schema. Save as CSV to import.
A10: ETSY EXPORT — auto-built, Etsy listing reference.
A11: DROPDOWNS — control lists, FX rates (USD/EUR/RUB), channel list, cleanup log.
A12: README — this sheet.
A14: Colour coding (industry standard)
... A33: Full log on the Dropdowns sheet (right side). All 474 original rows preserved.

Sheet Designs
A1: IDENTIFICATION | H1: STORY & CULTURE | L1: MATERIALS & CRAFT | W1: COST · PRICE · MARGIN | AF1: MARKETING / DIGITAL | AN1: LIFECYCLE
A2: DesignID | B2: Design name (EN) | C2: Design name (HY) | D2: Category | E2: Collection | F2: Subcollection | G2: Variant count | H2: Motif / Symbol | I2: Cultural meaning (EN) | J2: Cultural meaning (HY) | K2: Inspiration source | L2: Metal | M2: Plating / Finish | N2: Enamel type | O2: Stones / Inlays | P2: Base weight (g) | Q2: Length (mm) | R2: Width (mm) | S2: Chain length (mm) | T2: Clasp | U2: Handmade | V2: Production time (days) | W2: Base price (AMD) | X2: Materials cost (AMD) | Y2: Labor cost (AMD) | Z2: Packaging cost (AMD) | AA2: Total cost (AMD) | AB2: Gross margin % | AC2: Markup x | AD2: Status | AE2: Made to order | AF2: Primary image URL | AG2: IG post URL | AH2: Caption (EN) | AI2: Caption (HY) | AJ2: Hashtags | AK2: SEO title | AL2: SEO description | AM2: Hero product? | AN2: Launch date | AO2: Discontinued date | AP2: Notes
A3: DSGN-PEND-ALPHA-AYB | B3: Bird Letter Pendant | D3: Pendant | E3: Alphabet | F3: Ա | G3: 3 | H3: Armenian bird letter (թռչնագիր) | I3: Bird letters are an ornamental medieval Armenian script where each letter is formed from stylised birds, used in illuminated manuscripts. | L3: 925 Silver Gold-Plated | M3: 24k Gold Plate | N3: Hot / Vitreous | U3: Yes | W3: 19000 | AA3: =IF(COUNT(X3,Y3,Z3)=0,"",SUM(X3,Y3,Z3)) | AB3: =IFERROR(IF(OR(W3="",AA3=""),"",(W3-AA3)/W3),"") | AC3: =IFERROR(IF(OR(AA3="",AA3=0),"",W3/AA3),"") | AD3: Active | AE3: No | AL3: No
A4: DSGN-PEND-ALPHA-BEN | B4: Bird Letter Pendant | D4: Pendant | E4: Alphabet | F4: Բ | G4: 3 | H4: Armenian bird letter (թռչնագիր) | I4: Bird letters are an ornamental medieval Armenian script where each letter is formed from stylised birds, used in illuminated manuscripts. | L4: 925 Silver Gold-Plated | M4: 24k Gold Plate | N4: Hot / Vitreous | U4: Yes | W4: 19000 | AA4: =IF(COUNT(X4,Y4,Z4)=0,"",SUM(X4,Y4,Z4)) | AB4: =IFERROR(IF(OR(W4="",AA4=""),"",(W4-AA4)/W4),"") | AC4: =IFERROR(IF(OR(AA4="",AA4=0),"",W4/AA4),"") | AD4: Active | AE4: No | AL4: No
A5: DSGN-PEND-ALPHA-GIM | B5: Bird Letter Pendant | D5: Pendant | E5: Alphabet | F5: Գ | G5: 3 | H5: Armenian bird letter (թռչնագիր) | I5: Bird letters are an ornamental medieval Armenian script where each letter is formed from stylised birds, used in illuminated manuscripts. | L5: 925 Silver Gold-Plated | M5: 24k Gold Plate | N5: Hot / Vitreous | U5: Yes | W5: 19000 | AA5: =IF(COUNT(X5,Y5,Z5)=0,"",SUM(X5,Y5,Z5)) | AB5: =IFERROR(IF(OR(W5="",AA5=""),"",(W5-AA5)/W5),"") | AC5: =IFERROR(IF(OR(AA5="",AA5=0),"",W5/AA5),"") | AD5: Active | AE5: No | AL5: No
A6: DSGN-PEND-ALPHA-DA | B6: Bird Letter Pendant | D6: Pendant | E6: Alphabet | F6: Դ | G6: 3 | H6: Armenian bird letter (թռչնագիր) | I6: Bird letters are an ornamental medieval Armenian script where each letter is formed from stylised birds, used in illuminated manuscripts. | L6: 925 Silver Gold-Plated | M6: 24k Gold Plate | N6: Hot / Vitreous | U6: Yes | W6: 19000 | AA6: =IF(COUNT(X6,Y6,Z6)=0,"",SUM(X6,Y6,Z6)) | AB6: =IFERROR(IF(OR(W6="",AA6=""),"",(W6-AA6)/W6),"") | AC6: =IFERROR(IF(OR(AA6="",AA6=0),"",W6/AA6),"") | AD6: Active | AE6: No | AL6: No
A7: DSGN-PEND-ALPHA-YECH | B7: Bird Letter Pendant | D7: Pendant | E7: Alphabet | F7: Ե | G7: 3 | H7: Armenian bird letter (թռչնագիր) | I7: Bird letters are an ornamental medieval Armenian script where each letter is formed from stylised birds, used in illuminated manuscripts. | L7: 925 Silver Gold-Plated | M7: 24k Gold Plate | N7: Hot / Vitreous | U7: Yes | W7: 19000 | AA7: =IF(COUNT(X7,Y7,Z7)=0,"",SUM(X7,Y7,Z7)) | AB7: =IFERROR(IF(OR(W7="",AA7=""),"",(W7-AA7)/W7),"") | AC7: =IFERROR(IF(OR(AA7="",AA7=0),"",W7/AA7),"") | AD7: Active | AE7: No | AL7: No
A8: DSGN-PEND-ALPHA-ZA | B8: Bird Letter Pendant | D8: Pendant | E8: Alphabet | F8: Զ | G8: 3 | H8: Armenian bird letter (թռչնագիր) | I8: Bird letters are an ornamental medieval Armenian script where each letter is formed from stylised birds, used in illuminated manuscripts. | L8: 925 Silver Gold-Plated | M8: 24k Gold Plate | N8: Hot / Vitreous | U8: Yes | W8: 19000 | AA8: =IF(COUNT(X8,Y8,Z8)=0,"",SUM(X8,Y8,Z8)) | AB8: =IFERROR(IF(OR(W8="",AA8=""),"",(W8-AA8)/W8),"") | AC8: =IFERROR(IF(OR(AA8="",AA8=0),"",W8/AA8),"") | AD8: Active | AE8: No | AL8: No
A9: DSGN-PEND-ALPHA-E | B9: Bird Letter Pendant | D9: Pendant | E9: Alphabet | F9: Է | G9: 3 | H9: Armenian bird letter (թռչնագիր) | I9: Bird letters are an ornamental medieval Armenian script where each letter is formed from stylised birds, used in illuminated manuscripts. | L9: 925 Silver Gold-Plated | M9: 24k Gold Plate | N9: Hot / Vitreous | U9: Yes | W9: 19000 | AA9: =IF(COUNT(X9,Y9,Z9)=0,"",SUM(X9,Y9,Z9)) | AB9: =IFERROR(IF(OR(W9="",AA9=""),"",(W9-AA9)/W9),"") | AC9: =IFERROR(IF(OR(AA9="",AA9=0),"",W9/AA9),"") | AD9: Active | AE9: No | AL9: No
A10: DSGN-PEND-ALPHA-YT | B10: Bird Letter Pendant | D10: Pendant | E10: Alphabet | F10: Ը | G10: 3 | H10: Armenian bird letter (թռչնագիր) | I10: Bird letters are an ornamental medieval Armenian script where each letter is formed from stylised birds, used in illuminated manuscripts. | L10: 925 Silver Gold-Plated | M10: 24k Gold Plate | N10: Hot / Vitreous | U10: Yes | W10: 19000 | AA10: =IF(COUNT(X10,Y10,Z10)=0,"",SUM(X10,Y10,Z10)) | AB10: =IFERROR(IF(OR(W10="",AA10=""),"",(W10-AA10)/W10),"") | AC10: =IFERROR(IF(OR(AA10="",AA10=0),"",W10/AA10),"") | AD10: Active | AE10: No | AL10: No
A11: DSGN-PEND-ALPHA-TO | B11: Bird Letter Pendant | D11: Pendant | E11: Alphabet | F11: Թ | G11: 3 | H11: Armenian bird letter (թռչնագիր) | I11: Bird letters are an ornamental medieval Armenian script where each letter is formed from stylised birds, used in illuminated manuscripts. | L11: 925 Silver Gold-Plated | M11: 24k Gold Plate | N11: Hot / Vitreous | U11: Yes | W11: 19000 | AA11: =IF(COUNT(X11,Y11,Z11)=0,"",SUM(X11,Y11,Z11)) | AB11: =IFERROR(IF(OR(W11="",AA11=""),"",(W11-AA11)/W11),"") | AC11: =IFERROR(IF(OR(AA11="",AA11=0),"",W11/AA11),"") | AD11: Active | AE11: No | AL11: No
A12: DSGN-PEND-ALPHA-ZHE | B12: Bird Letter Pendant | D12: Pendant | E12: Alphabet | F12: Ժ | G12: 3 | H12: Armenian bird letter (թռչնագիր) | I12: Bird letters are an ornamental medieval Armenian script where each letter is formed from stylised birds, used in illuminated manuscripts. | L12: 925 Silver Gold-Plated | M12: 24k Gold Plate | N12: Hot / Vitreous | U12: Yes | W12: 19000 | AA12: =IF(COUNT(X12,Y12,Z12)=0,"",SUM(X12,Y12,Z12)) | AB12: =IFERROR(IF(OR(W12="",AA12=""),"",(W12-AA12)/W12),"") | AC12: =IFERROR(IF(OR(AA12="",AA12=0),"",W12/AA12),"") | AD12: Active | AE12: No | AL12: No
A13: DSGN-PEND-ALPHA-INI | B13: Bird Letter Pendant | D13: Pendant | E13: Alphabet | F13: Ի | G13: 3 | H13: Armenian bird letter (թռչնագիր) | I13: Bird letters are an ornamental medieval Armenian script where each letter is formed from stylised birds, used in illuminated manuscripts. | L13: 925 Silver Gold-Plated | M13: 24k Gold Plate | N13: Hot / Vitreous | U13: Yes | W13: 19000 | AA13: =IF(COUNT(X13,Y13,Z13)=0,"",SUM(X13,Y13,Z13)) | AB13: =IFERROR(IF(OR(W13="",AA13=""),"",(W13-AA13)/W13),"") | AC13: =IFERROR(IF(OR(AA13="",AA13=0),"",W13/AA13),"") | AD13: Active | AE13: No | AL13: No
A14: DSGN-PEND-ALPHA-LYUN | B14: Bird Letter Pendant | D14: Pendant | E14: Alphabet | F14: Լ | G14: 3 | H14: Armenian bird letter (թռչնագիր) | I14: Bird letters are an ornamental medieval Armenian script where each letter is formed from stylised birds, used in illuminated manuscripts. | L14: 925 Silver Gold-Plated | M14: 24k Gold Plate | N14: Hot / Vitreous | U14: Yes | W14: 19000 | AA14: =IF(COUNT(X14,Y14,Z14)=0,"",SUM(X14,Y14,Z14)) | AB14: =IFERROR(IF(OR(W14="",AA14=""),"",(W14-AA14)/W14),"") | AC14: =IFERROR(IF(OR(AA14="",AA14=0),"",W14/AA14),"") | AD14: Active | AE14: No | AL14: No
... A116: DSGN-BRCH-ALPHA-FEH | B116: Bird Letter Brooch | D116: Brooch | E116: Alphabet | F116: Ֆ | G116: 1 | H116: Armenian bird letter (թռչնագիր) | I116: Bird letters are an ornamental medieval Armenian script where each letter is formed from stylised birds, used in illuminated manuscripts. | L116: 925 Silver Gold-Plated | M116: 24k Gold Plate | N116: Hot / Vitreous | U116: Yes | W116: 25000 | AA116: =IF(COUNT(X116,Y116,Z116)=0,"",SUM(X116,Y116,Z116)) | AB116: =IFERROR(IF(OR(W116="",AA116=""),"",(W116-AA116)/W116),"") | AC116: =IFERROR(IF(OR(AA116="",AA116=0),"",W116/AA116),"") | AD116: Active | AE116: No | AL116: No
A117: DSGN-EARRNG-MARASH-S | B117: Marash Earrings | D117: Earring | E117: Marash | G117: 5 | H117: Marash embroidery motif | I117: Marash-work is a distinctive Armenian embroidery style from Cilician Marash, known for its interlaced geometric patterns. | L117: 925 Silver Gold-Plated | M117: 24k Gold Plate | N117: Hot / Vitreous | U117: Yes | W117: 13000 | AA117: =IF(COUNT(X117,Y117,Z117)=0,"",SUM(X117,Y117,Z117)) | AB117: =IFERROR(IF(OR(W117="",AA117=""),"",(W117-AA117)/W117),"") | AC117: =IFERROR(IF(OR(AA117="",AA117=0),"",W117/AA117),"") | AD117: Active | AE117: No | AL117: No
A118: DSGN-EARRNG-MARASH-M | B118: Marash Earrings | D118: Earring | E118: Marash | G118: 4 | H118: Marash embroidery motif | I118: Marash-work is a distinctive Armenian embroidery style from Cilician Marash, known for its interlaced geometric patterns. | L118: 925 Silver Gold-Plated | M118: 24k Gold Plate | N118: Hot / Vitreous | U118: Yes | W118: 27000 | AA118: =IF(COUNT(X118,Y118,Z118)=0,"",SUM(X118,Y118,Z118)) | AB118: =IFERROR(IF(OR(W118="",AA118=""),"",(W118-AA118)/W118),"") | AC118: =IFERROR(IF(OR(AA118="",AA118=0),"",W118/AA118),"") | AD118: Active | AE118: No | AL118: No
A119: DSGN-EARRNG-VAN-S | B119: Van Earrings | D119: Earring | E119: Van | G119: 5 | H119: Van / Vaspurakan motif | I119: Motifs from the Van/Vaspurakan region, echoing the ornament of the Lake Van heartland of historic Armenia. | L119: 925 Silver Gold-Plated | M119: 24k Gold Plate | N119: Hot / Vitreous | U119: Yes | W119: 13000 | AA119: =IF(COUNT(X119,Y119,Z119)=0,"",SUM(X119,Y119,Z119)) | AB119: =IFERROR(IF(OR(W119="",AA119=""),"",(W119-AA119)/W119),"") | AC119: =IFERROR(IF(OR(AA119="",AA119=0),"",W119/AA119),"") | AD119: Active | AE119: No | AL119: No
A120: DSGN-EARRNG-VAN-M | B120: Van Earrings | D120: Earring | E120: Van | G120: 4 | H120: Van / Vaspurakan motif | I120: Motifs from the Van/Vaspurakan region, echoing the ornament of the Lake Van heartland of historic Armenia. | L120: 925 Silver Gold-Plated | M120: 24k Gold Plate | N120: Hot / Vitreous | U120: Yes | W120: 27000 | AA120: =IF(COUNT(X120,Y120,Z120)=0,"",SUM(X120,Y120,Z120)) | AB120: =IFERROR(IF(OR(W120="",AA120=""),"",(W120-AA120)/W120),"") | AC120: =IFERROR(IF(OR(AA120="",AA120=0),"",W120/AA120),"") | AD120: Active | AE120: No | AL120: No
A121: DSGN-EARRNG-ARTSAKHIKHACHANAKHSH-S | B121: Artsakhi Khachanakhsh Earrings | D121: Earring | E121: Artsakhi Khachanakhsh | G121: 6 | H121: Artsakh cross-ornament (khachanakhsh) | I121: Cross-ornament patterns from Artsakh, carrying the carved cross-stone heritage of the region. | L121: 925 Silver Gold-Plated | M121: 24k Gold Plate | N121: Hot / Vitreous | U121: Yes | W121: 13000 | AA121: =IF(COUNT(X121,Y121,Z121)=0,"",SUM(X121,Y121,Z121)) | AB121: =IFERROR(IF(OR(W121="",AA121=""),"",(W121-AA121)/W121),"") | AC121: =IFERROR(IF(OR(AA121="",AA121=0),"",W121/AA121),"") | AD121: Active | AE121: No | AL121: No
A122: DSGN-EARRNG-ARTSAKHIKHACHANAKHSH-M | B122: Artsakhi Khachanakhsh Earrings | D122: Earring | E122: Artsakhi Khachanakhsh | G122: 4 | H122: Artsakh cross-ornament (khachanakhsh) | I122: Cross-ornament patterns from Artsakh, carrying the carved cross-stone heritage of the region. | L122: 925 Silver Gold-Plated | M122: 24k Gold Plate | N122: Hot / Vitreous | U122: Yes | W122: 27000 | AA122: =IF(COUNT(X122,Y122,Z122)=0,"",SUM(X122,Y122,Z122)) | AB122: =IFERROR(IF(OR(W122="",AA122=""),"",(W122-AA122)/W122),"") | AC122: =IFERROR(IF(OR(AA122="",AA122=0),"",W122/AA122),"") | AD122: Active | AE122: No | AL122: No
A123: DSGN-EARRNG-VISHAB-S | B123: Vishab Earrings | D123: Earring | E123: Vishab | G123: 5 | H123: Vishap (dragon-stone) motif | I123: Vishaps are ancient Armenian dragon-stones (vishapakar) found in the highlands, among the oldest carved monuments in the region. | L123: 925 Silver Gold-Plated | M123: 24k Gold Plate | N123: Hot / Vitreous | U123: Yes | W123: 13000 | AA123: =IF(COUNT(X123,Y123,Z123)=0,"",SUM(X123,Y123,Z123)) | AB123: =IFERROR(IF(OR(W123="",AA123=""),"",(W123-AA123)/W123),"") | AC123: =IFERROR(IF(OR(AA123="",AA123=0),"",W123/AA123),"") | AD123: Active | AE123: No | AL123: No
A124: DSGN-EARRNG-VISHAB-M | B124: Vishab Earrings | D124: Earring | E124: Vishab | G124: 4 | H124: Vishap (dragon-stone) motif | I124: Vishaps are ancient Armenian dragon-stones (vishapakar) found in the highlands, among the oldest carved monuments in the region. | L124: 925 Silver Gold-Plated | M124: 24k Gold Plate | N124: Hot / Vitreous | U124: Yes | W124: 27000 | AA124: =IF(COUNT(X124,Y124,Z124)=0,"",SUM(X124,Y124,Z124)) | AB124: =IFERROR(IF(OR(W124="",AA124=""),"",(W124-AA124)/W124),"") | AC124: =IFERROR(IF(OR(AA124="",AA124=0),"",W124/AA124),"") | AD124: Active | AE124: No | AL124: No
A125: DSGN-EARRNG-VISHABAREVAGORG-S | B125: Արեւագորգի Վիշապ | D125: Earring | E125: Vishab Arevagorg | G125: 5 | H125: Vishap + Arevagorg (sun-carpet) motif | I125: Combines the vishap (dragon) motif with the arevagorg (sun-carpet) — an Armenian solar ornament symbolising life and eternity. | L125: 925 Silver Gold-Plated | M125: 24k Gold Plate | N125: Hot / Vitreous | U125: Yes | W125: 13000 | AA125: =IF(COUNT(X125,Y125,Z125)=0,"",SUM(X125,Y125,Z125)) | AB125: =IFERROR(IF(OR(W125="",AA125=""),"",(W125-AA125)/W125),"") | AC125: =IFERROR(IF(OR(AA125="",AA125=0),"",W125/AA125),"") | AD125: Active | AE125: No | AL125: No
A126: DSGN-EARRNG-VISHABAREVAGORG-M | B126: Արեւագորգի Վիշապ | D126: Earring | E126: Vishab Arevagorg | G126: 4 | H126: Vishap + Arevagorg (sun-carpet) motif | I126: Combines the vishap (dragon) motif with the arevagorg (sun-carpet) — an Armenian solar ornament symbolising life and eternity. | L126: 925 Silver Gold-Plated | M126: 24k Gold Plate | N126: Hot / Vitreous | U126: Yes | W126: 27000 | AA126: =IF(COUNT(X126,Y126,Z126)=0,"",SUM(X126,Y126,Z126)) | AB126: =IFERROR(IF(OR(W126="",AA126=""),"",(W126-AA126)/W126),"") | AC126: =IFERROR(IF(OR(AA126="",AA126=0),"",W126/AA126),"") | AD126: Active | AE126: No | AL126: No
A127: DSGN-EARRNG2-MARASH | B127: Marash Earrings (2 pcs) | D127: earrings 2 pcs. | E127: Marash | G127: 4 | H127: Marash embroidery motif | I127: Marash-work is a distinctive Armenian embroidery style from Cilician Marash, known for its interlaced geometric patterns. | L127: 925 Silver Gold-Plated | M127: 24k Gold Plate | N127: Hot / Vitreous | U127: Yes | W127: 36000 | AA127: =IF(COUNT(X127,Y127,Z127)=0,"",SUM(X127,Y127,Z127)) | AB127: =IFERROR(IF(OR(W127="",AA127=""),"",(W127-AA127)/W127),"") | AC127: =IFERROR(IF(OR(AA127="",AA127=0),"",W127/AA127),"") | AD127: Active | AE127: No | AL127: No
A128: DSGN-EARRNG2-VISHAB | B128: Vishab Earrings (2 pcs) | D128: earrings 2 pcs. | E128: Vishab | G128: 4 | H128: Vishap (dragon-stone) motif | I128: Vishaps are ancient Armenian dragon-stones (vishapakar) found in the highlands, among the oldest carved monuments in the region. | L128: 925 Silver Gold-Plated | M128: 24k Gold Plate | N128: Hot / Vitreous | U128: Yes | W128: 36000 | AA128: =IF(COUNT(X128,Y128,Z128)=0,"",SUM(X128,Y128,Z128)) | AB128: =IFERROR(IF(OR(W128="",AA128=""),"",(W128-AA128)/W128),"") | AC128: =IFERROR(IF(OR(AA128="",AA128=0),"",W128/AA128),"") | AD128: Active | AE128: No | AL128: No
... A165: DSGN-CHBRAC-VISHABAREVAGORG | B165: Արեւագորգի Վիշապ | D165: chain bracelet | E165: Vishab Arevagorg | G165: 5 | H165: Vishap + Arevagorg (sun-carpet) motif | I165: Combines the vishap (dragon) motif with the arevagorg (sun-carpet) — an Armenian solar ornament symbolising life and eternity. | L165: 925 Silver Gold-Plated | M165: 24k Gold Plate | N165: Hot / Vitreous | U165: Yes | W165: 17000 | AA165: =IF(COUNT(X165,Y165,Z165)=0,"",SUM(X165,Y165,Z165)) | AB165: =IFERROR(IF(OR(W165="",AA165=""),"",(W165-AA165)/W165),"") | AC165: =IFERROR(IF(OR(AA165="",AA165=0),"",W165/AA165),"") | AD165: Active | AE165: No | AL165: No

Sheet Variants
A1: PRODUCT | I1: PRICING | O1: INVENTORY | T1: COMPLIANCE / PHYSICAL | Z1: CHANNELS | AD1: PERFORMANCE
A2: ID (SKU) | B2: DesignID | C2: Design name | D2: Category | E2: Collection | F2: Subcollection (letter) | G2: Size | H2: Color | I2: Price (AMD) | J2: Price (USD) | K2: Price (EUR) | L2: Price (RUB) | M2: Cost (AMD) | N2: Margin % | O2: Stock on hand | P2: Reserved | Q2: Available | R2: Reorder point | S2: Reorder flag | T2: Location / Bin | U2: Barcode / GTIN | V2: HS code | W2: Country of origin | X2: Weight (g) | Y2: Variant image URL | Z2: On website? | AA2: On Etsy? | AB2: On IG? | AC2: In stockists? | AD2: Status | AE2: Units sold | AF2: Revenue (AMD) | AG2: Last sold | AH2: Notes
A3: KARNI-PEND-ALPHA-AYB-RED | B3: DSGN-PEND-ALPHA-AYB | C3: Bird Letter Pendant | D3: Pendant | E3: Alphabet | F3: Ա | H3: red | I3: 19000 | J3: =IF($I3="","",ROUND($I3*Dropdowns!$K$5,2)) -> 49.4 | K3: =IF($I3="","",ROUND($I3*Dropdowns!$K$6,2)) -> 45.6 | L3: =IF($I3="","",ROUND($I3*Dropdowns!$K$7,2)) -> 3895 | M3: =IFERROR(IF($B3="","",VLOOKUP($B3,Designs!$A$3:$AP$165,27,FALSE())),"") | N3: =IFERROR(IF(OR($I3="",$M3="",$M3=0),"",($I3-$M3)/$I3),"") | O3: 0 | P3: 0 | Q3: =IF($O3="","",$O3-IF($P3="",0,$P3)) -> 0 | R3: 2 | S3: =IF($O3="","",IF($Q3<=$R3,"⚠ REORDER","OK")) -> ⚠ REORDER | V3: 7117.19 | W3: Armenia | Z3: No | AA3: No | AB3: No | AC3: No | AD3: Active | AE3: =IFERROR(SUMIFS(Transactions!$F:$F,Transactions!$C:$C,$A3,Transactions!$D:$D,"Sale"),0) -> 1 | AF3: =IFERROR(SUMIFS(Transactions!$H:$H,Transactions!$C:$C,$A3,Transactions!$D:$D,"Sale"),0) -> 19000 | AG3: =IFERROR(IF(maxifs(Transactions!$B:$B,Transactions!$C:$C,$A3,Transactions!$D:$D,"Sale")=0,"",maxifs(Transactions!$B:$B,Transactions!$C:$C,$A3,Transactions!$D:$D,"Sale")),"")
A4: KARNI-PEND-ALPHA-AYB-TURQUOISE | B4: DSGN-PEND-ALPHA-AYB | C4: Bird Letter Pendant | D4: Pendant | E4: Alphabet | F4: Ա | H4: turquoise | I4: 19000 | J4: =IF($I4="","",ROUND($I4*Dropdowns!$K$5,2)) -> 49.4 | K4: =IF($I4="","",ROUND($I4*Dropdowns!$K$6,2)) -> 45.6 | L4: =IF($I4="","",ROUND($I4*Dropdowns!$K$7,2)) -> 3895 | M4: =IFERROR(IF($B4="","",VLOOKUP($B4,Designs!$A$3:$AP$165,27,FALSE())),"") | N4: =IFERROR(IF(OR($I4="",$M4="",$M4=0),"",($I4-$M4)/$I4),"") | O4: 0 | P4: 0 | Q4: =IF($O4="","",$O4-IF($P4="",0,$P4)) -> 0 | R4: 2 | S4: =IF($O4="","",IF($Q4<=$R4,"⚠ REORDER","OK")) -> ⚠ REORDER | V4: 7117.19 | W4: Armenia | Z4: No | AA4: No | AB4: No | AC4: No | AD4: Active | AE4: =IFERROR(SUMIFS(Transactions!$F:$F,Transactions!$C:$C,$A4,Transactions!$D:$D,"Sale"),0) -> 0 | AF4: =IFERROR(SUMIFS(Transactions!$H:$H,Transactions!$C:$C,$A4,Transactions!$D:$D,"Sale"),0) -> 0 | AG4: =IFERROR(IF(maxifs(Transactions!$B:$B,Transactions!$C:$C,$A4,Transactions!$D:$D,"Sale")=0,"",maxifs(Transactions!$B:$B,Transactions!$C:$C,$A4,Transactions!$D:$D,"Sale")),"")
A5: KARNI-PEND-ALPHA-AYB-WHITE | B5: DSGN-PEND-ALPHA-AYB | C5: Bird Letter Pendant | D5: Pendant | E5: Alphabet | F5: Ա | H5: white | I5: 19000 | J5: =IF($I5="","",ROUND($I5*Dropdowns!$K$5,2)) -> 49.4 | K5: =IF($I5="","",ROUND($I5*Dropdowns!$K$6,2)) -> 45.6 | L5: =IF($I5="","",ROUND($I5*Dropdowns!$K$7,2)) -> 3895 | M5: =IFERROR(IF($B5="","",VLOOKUP($B5,Designs!$A$3:$AP$165,27,FALSE())),"") | N5: =IFERROR(IF(OR($I5="",$M5="",$M5=0),"",($I5-$M5)/$I5),"") | O5: 0 | P5: 0 | Q5: =IF($O5="","",$O5-IF($P5="",0,$P5)) -> 0 | R5: 2 | S5: =IF($O5="","",IF($Q5<=$R5,"⚠ REORDER","OK")) -> ⚠ REORDER | V5: 7117.19 | W5: Armenia | Z5: No | AA5: No | AB5: No | AC5: No | AD5: Active | AE5: =IFERROR(SUMIFS(Transactions!$F:$F,Transactions!$C:$C,$A5,Transactions!$D:$D,"Sale"),0) -> 0 | AF5: =IFERROR(SUMIFS(Transactions!$H:$H,Transactions!$C:$C,$A5,Transactions!$D:$D,"Sale"),0) -> 0 | AG5: =IFERROR(IF(maxifs(Transactions!$B:$B,Transactions!$C:$C,$A5,Transactions!$D:$D,"Sale")=0,"",maxifs(Transactions!$B:$B,Transactions!$C:$C,$A5,Transactions!$D:$D,"Sale")),"")
A6: KARNI-PEND-ALPHA-BEN-RED | B6: DSGN-PEND-ALPHA-BEN | C6: Bird Letter Pendant | D6: Pendant | E6: Alphabet | F6: Բ | H6: red | I6: 19000 | J6: =IF($I6="","",ROUND($I6*Dropdowns!$K$5,2)) -> 49.4 | K6: =IF($I6="","",ROUND($I6*Dropdowns!$K$6,2)) -> 45.6 | L6: =IF($I6="","",ROUND($I6*Dropdowns!$K$7,2)) -> 3895 | M6: =IFERROR(IF($B6="","",VLOOKUP($B6,Designs!$A$3:$AP$165,27,FALSE())),"") | N6: =IFERROR(IF(OR($I6="",$M6="",$M6=0),"",($I6-$M6)/$I6),"") | O6: 0 | P6: 0 | Q6: =IF($O6="","",$O6-IF($P6="",0,$P6)) -> 0 | R6: 2 | S6: =IF($O6="","",IF($Q6<=$R6,"⚠ REORDER","OK")) -> ⚠ REORDER | V6: 7117.19 | W6: Armenia | Z6: No | AA6: No | AB6: No | AC6: No | AD6: Active | AE6: =IFERROR(SUMIFS(Transactions!$F:$F,Transactions!$C:$C,$A6,Transactions!$D:$D,"Sale"),0) -> 0 | AF6: =IFERROR(SUMIFS(Transactions!$H:$H,Transactions!$C:$C,$A6,Transactions!$D:$D,"Sale"),0) -> 0 | AG6: =IFERROR(IF(maxifs(Transactions!$B:$B,Transactions!$C:$C,$A6,Transactions!$D:$D,"Sale")=0,"",maxifs(Transactions!$B:$B,Transactions!$C:$C,$A6,Transactions!$D:$D,"Sale")),"")
A7: KARNI-PEND-ALPHA-BEN-TURQUOISE | B7: DSGN-PEND-ALPHA-BEN | C7: Bird Letter Pendant | D7: Pendant | E7: Alphabet | F7: Բ | H7: turquoise | I7: 19000 | J7: =IF($I7="","",ROUND($I7*Dropdowns!$K$5,2)) -> 49.4 | K7: =IF($I7="","",ROUND($I7*Dropdowns!$K$6,2)) -> 45.6 | L7: =IF($I7="","",ROUND($I7*Dropdowns!$K$7,2)) -> 3895 | M7: =IFERROR(IF($B7="","",VLOOKUP($B7,Designs!$A$3:$AP$165,27,FALSE())),"") | N7: =IFERROR(IF(OR($I7="",$M7="",$M7=0),"",($I7-$M7)/$I7),"") | O7: 0 | P7: 0 | Q7: =IF($O7="","",$O7-IF($P7="",0,$P7)) -> 0 | R7: 2 | S7: =IF($O7="","",IF($Q7<=$R7,"⚠ REORDER","OK")) -> ⚠ REORDER | V7: 7117.19 | W7: Armenia | Z7: No | AA7: No | AB7: No | AC7: No | AD7: Active | AE7: =IFERROR(SUMIFS(Transactions!$F:$F,Transactions!$C:$C,$A7,Transactions!$D:$D,"Sale"),0) -> 0 | AF7: =IFERROR(SUMIFS(Transactions!$H:$H,Transactions!$C:$C,$A7,Transactions!$D:$D,"Sale"),0) -> 0 | AG7: =IFERROR(IF(maxifs(Transactions!$B:$B,Transactions!$C:$C,$A7,Transactions!$D:$D,"Sale")=0,"",maxifs(Transactions!$B:$B,Transactions!$C:$C,$A7,Transactions!$D:$D,"Sale")),"")
A8: KARNI-PEND-ALPHA-BEN-WHITE | B8: DSGN-PEND-ALPHA-BEN | C8: Bird Letter Pendant | D8: Pendant | E8: Alphabet | F8: Բ | H8: white | I8: 19000 | J8: =IF($I8="","",ROUND($I8*Dropdowns!$K$5,2)) -> 49.4 | K8: =IF($I8="","",ROUND($I8*Dropdowns!$K$6,2)) -> 45.6 | L8: =IF($I8="","",ROUND($I8*Dropdowns!$K$7,2)) -> 3895 | M8: =IFERROR(IF($B8="","",VLOOKUP($B8,Designs!$A$3:$AP$165,27,FALSE())),"") | N8: =IFERROR(IF(OR($I8="",$M8="",$M8=0),"",($I8-$M8)/$I8),"") | O8: 0 | P8: 0 | Q8: =IF($O8="","",$O8-IF($P8="",0,$P8)) -> 0 | R8: 2 | S8: =IF($O8="","",IF($Q8<=$R8,"⚠ REORDER","OK")) -> ⚠ REORDER | V8: 7117.19 | W8: Armenia | Z8: No | AA8: No | AB8: No | AC8: No | AD8: Active | AE8: =IFERROR(SUMIFS(Transactions!$F:$F,Transactions!$C:$C,$A8,Transactions!$D:$D,"Sale"),0) -> 0 | AF8: =IFERROR(SUMIFS(Transactions!$H:$H,Transactions!$C:$C,$A8,Transactions!$D:$D,"Sale"),0) -> 0 | AG8: =IFERROR(IF(maxifs(Transactions!$B:$B,Transactions!$C:$C,$A8,Transactions!$D:$D,"Sale")=0,"",maxifs(Transactions!$B:$B,Transactions!$C:$C,$A8,Transactions!$D:$D,"Sale")),"")
A9: KARNI-PEND-ALPHA-GIM-RED | B9: DSGN-PEND-ALPHA-GIM | C9: Bird Letter Pendant | D9: Pendant | E9: Alphabet | F9: Գ | H9: red | I9: 19000 | J9: =IF($I9="","",ROUND($I9*Dropdowns!$K$5,2)) -> 49.4 | K9: =IF($I9="","",ROUND($I9*Dropdowns!$K$6,2)) -> 45.6 | L9: =IF($I9="","",ROUND($I9*Dropdowns!$K$7,2)) -> 3895 | M9: =IFERROR(IF($B9="","",VLOOKUP($B9,Designs!$A$3:$AP$165,27,FALSE())),"") | N9: =IFERROR(IF(OR($I9="",$M9="",$M9=0),"",($I9-$M9)/$I9),"") | O9: 0 | P9: 0 | Q9: =IF($O9="","",$O9-IF($P9="",0,$P9)) -> 0 | R9: 2 | S9: =IF($O9="","",IF($Q9<=$R9,"⚠ REORDER","OK")) -> ⚠ REORDER | V9: 7117.19 | W9: Armenia | Z9: No | AA9: No | AB9: No | AC9: No | AD9: Active | AE9: =IFERROR(SUMIFS(Transactions!$F:$F,Transactions!$C:$C,$A9,Transactions!$D:$D,"Sale"),0) -> 0 | AF9: =IFERROR(SUMIFS(Transactions!$H:$H,Transactions!$C:$C,$A9,Transactions!$D:$D,"Sale"),0) -> 0 | AG9: =IFERROR(IF(maxifs(Transactions!$B:$B,Transactions!$C:$C,$A9,Transactions!$D:$D,"Sale")=0,"",maxifs(Transactions!$B:$B,Transactions!$C:$C,$A9,Transactions!$D:$D,"Sale")),"")
A10: KARNI-PEND-ALPHA-GIM-TURQUOISE | B10: DSGN-PEND-ALPHA-GIM | C10: Bird Letter Pendant | D10: Pendant | E10: Alphabet | F10: Գ | H10: turquoise | I10: 19000 | J10: =IF($I10="","",ROUND($I10*Dropdowns!$K$5,2)) -> 49.4 | K10: =IF($I10="","",ROUND($I10*Dropdowns!$K$6,2)) -> 45.6 | L10: =IF($I10="","",ROUND($I10*Dropdowns!$K$7,2)) -> 3895 | M10: =IFERROR(IF($B10="","",VLOOKUP($B10,Designs!$A$3:$AP$165,27,FALSE())),"") | N10: =IFERROR(IF(OR($I10="",$M10="",$M10=0),"",($I10-$M10)/$I10),"") | O10: 0 | P10: 0 | Q10: =IF($O10="","",$O10-IF($P10="",0,$P10)) -> 0 | R10: 2 | S10: =IF($O10="","",IF($Q10<=$R10,"⚠ REORDER","OK")) -> ⚠ REORDER | V10: 7117.19 | W10: Armenia | Z10: No | AA10: No | AB10: No | AC10: No | AD10: Active | AE10: =IFERROR(SUMIFS(Transactions!$F:$F,Transactions!$C:$C,$A10,Transactions!$D:$D,"Sale"),0) -> 0 | AF10: =IFERROR(SUMIFS(Transactions!$H:$H,Transactions!$C:$C,$A10,Transactions!$D:$D,"Sale"),0) -> 0 | AG10: =IFERROR(IF(maxifs(Transactions!$B:$B,Transactions!$C:$C,$A10,Transactions!$D:$D,"Sale")=0,"",maxifs(Transactions!$B:$B,Transactions!$C:$C,$A10,Transactions!$D:$D,"Sale")),"")
A11: KARNI-PEND-ALPHA-GIM-WHITE | B11: DSGN-PEND-ALPHA-GIM | C11: Bird Letter Pendant | D11: Pendant | E11: Alphabet | F11: Գ | H11: white | I11: 19000 | J11: =IF($I11="","",ROUND($I11*Dropdowns!$K$5,2)) -> 49.4 | K11: =IF($I11="","",ROUND($I11*Dropdowns!$K$6,2)) -> 45.6 | L11: =IF($I11="","",ROUND($I11*Dropdowns!$K$7,2)) -> 3895 | M11: =IFERROR(IF($B11="","",VLOOKUP($B11,Designs!$A$3:$AP$165,27,FALSE())),"") | N11: =IFERROR(IF(OR($I11="",$M11="",$M11=0),"",($I11-$M11)/$I11),"") | O11: 0 | P11: 0 | Q11: =IF($O11="","",$O11-IF($P11="",0,$P11)) -> 0 | R11: 2 | S11: =IF($O11="","",IF($Q11<=$R11,"⚠ REORDER","OK")) -> ⚠ REORDER | V11: 7117.19 | W11: Armenia | Z11: No | AA11: No | AB11: No | AC11: No | AD11: Active | AE11: =IFERROR(SUMIFS(Transactions!$F:$F,Transactions!$C:$C,$A11,Transactions!$D:$D,"Sale"),0) -> 0 | AF11: =IFERROR(SUMIFS(Transactions!$H:$H,Transactions!$C:$C,$A11,Transactions!$D:$D,"Sale"),0) -> 0 | AG11: =IFERROR(IF(maxifs(Transactions!$B:$B,Transactions!$C:$C,$A11,Transactions!$D:$D,"Sale")=0,"",maxifs(Transactions!$B:$B,Transactions!$C:$C,$A11,Transactions!$D:$D,"Sale")),"")
A12: KARNI-PEND-ALPHA-DA-RED | B12: DSGN-PEND-ALPHA-DA | C12: Bird Letter Pendant | D12: Pendant | E12: Alphabet | F12: Դ | H12: red | I12: 19000 | J12: =IF($I12="","",ROUND($I12*Dropdowns!$K$5,2)) -> 49.4 | K12: =IF($I12="","",ROUND($I12*Dropdowns!$K$6,2)) -> 45.6 | L12: =IF($I12="","",ROUND($I12*Dropdowns!$K$7,2)) -> 3895 | M12: =IFERROR(IF($B12="","",VLOOKUP($B12,Designs!$A$3:$AP$165,27,FALSE())),"") | N12: =IFERROR(IF(OR($I12="",$M12="",$M12=0),"",($I12-$M12)/$I12),"") | O12: 0 | P12: 0 | Q12: =IF($O12="","",$O12-IF($P12="",0,$P12)) -> 0 | R12: 2 | S12: =IF($O12="","",IF($Q12<=$R12,"⚠ REORDER","OK")) -> ⚠ REORDER | V12: 7117.19 | W12: Armenia | Z12: No | AA12: No | AB12: No | AC12: No | AD12: Active | AE12: =IFERROR(SUMIFS(Transactions!$F:$F,Transactions!$C:$C,$A12,Transactions!$D:$D,"Sale"),0) -> 0 | AF12: =IFERROR(SUMIFS(Transactions!$H:$H,Transactions!$C:$C,$A12,Transactions!$D:$D,"Sale"),0) -> 0 | AG12: =IFERROR(IF(maxifs(Transactions!$B:$B,Transactions!$C:$C,$A12,Transactions!$D:$D,"Sale")=0,"",maxifs(Transactions!$B:$B,Transactions!$C:$C,$A12,Transactions!$D:$D,"Sale")),"")
A13: KARNI-PEND-ALPHA-DA-TURQUOISE | B13: DSGN-PEND-ALPHA-DA | C13: Bird Letter Pendant | D13: Pendant | E13: Alphabet | F13: Դ | H13: turquoise | I13: 19000 | J13: =IF($I13="","",ROUND($I13*Dropdowns!$K$5,2)) -> 49.4 | K13: =IF($I13="","",ROUND($I13*Dropdowns!$K$6,2)) -> 45.6 | L13: =IF($I13="","",ROUND($I13*Dropdowns!$K$7,2)) -> 3895 | M13: =IFERROR(IF($B13="","",VLOOKUP($B13,Designs!$A$3:$AP$165,27,FALSE())),"") | N13: =IFERROR(IF(OR($I13="",$M13="",$M13=0),"",($I13-$M13)/$I13),"") | O13: 0 | P13: 0 | Q13: =IF($O13="","",$O13-IF($P13="",0,$P13)) -> 0 | R13: 2 | S13: =IF($O13="","",IF($Q13<=$R13,"⚠ REORDER","OK")) -> ⚠ REORDER | V13: 7117.19 | W13: Armenia | Z13: No | AA13: No | AB13: No | AC13: No | AD13: Active | AE13: =IFERROR(SUMIFS(Transactions!$F:$F,Transactions!$C:$C,$A13,Transactions!$D:$D,"Sale"),0) -> 0 | AF13: =IFERROR(SUMIFS(Transactions!$H:$H,Transactions!$C:$C,$A13,Transactions!$D:$D,"Sale"),0) -> 0 | AG13: =IFERROR(IF(maxifs(Transactions!$B:$B,Transactions!$C:$C,$A13,Transactions!$D:$D,"Sale")=0,"",maxifs(Transactions!$B:$B,Transactions!$C:$C,$A13,Transactions!$D:$D,"Sale")),"")
A14: KARNI-PEND-ALPHA-DA-WHITE | B14: DSGN-PEND-ALPHA-DA | C14: Bird Letter Pendant | D14: Pendant | E14: Alphabet | F14: Դ | H14: white | I14: 19000 | J14: =IF($I14="","",ROUND($I14*Dropdowns!$K$5,2)) -> 49.4 | K14: =IF($I14="","",ROUND($I14*Dropdowns!$K$6,2)) -> 45.6 | L14: =IF($I14="","",ROUND($I14*Dropdowns!$K$7,2)) -> 3895 | M14: =IFERROR(IF($B14="","",VLOOKUP($B14,Designs!$A$3:$AP$165,27,FALSE())),"") | N14: =IFERROR(IF(OR($I14="",$M14="",$M14=0),"",($I14-$M14)/$I14),"") | O14: 0 | P14: 0 | Q14: =IF($O14="","",$O14-IF($P14="",0,$P14)) -> 0 | R14: 2 | S14: =IF($O14="","",IF($Q14<=$R14,"⚠ REORDER","OK")) -> ⚠ REORDER | V14: 7117.19 | W14: Armenia | Z14: No | AA14: No | AB14: No | AC14: No | AD14: Active | AE14: =IFERROR(SUMIFS(Transactions!$F:$F,Transactions!$C:$C,$A14,Transactions!$D:$D,"Sale"),0) -> 0 | AF14: =IFERROR(SUMIFS(Transactions!$H:$H,Transactions!$C:$C,$A14,Transactions!$D:$D,"Sale"),0) -> 0 | AG14: =IFERROR(IF(maxifs(Transactions!$B:$B,Transactions!$C:$C,$A14,Transactions!$D:$D,"Sale")=0,"",maxifs(Transactions!$B:$B,Transactions!$C:$C,$A14,Transactions!$D:$D,"Sale")),"")
... A268: KARNI-BRCH-ALPHA-FEH-TURQUOISE | B268: DSGN-BRCH-ALPHA-FEH | C268: Bird Letter Brooch | D268: Brooch | E268: Alphabet | F268: Ֆ | H268: turquoise | I268: 25000 | J268: =IF($I268="","",ROUND($I268*Dropdowns!$K$5,2)) -> 65 | K268: =IF($I268="","",ROUND($I268*Dropdowns!$K$6,2)) -> 60 | L268: =IF($I268="","",ROUND($I268*Dropdowns!$K$7,2)) -> 5125 | M268: =IFERROR(IF($B268="","",VLOOKUP($B268,Designs!$A$3:$AP$165,27,FALSE())),"") | N268: =IFERROR(IF(OR($I268="",$M268="",$M268=0),"",($I268-$M268)/$I268),"") | O268: 0 | P268: 0 | Q268: =IF($O268="","",$O268-IF($P268="",0,$P268)) -> 0 | R268: 2 | S268: =IF($O268="","",IF($Q268<=$R268,"⚠ REORDER","OK")) -> ⚠ REORDER | V268: 7117.19 | W268: Armenia | Z268: No | AA268: No | AB268: No | AC268: No | AD268: Active | AE268: =IFERROR(SUMIFS(Transactions!$F:$F,Transactions!$C:$C,$A268,Transactions!$D:$D,"Sale"),0) -> 0 | AF268: =IFERROR(SUMIFS(Transactions!$H:$H,Transactions!$C:$C,$A268,Transactions!$D:$D,"Sale"),0) -> 0 | AG268: =IFERROR(IF(maxifs(Transactions!$B:$B,Transactions!$C:$C,$A268,Transactions!$D:$D,"Sale")=0,"",maxifs(Transactions!$B:$B,Transactions!$C:$C,$A268,Transactions!$D:$D,"Sale")),"")
A269: KARNI-EARRNG-MARASH-S-BLUE | B269: DSGN-EARRNG-MARASH-S | C269: Marash Earrings | D269: Earring | E269: Marash | G269: small | H269: blue | I269: 13000 | J269: =IF($I269="","",ROUND($I269*Dropdowns!$K$5,2)) -> 33.8 | K269: =IF($I269="","",ROUND($I269*Dropdowns!$K$6,2)) -> 31.2 | L269: =IF($I269="","",ROUND($I269*Dropdowns!$K$7,2)) -> 2665 | M269: =IFERROR(IF($B269="","",VLOOKUP($B269,Designs!$A$3:$AP$165,27,FALSE())),"") | N269: =IFERROR(IF(OR($I269="",$M269="",$M269=0),"",($I269-$M269)/$I269),"") | O269: 0 | P269: 0 | Q269: =IF($O269="","",$O269-IF($P269="",0,$P269)) -> 0 | R269: 2 | S269: =IF($O269="","",IF($Q269<=$R269,"⚠ REORDER","OK")) -> ⚠ REORDER | V269: 7117.19 | W269: Armenia | Z269: No | AA269: No | AB269: No | AC269: No | AD269: Active | AE269: =IFERROR(SUMIFS(Transactions!$F:$F,Transactions!$C:$C,$A269,Transactions!$D:$D,"Sale"),0) -> 0 | AF269: =IFERROR(SUMIFS(Transactions!$H:$H,Transactions!$C:$C,$A269,Transactions!$D:$D,"Sale"),0) -> 0 | AG269: =IFERROR(IF(maxifs(Transactions!$B:$B,Transactions!$C:$C,$A269,Transactions!$D:$D,"Sale")=0,"",maxifs(Transactions!$B:$B,Transactions!$C:$C,$A269,Transactions!$D:$D,"Sale")),"")
A270: KARNI-EARRNG-MARASH-S-WHITE | B270: DSGN-EARRNG-MARASH-S | C270: Marash Earrings | D270: Earring | E270: Marash | G270: small | H270: white | I270: 13000 | J270: =IF($I270="","",ROUND($I270*Dropdowns!$K$5,2)) -> 33.8 | K270: =IF($I270="","",ROUND($I270*Dropdowns!$K$6,2)) -> 31.2 | L270: =IF($I270="","",ROUND($I270*Dropdowns!$K$7,2)) -> 2665 | M270: =IFERROR(IF($B270="","",VLOOKUP($B270,Designs!$A$3:$AP$165,27,FALSE())),"") | N270: =IFERROR(IF(OR($I270="",$M270="",$M270=0),"",($I270-$M270)/$I270),"") | O270: 0 | P270: 0 | Q270: =IF($O270="","",$O270-IF($P270="",0,$P270)) -> 0 | R270: 2 | S270: =IF($O270="","",IF($Q270<=$R270,"⚠ REORDER","OK")) -> ⚠ REORDER | V270: 7117.19 | W270: Armenia | Z270: No | AA270: No | AB270: No | AC270: No | AD270: Active | AE270: =IFERROR(SUMIFS(Transactions!$F:$F,Transactions!$C:$C,$A270,Transactions!$D:$D,"Sale"),0) -> 0 | AF270: =IFERROR(SUMIFS(Transactions!$H:$H,Transactions!$C:$C,$A270,Transactions!$D:$D,"Sale"),0) -> 0 | AG270: =IFERROR(IF(maxifs(Transactions!$B:$B,Transactions!$C:$C,$A270,Transactions!$D:$D,"Sale")=0,"",maxifs(Transactions!$B:$B,Transactions!$C:$C,$A270,Transactions!$D:$D,"Sale")),"")
A271: KARNI-EARRNG-MARASH-S-BORDEAUX | B271: DSGN-EARRNG-MARASH-S | C271: Marash Earrings | D271: Earring | E271: Marash | G271: small | H271: bordeaux | I271: 13000 | J271: =IF($I271="","",ROUND($I271*Dropdowns!$K$5,2)) -> 33.8 | K271: =IF($I271="","",ROUND($I271*Dropdowns!$K$6,2)) -> 31.2 | L271: =IF($I271="","",ROUND($I271*Dropdowns!$K$7,2)) -> 2665 | M271: =IFERROR(IF($B271="","",VLOOKUP($B271,Designs!$A$3:$AP$165,27,FALSE())),"") | N271: =IFERROR(IF(OR($I271="",$M271="",$M271=0),"",($I271-$M271)/$I271),"") | O271: 0 | P271: 0 | Q271: =IF($O271="","",$O271-IF($P271="",0,$P271)) -> 0 | R271: 2 | S271: =IF($O271="","",IF($Q271<=$R271,"⚠ REORDER","OK")) -> ⚠ REORDER | V271: 7117.19 | W271: Armenia | Z271: No | AA271: No | AB271: No | AC271: No | AD271: Active | AE271: =IFERROR(SUMIFS(Transactions!$F:$F,Transactions!$C:$C,$A271,Transactions!$D:$D,"Sale"),0) -> 0 | AF271: =IFERROR(SUMIFS(Transactions!$H:$H,Transactions!$C:$C,$A271,Transactions!$D:$D,"Sale"),0) -> 0 | AG271: =IFERROR(IF(maxifs(Transactions!$B:$B,Transactions!$C:$C,$A271,Transactions!$D:$D,"Sale")=0,"",maxifs(Transactions!$B:$B,Transactions!$C:$C,$A271,Transactions!$D:$D,"Sale")),"")
A272: KARNI-EARRNG-MARASH-S-TURQUOISE | B272: DSGN-EARRNG-MARASH-S | C272: Marash Earrings | D272: Earring | E272: Marash | G272: small | H272: turquoise | I272: 13000 | J272: =IF($I272="","",ROUND($I272*Dropdowns!$K$5,2)) -> 33.8 | K272: =IF($I272="","",ROUND($I272*Dropdowns!$K$6,2)) -> 31.2 | L272: =IF($I272="","",ROUND($I272*Dropdowns!$K$7,2)) -> 2665 | M272: =IFERROR(IF($B272="","",VLOOKUP($B272,Designs!$A$3:$AP$165,27,FALSE())),"") | N272: =IFERROR(IF(OR($I272="",$M272="",$M272=0),"",($I272-$M272)/$I272),"") | O272: 0 | P272: 0 | Q272: =IF($O272="","",$O272-IF($P272="",0,$P272)) -> 0 | R272: 2 | S272: =IF($O272="","",IF($Q272<=$R272,"⚠ REORDER","OK")) -> ⚠ REORDER | V272: 7117.19 | W272: Armenia | Z272: No | AA272: No | AB272: No | AC272: No | AD272: Active | AE272: =IFERROR(SUMIFS(Transactions!$F:$F,Transactions!$C:$C,$A272,Transactions!$D:$D,"Sale"),0) -> 0 | AF272: =IFERROR(SUMIFS(Transactions!$H:$H,Transactions!$C:$C,$A272,Transactions!$D:$D,"Sale"),0) -> 0 | AG272: =IFERROR(IF(maxifs(Transactions!$B:$B,Transactions!$C:$C,$A272,Transactions!$D:$D,"Sale")=0,"",maxifs(Transactions!$B:$B,Transactions!$C:$C,$A272,Transactions!$D:$D,"Sale")),"")
A273: KARNI-EARRNG-MARASH-S-GREEN | B273: DSGN-EARRNG-MARASH-S | C273: Marash Earrings | D273: Earring | E273: Marash | G273: small | H273: green | I273: 13000 | J273: =IF($I273="","",ROUND($I273*Dropdowns!$K$5,2)) -> 33.8 | K273: =IF($I273="","",ROUND($I273*Dropdowns!$K$6,2)) -> 31.2 | L273: =IF($I273="","",ROUND($I273*Dropdowns!$K$7,2)) -> 2665 | M273: =IFERROR(IF($B273="","",VLOOKUP($B273,Designs!$A$3:$AP$165,27,FALSE())),"") | N273: =IFERROR(IF(OR($I273="",$M273="",$M273=0),"",($I273-$M273)/$I273),"") | O273: 0 | P273: 0 | Q273: =IF($O273="","",$O273-IF($P273="",0,$P273)) -> 0 | R273: 2 | S273: =IF($O273="","",IF($Q273<=$R273,"⚠ REORDER","OK")) -> ⚠ REORDER | V273: 7117.19 | W273: Armenia | Z273: No | AA273: No | AB273: No | AC273: No | AD273: Active | AE273: =IFERROR(SUMIFS(Transactions!$F:$F,Transactions!$C:$C,$A273,Transactions!$D:$D,"Sale"),0) -> 0 | AF273: =IFERROR(SUMIFS(Transactions!$H:$H,Transactions!$C:$C,$A273,Transactions!$D:$D,"Sale"),0) -> 0 | AG273: =IFERROR(IF(maxifs(Transactions!$B:$B,Transactions!$C:$C,$A273,Transactions!$D:$D,"Sale")=0,"",maxifs(Transactions!$B:$B,Transactions!$C:$C,$A273,Transactions!$D:$D,"Sale")),"")
A274: KARNI-EARRNG-MARASH-M-BLUE-WHITE | B274: DSGN-EARRNG-MARASH-M | C274: Marash Earrings | D274: Earring | E274: Marash | G274: medium | H274: blue-white | I274: 27000 | J274: =IF($I274="","",ROUND($I274*Dropdowns!$K$5,2)) -> 70.2 | K274: =IF($I274="","",ROUND($I274*Dropdowns!$K$6,2)) -> 64.8 | L274: =IF($I274="","",ROUND($I274*Dropdowns!$K$7,2)) -> 5535 | M274: =IFERROR(IF($B274="","",VLOOKUP($B274,Designs!$A$3:$AP$165,27,FALSE())),"") | N274: =IFERROR(IF(OR($I274="",$M274="",$M274=0),"",($I274-$M274)/$I274),"") | O274: 0 | P274: 0 | Q274: =IF($O274="","",$O274-IF($P274="",0,$P274)) -> 0 | R274: 2 | S274: =IF($O274="","",IF($Q274<=$R274,"⚠ REORDER","OK")) -> ⚠ REORDER | V274: 7117.19 | W274: Armenia | Z274: No | AA274: No | AB274: No | AC274: No | AD274: Active | AE274: =IFERROR(SUMIFS(Transactions!$F:$F,Transactions!$C:$C,$A274,Transactions!$D:$D,"Sale"),0) -> 0 | AF274: =IFERROR(SUMIFS(Transactions!$H:$H,Transactions!$C:$C,$A274,Transactions!$D:$D,"Sale"),0) -> 0 | AG274: =IFERROR(IF(maxifs(Transactions!$B:$B,Transactions!$C:$C,$A274,Transactions!$D:$D,"Sale")=0,"",maxifs(Transactions!$B:$B,Transactions!$C:$C,$A274,Transactions!$D:$D,"Sale")),"")
A275: KARNI-EARRNG-MARASH-M-WHITE-BLUE | B275: DSGN-EARRNG-MARASH-M | C275: Marash Earrings | D275: Earring | E275: Marash | G275: medium | H275: white-blue | I275: 27000 | J275: =IF($I275="","",ROUND($I275*Dropdowns!$K$5,2)) -> 70.2 | K275: =IF($I275="","",ROUND($I275*Dropdowns!$K$6,2)) -> 64.8 | L275: =IF($I275="","",ROUND($I275*Dropdowns!$K$7,2)) -> 5535 | M275: =IFERROR(IF($B275="","",VLOOKUP($B275,Designs!$A$3:$AP$165,27,FALSE())),"") | N275: =IFERROR(IF(OR($I275="",$M275="",$M275=0),"",($I275-$M275)/$I275),"") | O275: 0 | P275: 0 | Q275: =IF($O275="","",$O275-IF($P275="",0,$P275)) -> 0 | R275: 2 | S275: =IF($O275="","",IF($Q275<=$R275,"⚠ REORDER","OK")) -> ⚠ REORDER | V275: 7117.19 | W275: Armenia | Z275: No | AA275: No | AB275: No | AC275: No | AD275: Active | AE275: =IFERROR(SUMIFS(Transactions!$F:$F,Transactions!$C:$C,$A275,Transactions!$D:$D,"Sale"),0) -> 0 | AF275: =IFERROR(SUMIFS(Transactions!$H:$H,Transactions!$C:$C,$A275,Transactions!$D:$D,"Sale"),0) -> 0 | AG275: =IFERROR(IF(maxifs(Transactions!$B:$B,Transactions!$C:$C,$A275,Transactions!$D:$D,"Sale")=0,"",maxifs(Transactions!$B:$B,Transactions!$C:$C,$A275,Transactions!$D:$D,"Sale")),"")
A276: KARNI-EARRNG-MARASH-M-WHITE-BORDEAUX | B276: DSGN-EARRNG-MARASH-M | C276: Marash Earrings | D276: Earring | E276: Marash | G276: medium | H276: white-bordeaux | I276: 27000 | J276: =IF($I276="","",ROUND($I276*Dropdowns!$K$5,2)) -> 70.2 | K276: =IF($I276="","",ROUND($I276*Dropdowns!$K$6,2)) -> 64.8 | L276: =IF($I276="","",ROUND($I276*Dropdowns!$K$7,2)) -> 5535 | M276: =IFERROR(IF($B276="","",VLOOKUP($B276,Designs!$A$3:$AP$165,27,FALSE())),"") | N276: =IFERROR(IF(OR($I276="",$M276="",$M276=0),"",($I276-$M276)/$I276),"") | O276: 0 | P276: 0 | Q276: =IF($O276="","",$O276-IF($P276="",0,$P276)) -> 0 | R276: 2 | S276: =IF($O276="","",IF($Q276<=$R276,"⚠ REORDER","OK")) -> ⚠ REORDER | V276: 7117.19 | W276: Armenia | Z276: No | AA276: No | AB276: No | AC276: No | AD276: Active | AE276: =IFERROR(SUMIFS(Transactions!$F:$F,Transactions!$C:$C,$A276,Transactions!$D:$D,"Sale"),0) -> 0 | AF276: =IFERROR(SUMIFS(Transactions!$H:$H,Transactions!$C:$C,$A276,Transactions!$D:$D,"Sale"),0) -> 0 | AG276: =IFERROR(IF(maxifs(Transactions!$B:$B,Transactions!$C:$C,$A276,Transactions!$D:$D,"Sale")=0,"",maxifs(Transactions!$B:$B,Transactions!$C:$C,$A276,Transactions!$D:$D,"Sale")),"")
A277: KARNI-EARRNG-MARASH-M-TURQUOISE-BLUE | B277: DSGN-EARRNG-MARASH-M | C277: Marash Earrings | D277: Earring | E277: Marash | G277: medium | H277: turquoise-blue | I277: 27000 | J277: =IF($I277="","",ROUND($I277*Dropdowns!$K$5,2)) -> 70.2 | K277: =IF($I277="","",ROUND($I277*Dropdowns!$K$6,2)) -> 64.8 | L277: =IF($I277="","",ROUND($I277*Dropdowns!$K$7,2)) -> 5535 | M277: =IFERROR(IF($B277="","",VLOOKUP($B277,Designs!$A$3:$AP$165,27,FALSE())),"") | N277: =IFERROR(IF(OR($I277="",$M277="",$M277=0),"",($I277-$M277)/$I277),"") | O277: 0 | P277: 0 | Q277: =IF($O277="","",$O277-IF($P277="",0,$P277)) -> 0 | R277: 2 | S277: =IF($O277="","",IF($Q277<=$R277,"⚠ REORDER","OK")) -> ⚠ REORDER | V277: 7117.19 | W277: Armenia | Z277: No | AA277: No | AB277: No | AC277: No | AD277: Active | AE277: =IFERROR(SUMIFS(Transactions!$F:$F,Transactions!$C:$C,$A277,Transactions!$D:$D,"Sale"),0) -> 0 | AF277: =IFERROR(SUMIFS(Transactions!$H:$H,Transactions!$C:$C,$A277,Transactions!$D:$D,"Sale"),0) -> 0 | AG277: =IFERROR(IF(maxifs(Transactions!$B:$B,Transactions!$C:$C,$A277,Transactions!$D:$D,"Sale")=0,"",maxifs(Transactions!$B:$B,Transactions!$C:$C,$A277,Transactions!$D:$D,"Sale")),"")
A278: KARNI-EARRNG-VAN-S-BLUE | B278: DSGN-EARRNG-VAN-S | C278: Van Earrings | D278: Earring | E278: Van | G278: small | H278: blue | I278: 13000 | J278: =IF($I278="","",ROUND($I278*Dropdowns!$K$5,2)) -> 33.8 | K278: =IF($I278="","",ROUND($I278*Dropdowns!$K$6,2)) -> 31.2 | L278: =IF($I278="","",ROUND($I278*Dropdowns!$K$7,2)) -> 2665 | M278: =IFERROR(IF($B278="","",VLOOKUP($B278,Designs!$A$3:$AP$165,27,FALSE())),"") | N278: =IFERROR(IF(OR($I278="",$M278="",$M278=0),"",($I278-$M278)/$I278),"") | O278: 0 | P278: 0 | Q278: =IF($O278="","",$O278-IF($P278="",0,$P278)) -> 0 | R278: 2 | S278: =IF($O278="","",IF($Q278<=$R278,"⚠ REORDER","OK")) -> ⚠ REORDER | V278: 7117.19 | W278: Armenia | Z278: No | AA278: No | AB278: No | AC278: No | AD278: Active | AE278: =IFERROR(SUMIFS(Transactions!$F:$F,Transactions!$C:$C,$A278,Transactions!$D:$D,"Sale"),0) -> 0 | AF278: =IFERROR(SUMIFS(Transactions!$H:$H,Transactions!$C:$C,$A278,Transactions!$D:$D,"Sale"),0) -> 0 | AG278: =IFERROR(IF(maxifs(Transactions!$B:$B,Transactions!$C:$C,$A278,Transactions!$D:$D,"Sale")=0,"",maxifs(Transactions!$B:$B,Transactions!$C:$C,$A278,Transactions!$D:$D,"Sale")),"")
A279: KARNI-EARRNG-VAN-S-WHITE | B279: DSGN-EARRNG-VAN-S | C279: Van Earrings | D279: Earring | E279: Van | G279: small | H279: white | I279: 13000 | J279: =IF($I279="","",ROUND($I279*Dropdowns!$K$5,2)) -> 33.8 | K279: =IF($I279="","",ROUND($I279*Dropdowns!$K$6,2)) -> 31.2 | L279: =IF($I279="","",ROUND($I279*Dropdowns!$K$7,2)) -> 2665 | M279: =IFERROR(IF($B279="","",VLOOKUP($B279,Designs!$A$3:$AP$165,27,FALSE())),"") | N279: =IFERROR(IF(OR($I279="",$M279="",$M279=0),"",($I279-$M279)/$I279),"") | O279: 0 | P279: 0 | Q279: =IF($O279="","",$O279-IF($P279="",0,$P279)) -> 0 | R279: 2 | S279: =IF($O279="","",IF($Q279<=$R279,"⚠ REORDER","OK")) -> ⚠ REORDER | V279: 7117.19 | W279: Armenia | Z279: No | AA279: No | AB279: No | AC279: No | AD279: Active | AE279: =IFERROR(SUMIFS(Transactions!$F:$F,Transactions!$C:$C,$A279,Transactions!$D:$D,"Sale"),0) -> 0 | AF279: =IFERROR(SUMIFS(Transactions!$H:$H,Transactions!$C:$C,$A279,Transactions!$D:$D,"Sale"),0) -> 0 | AG279: =IFERROR(IF(maxifs(Transactions!$B:$B,Transactions!$C:$C,$A279,Transactions!$D:$D,"Sale")=0,"",maxifs(Transactions!$B:$B,Transactions!$C:$C,$A279,Transactions!$D:$D,"Sale")),"")
A280: KARNI-EARRNG-VAN-S-BORDEAUX | B280: DSGN-EARRNG-VAN-S | C280: Van Earrings | D280: Earring | E280: Van | G280: small | H280: bordeaux | I280: 13000 | J280: =IF($I280="","",ROUND($I280*Dropdowns!$K$5,2)) -> 33.8 | K280: =IF($I280="","",ROUND($I280*Dropdowns!$K$6,2)) -> 31.2 | L280: =IF($I280="","",ROUND($I280*Dropdowns!$K$7,2)) -> 2665 | M280: =IFERROR(IF($B280="","",VLOOKUP($B280,Designs!$A$3:$AP$165,27,FALSE())),"") | N280: =IFERROR(IF(OR($I280="",$M280="",$M280=0),"",($I280-$M280)/$I280),"") | O280: 0 | P280: 0 | Q280: =IF($O280="","",$O280-IF($P280="",0,$P280)) -> 0 | R280: 2 | S280: =IF($O280="","",IF($Q280<=$R280,"⚠ REORDER","OK")) -> ⚠ REORDER | V280: 7117.19 | W280: Armenia | Z280: No | AA280: No | AB280: No | AC280: No | AD280: Active | AE280: =IFERROR(SUMIFS(Transactions!$F:$F,Transactions!$C:$C,$A280,Transactions!$D:$D,"Sale"),0) -> 0 | AF280: =IFERROR(SUMIFS(Transactions!$H:$H,Transactions!$C:$C,$A280,Transactions!$D:$D,"Sale"),0) -> 0 | AG280: =IFERROR(IF(maxifs(Transactions!$B:$B,Transactions!$C:$C,$A280,Transactions!$D:$D,"Sale")=0,"",maxifs(Transactions!$B:$B,Transactions!$C:$C,$A280,Transactions!$D:$D,"Sale")),"")
... A314: KARNI-EARRNG-VISHABAREVAGORG-M-WHITE-BLUE-RED | B314: DSGN-EARRNG-VISHABAREVAGORG-M | C314: Արեւագորգի Վիշապ | D314: Earring | E314: Vishab Arevagorg | G314: medium | H314: white-blue-red | I314: 27000 | J314: =IF($I314="","",ROUND($I314*Dropdowns!$K$5,2)) -> 70.2 | K314: =IF($I314="","",ROUND($I314*Dropdowns!$K$6,2)) -> 64.8 | L314: =IF($I314="","",ROUND($I314*Dropdowns!$K$7,2)) -> 5535 | M314: =IFERROR(IF($B314="","",VLOOKUP($B314,Designs!$A$3:$AP$165,27,FALSE())),"") | N314: =IFERROR(IF(OR($I314="",$M314="",$M314=0),"",($I314-$M314)/$I314),"") | O314: 0 | P314: 0 | Q314: =IF($O314="","",$O314-IF($P314="",0,$P314)) -> 0 | R314: 2 | S314: =IF($O314="","",IF($Q314<=$R314,"⚠ REORDER","OK")) -> ⚠ REORDER | V314: 7117.19 | W314: Armenia | Z314: No | AA314: No | AB314: No | AC314: No | AD314: Active | AE314: =IFERROR(SUMIFS(Transactions!$F:$F,Transactions!$C:$C,$A314,Transactions!$D:$D,"Sale"),0) -> 0 | AF314: =IFERROR(SUMIFS(Transactions!$H:$H,Transactions!$C:$C,$A314,Transactions!$D:$D,"Sale"),0) -> 0 | AG314: =IFERROR(IF(maxifs(Transactions!$B:$B,Transactions!$C:$C,$A314,Transactions!$D:$D,"Sale")=0,"",maxifs(Transactions!$B:$B,Transactions!$C:$C,$A314,Transactions!$D:$D,"Sale")),"")
A315: KARNI-EARRNG2-MARASH-BLUE-WHITE | B315: DSGN-EARRNG2-MARASH | C315: Marash Earrings (2 pcs) | D315: earrings 2 pcs. | E315: Marash | H315: blue-white | I315: 36000 | J315: =IF($I315="","",ROUND($I315*Dropdowns!$K$5,2)) -> 93.6 | K315: =IF($I315="","",ROUND($I315*Dropdowns!$K$6,2)) -> 86.4 | L315: =IF($I315="","",ROUND($I315*Dropdowns!$K$7,2)) -> 7380 | M315: =IFERROR(IF($B315="","",VLOOKUP($B315,Designs!$A$3:$AP$165,27,FALSE())),"") | N315: =IFERROR(IF(OR($I315="",$M315="",$M315=0),"",($I315-$M315)/$I315),"") | O315: 0 | P315: 0 | Q315: =IF($O315="","",$O315-IF($P315="",0,$P315)) -> 0 | R315: 2 | S315: =IF($O315="","",IF($Q315<=$R315,"⚠ REORDER","OK")) -> ⚠ REORDER | V315: 7117.19 | W315: Armenia | Z315: No | AA315: No | AB315: No | AC315: No | AD315: Active | AE315: =IFERROR(SUMIFS(Transactions!$F:$F,Transactions!$C:$C,$A315,Transactions!$D:$D,"Sale"),0) -> 0 | AF315: =IFERROR(SUMIFS(Transactions!$H:$H,Transactions!$C:$C,$A315,Transactions!$D:$D,"Sale"),0) -> 0 | AG315: =IFERROR(IF(maxifs(Transactions!$B:$B,Transactions!$C:$C,$A315,Transactions!$D:$D,"Sale")=0,"",maxifs(Transactions!$B:$B,Transactions!$C:$C,$A315,Transactions!$D:$D,"Sale")),"")
A316: KARNI-EARRNG2-MARASH-WHITE-BLUE | B316: DSGN-EARRNG2-MARASH | C316: Marash Earrings (2 pcs) | D316: earrings 2 pcs. | E316: Marash | H316: white-blue | I316: 36000 | J316: =IF($I316="","",ROUND($I316*Dropdowns!$K$5,2)) -> 93.6 | K316: =IF($I316="","",ROUND($I316*Dropdowns!$K$6,2)) -> 86.4 | L316: =IF($I316="","",ROUND($I316*Dropdowns!$K$7,2)) -> 7380 | M316: =IFERROR(IF($B316="","",VLOOKUP($B316,Designs!$A$3:$AP$165,27,FALSE())),"") | N316: =IFERROR(IF(OR($I316="",$M316="",$M316=0),"",($I316-$M316)/$I316),"") | O316: 0 | P316: 0 | Q316: =IF($O316="","",$O316-IF($P316="",0,$P316)) -> 0 | R316: 2 | S316: =IF($O316="","",IF($Q316<=$R316,"⚠ REORDER","OK")) -> ⚠ REORDER | V316: 7117.19 | W316: Armenia | Z316: No | AA316: No | AB316: No | AC316: No | AD316: Active | AE316: =IFERROR(SUMIFS(Transactions!$F:$F,Transactions!$C:$C,$A316,Transactions!$D:$D,"Sale"),0) -> 0 | AF316: =IFERROR(SUMIFS(Transactions!$H:$H,Transactions!$C:$C,$A316,Transactions!$D:$D,"Sale"),0) -> 0 | AG316: =IFERROR(IF(maxifs(Transactions!$B:$B,Transactions!$C:$C,$A316,Transactions!$D:$D,"Sale")=0,"",maxifs(Transactions!$B:$B,Transactions!$C:$C,$A316,Transactions!$D:$D,"Sale")),"")
A317: KARNI-EARRNG2-MARASH-WHITE-BORDEAUX | B317: DSGN-EARRNG2-MARASH | C317: Marash Earrings (2 pcs) | D317: earrings 2 pcs. | E317: Marash | H317: white-bordeaux | I317: 36000 | J317: =IF($I317="","",ROUND($I317*Dropdowns!$K$5,2)) -> 93.6 | K317: =IF($I317="","",ROUND($I317*Dropdowns!$K$6,2)) -> 86.4 | L317: =IF($I317="","",ROUND($I317*Dropdowns!$K$7,2)) -> 7380 | M317: =IFERROR(IF($B317="","",VLOOKUP($B317,Designs!$A$3:$AP$165,27,FALSE())),"") | N317: =IFERROR(IF(OR($I317="",$M317="",$M317=0),"",($I317-$M317)/$I317),"") | O317: 0 | P317: 0 | Q317: =IF($O317="","",$O317-IF($P317="",0,$P317)) -> 0 | R317: 2 | S317: =IF($O317="","",IF($Q317<=$R317,"⚠ REORDER","OK")) -> ⚠ REORDER | V317: 7117.19 | W317: Armenia | Z317: No | AA317: No | AB317: No | AC317: No | AD317: Active | AE317: =IFERROR(SUMIFS(Transactions!$F:$F,Transactions!$C:$C,$A317,Transactions!$D:$D,"Sale"),0) -> 0 | AF317: =IFERROR(SUMIFS(Transactions!$H:$H,Transactions!$C:$C,$A317,Transactions!$D:$D,"Sale"),0) -> 0 | AG317: =IFERROR(IF(maxifs(Transactions!$B:$B,Transactions!$C:$C,$A317,Transactions!$D:$D,"Sale")=0,"",maxifs(Transactions!$B:$B,Transactions!$C:$C,$A317,Transactions!$D:$D,"Sale")),"")
A318: KARNI-EARRNG2-MARASH-TURQUOISE-BLUE | B318: DSGN-EARRNG2-MARASH | C318: Marash Earrings (2 pcs) | D318: earrings 2 pcs. | E318: Marash | H318: turquoise-blue | I318: 36000 | J318: =IF($I318="","",ROUND($I318*Dropdowns!$K$5,2)) -> 93.6 | K318: =IF($I318="","",ROUND($I318*Dropdowns!$K$6,2)) -> 86.4 | L318: =IF($I318="","",ROUND($I318*Dropdowns!$K$7,2)) -> 7380 | M318: =IFERROR(IF($B318="","",VLOOKUP($B318,Designs!$A$3:$AP$165,27,FALSE())),"") | N318: =IFERROR(IF(OR($I318="",$M318="",$M318=0),"",($I318-$M318)/$I318),"") | O318: 0 | P318: 0 | Q318: =IF($O318="","",$O318-IF($P318="",0,$P318)) -> 0 | R318: 2 | S318: =IF($O318="","",IF($Q318<=$R318,"⚠ REORDER","OK")) -> ⚠ REORDER | V318: 7117.19 | W318: Armenia | Z318: No | AA318: No | AB318: No | AC318: No | AD318: Active | AE318: =IFERROR(SUMIFS(Transactions!$F:$F,Transactions!$C:$C,$A318,Transactions!$D:$D,"Sale"),0) -> 0 | AF318: =IFERROR(SUMIFS(Transactions!$H:$H,Transactions!$C:$C,$A318,Transactions!$D:$D,"Sale"),0) -> 0 | AG318: =IFERROR(IF(maxifs(Transactions!$B:$B,Transactions!$C:$C,$A318,Transactions!$D:$D,"Sale")=0,"",maxifs(Transactions!$B:$B,Transactions!$C:$C,$A318,Transactions!$D:$D,"Sale")),"")
A319: KARNI-EARRNG2-VISHAB-BLUE-WHITE | B319: DSGN-EARRNG2-VISHAB | C319: Vishab Earrings (2 pcs) | D319: earrings 2 pcs. | E319: Vishab | H319: blue-white | I319: 36000 | J319: =IF($I319="","",ROUND($I319*Dropdowns!$K$5,2)) -> 93.6 | K319: =IF($I319="","",ROUND($I319*Dropdowns!$K$6,2)) -> 86.4 | L319: =IF($I319="","",ROUND($I319*Dropdowns!$K$7,2)) -> 7380 | M319: =IFERROR(IF($B319="","",VLOOKUP($B319,Designs!$A$3:$AP$165,27,FALSE())),"") | N319: =IFERROR(IF(OR($I319="",$M319="",$M319=0),"",($I319-$M319)/$I319),"") | O319: 0 | P319: 0 | Q319: =IF($O319="","",$O319-IF($P319="",0,$P319)) -> 0 | R319: 2 | S319: =IF($O319="","",IF($Q319<=$R319,"⚠ REORDER","OK")) -> ⚠ REORDER | V319: 7117.19 | W319: Armenia | Z319: No | AA319: No | AB319: No | AC319: No | AD319: Active | AE319: =IFERROR(SUMIFS(Transactions!$F:$F,Transactions!$C:$C,$A319,Transactions!$D:$D,"Sale"),0) -> 0 | AF319: =IFERROR(SUMIFS(Transactions!$H:$H,Transactions!$C:$C,$A319,Transactions!$D:$D,"Sale"),0) -> 0 | AG319: =IFERROR(IF(maxifs(Transactions!$B:$B,Transactions!$C:$C,$A319,Transactions!$D:$D,"Sale")=0,"",maxifs(Transactions!$B:$B,Transactions!$C:$C,$A319,Transactions!$D:$D,"Sale")),"")
A320: KARNI-EARRNG2-VISHAB-BLUE-RED | B320: DSGN-EARRNG2-VISHAB | C320: Vishab Earrings (2 pcs) | D320: earrings 2 pcs. | E320: Vishab | H320: blue-red | I320: 36000 | J320: =IF($I320="","",ROUND($I320*Dropdowns!$K$5,2)) -> 93.6 | K320: =IF($I320="","",ROUND($I320*Dropdowns!$K$6,2)) -> 86.4 | L320: =IF($I320="","",ROUND($I320*Dropdowns!$K$7,2)) -> 7380 | M320: =IFERROR(IF($B320="","",VLOOKUP($B320,Designs!$A$3:$AP$165,27,FALSE())),"") | N320: =IFERROR(IF(OR($I320="",$M320="",$M320=0),"",($I320-$M320)/$I320),"") | O320: 0 | P320: 0 | Q320: =IF($O320="","",$O320-IF($P320="",0,$P320)) -> 0 | R320: 2 | S320: =IF($O320="","",IF($Q320<=$R320,"⚠ REORDER","OK")) -> ⚠ REORDER | V320: 7117.19 | W320: Armenia | Z320: No | AA320: No | AB320: No | AC320: No | AD320: Active | AE320: =IFERROR(SUMIFS(Transactions!$F:$F,Transactions!$C:$C,$A320,Transactions!$D:$D,"Sale"),0) -> 0 | AF320: =IFERROR(SUMIFS(Transactions!$H:$H,Transactions!$C:$C,$A320,Transactions!$D:$D,"Sale"),0) -> 0 | AG320: =IFERROR(IF(maxifs(Transactions!$B:$B,Transactions!$C:$C,$A320,Transactions!$D:$D,"Sale")=0,"",maxifs(Transactions!$B:$B,Transactions!$C:$C,$A320,Transactions!$D:$D,"Sale")),"")
A321: KARNI-EARRNG2-VISHAB-WHITE-BORDEAUX | B321: DSGN-EARRNG2-VISHAB | C321: Vishab Earrings (2 pcs) | D321: earrings 2 pcs. | E321: Vishab | H321: white-bordeaux | I321: 36000 | J321: =IF($I321="","",ROUND($I321*Dropdowns!$K$5,2)) -> 93.6 | K321: =IF($I321="","",ROUND($I321*Dropdowns!$K$6,2)) -> 86.4 | L321: =IF($I321="","",ROUND($I321*Dropdowns!$K$7,2)) -> 7380 | M321: =IFERROR(IF($B321="","",VLOOKUP($B321,Designs!$A$3:$AP$165,27,FALSE())),"") | N321: =IFERROR(IF(OR($I321="",$M321="",$M321=0),"",($I321-$M321)/$I321),"") | O321: 0 | P321: 0 | Q321: =IF($O321="","",$O321-IF($P321="",0,$P321)) -> 0 | R321: 2 | S321: =IF($O321="","",IF($Q321<=$R321,"⚠ REORDER","OK")) -> ⚠ REORDER | V321: 7117.19 | W321: Armenia | Z321: No | AA321: No | AB321: No | AC321: No | AD321: Active | AE321: =IFERROR(SUMIFS(Transactions!$F:$F,Transactions!$C:$C,$A321,Transactions!$D:$D,"Sale"),0) -> 0 | AF321: =IFERROR(SUMIFS(Transactions!$H:$H,Transactions!$C:$C,$A321,Transactions!$D:$D,"Sale"),0) -> 0 | AG321: =IFERROR(IF(maxifs(Transactions!$B:$B,Transactions!$C:$C,$A321,Transactions!$D:$D,"Sale")=0,"",maxifs(Transactions!$B:$B,Transactions!$C:$C,$A321,Transactions!$D:$D,"Sale")),"")
A322: KARNI-EARRNG2-VISHAB-TURQUOISE-BLUE | B322: DSGN-EARRNG2-VISHAB | C322: Vishab Earrings (2 pcs) | D322: earrings 2 pcs. | E322: Vishab | H322: turquoise-blue | I322: 36000 | J322: =IF($I322="","",ROUND($I322*Dropdowns!$K$5,2)) -> 93.6 | K322: =IF($I322="","",ROUND($I322*Dropdowns!$K$6,2)) -> 86.4 | L322: =IF($I322="","",ROUND($I322*Dropdowns!$K$7,2)) -> 7380 | M322: =IFERROR(IF($B322="","",VLOOKUP($B322,Designs!$A$3:$AP$165,27,FALSE())),"") | N322: =IFERROR(IF(OR($I322="",$M322="",$M322=0),"",($I322-$M322)/$I322),"") | O322: 0 | P322: 0 | Q322: =IF($O322="","",$O322-IF($P322="",0,$P322)) -> 0 | R322: 2 | S322: =IF($O322="","",IF($Q322<=$R322,"⚠ REORDER","OK")) -> ⚠ REORDER | V322: 7117.19 | W322: Armenia | Z322: No | AA322: No | AB322: No | AC322: No | AD322: Active | AE322: =IFERROR(SUMIFS(Transactions!$F:$F,Transactions!$C:$C,$A322,Transactions!$D:$D,"Sale"),0) -> 0 | AF322: =IFERROR(SUMIFS(Transactions!$H:$H,Transactions!$C:$C,$A322,Transactions!$D:$D,"Sale"),0) -> 0 | AG322: =IFERROR(IF(maxifs(Transactions!$B:$B,Transactions!$C:$C,$A322,Transactions!$D:$D,"Sale")=0,"",maxifs(Transactions!$B:$B,Transactions!$C:$C,$A322,Transactions!$D:$D,"Sale")),"")
A323: KARNI-EARRNG2-VAN-WHITE | B323: DSGN-EARRNG2-VAN | C323: Van Earrings (2 pcs) | D323: earrings 2 pcs. | E323: Van | H323: white | I323: 36000 | J323: =IF($I323="","",ROUND($I323*Dropdowns!$K$5,2)) -> 93.6 | K323: =IF($I323="","",ROUND($I323*Dropdowns!$K$6,2)) -> 86.4 | L323: =IF($I323="","",ROUND($I323*Dropdowns!$K$7,2)) -> 7380 | M323: =IFERROR(IF($B323="","",VLOOKUP($B323,Designs!$A$3:$AP$165,27,FALSE())),"") | N323: =IFERROR(IF(OR($I323="",$M323="",$M323=0),"",($I323-$M323)/$I323),"") | O323: 0 | P323: 0 | Q323: =IF($O323="","",$O323-IF($P323="",0,$P323)) -> 0 | R323: 2 | S323: =IF($O323="","",IF($Q323<=$R323,"⚠ REORDER","OK")) -> ⚠ REORDER | V323: 7117.19 | W323: Armenia | Z323: No | AA323: No | AB323: No | AC323: No | AD323: Active | AE323: =IFERROR(SUMIFS(Transactions!$F:$F,Transactions!$C:$C,$A323,Transactions!$D:$D,"Sale"),0) -> 0 | AF323: =IFERROR(SUMIFS(Transactions!$H:$H,Transactions!$C:$C,$A323,Transactions!$D:$D,"Sale"),0) -> 0 | AG323: =IFERROR(IF(maxifs(Transactions!$B:$B,Transactions!$C:$C,$A323,Transactions!$D:$D,"Sale")=0,"",maxifs(Transactions!$B:$B,Transactions!$C:$C,$A323,Transactions!$D:$D,"Sale")),"")
A324: KARNI-EARRNG2-VAN-BLUE | B324: DSGN-EARRNG2-VAN | C324: Van Earrings (2 pcs) | D324: earrings 2 pcs. | E324: Van | H324: blue | I324: 36000 | J324: =IF($I324="","",ROUND($I324*Dropdowns!$K$5,2)) -> 93.6 | K324: =IF($I324="","",ROUND($I324*Dropdowns!$K$6,2)) -> 86.4 | L324: =IF($I324="","",ROUND($I324*Dropdowns!$K$7,2)) -> 7380 | M324: =IFERROR(IF($B324="","",VLOOKUP($B324,Designs!$A$3:$AP$165,27,FALSE())),"") | N324: =IFERROR(IF(OR($I324="",$M324="",$M324=0),"",($I324-$M324)/$I324),"") | O324: 0 | P324: 0 | Q324: =IF($O324="","",$O324-IF($P324="",0,$P324)) -> 0 | R324: 2 | S324: =IF($O324="","",IF($Q324<=$R324,"⚠ REORDER","OK")) -> ⚠ REORDER | V324: 7117.19 | W324: Armenia | Z324: No | AA324: No | AB324: No | AC324: No | AD324: Active | AE324: =IFERROR(SUMIFS(Transactions!$F:$F,Transactions!$C:$C,$A324,Transactions!$D:$D,"Sale"),0) -> 0 | AF324: =IFERROR(SUMIFS(Transactions!$H:$H,Transactions!$C:$C,$A324,Transactions!$D:$D,"Sale"),0) -> 0 | AG324: =IFERROR(IF(maxifs(Transactions!$B:$B,Transactions!$C:$C,$A324,Transactions!$D:$D,"Sale")=0,"",maxifs(Transactions!$B:$B,Transactions!$C:$C,$A324,Transactions!$D:$D,"Sale")),"")
A325: KARNI-EARRNG2-VAN-CAMEL | B325: DSGN-EARRNG2-VAN | C325: Van Earrings (2 pcs) | D325: earrings 2 pcs. | E325: Van | H325: camel | I325: 36000 | J325: =IF($I325="","",ROUND($I325*Dropdowns!$K$5,2)) -> 93.6 | K325: =IF($I325="","",ROUND($I325*Dropdowns!$K$6,2)) -> 86.4 | L325: =IF($I325="","",ROUND($I325*Dropdowns!$K$7,2)) -> 7380 | M325: =IFERROR(IF($B325="","",VLOOKUP($B325,Designs!$A$3:$AP$165,27,FALSE())),"") | N325: =IFERROR(IF(OR($I325="",$M325="",$M325=0),"",($I325-$M325)/$I325),"") | O325: 0 | P325: 0 | Q325: =IF($O325="","",$O325-IF($P325="",0,$P325)) -> 0 | R325: 2 | S325: =IF($O325="","",IF($Q325<=$R325,"⚠ REORDER","OK")) -> ⚠ REORDER | V325: 7117.19 | W325: Armenia | Z325: No | AA325: No | AB325: No | AC325: No | AD325: Active | AE325: =IFERROR(SUMIFS(Transactions!$F:$F,Transactions!$C:$C,$A325,Transactions!$D:$D,"Sale"),0) -> 0 | AF325: =IFERROR(SUMIFS(Transactions!$H:$H,Transactions!$C:$C,$A325,Transactions!$D:$D,"Sale"),0) -> 0 | AG325: =IFERROR(IF(maxifs(Transactions!$B:$B,Transactions!$C:$C,$A325,Transactions!$D:$D,"Sale")=0,"",maxifs(Transactions!$B:$B,Transactions!$C:$C,$A325,Transactions!$D:$D,"Sale")),"")
A326: KARNI-EARRNG2-VAN-TURQUOISE | B326: DSGN-EARRNG2-VAN | C326: Van Earrings (2 pcs) | D326: earrings 2 pcs. | E326: Van | H326: turquoise | I326: 36000 | J326: =IF($I326="","",ROUND($I326*Dropdowns!$K$5,2)) -> 93.6 | K326: =IF($I326="","",ROUND($I326*Dropdowns!$K$6,2)) -> 86.4 | L326: =IF($I326="","",ROUND($I326*Dropdowns!$K$7,2)) -> 7380 | M326: =IFERROR(IF($B326="","",VLOOKUP($B326,Designs!$A$3:$AP$165,27,FALSE())),"") | N326: =IFERROR(IF(OR($I326="",$M326="",$M326=0),"",($I326-$M326)/$I326),"") | O326: 0 | P326: 0 | Q326: =IF($O326="","",$O326-IF($P326="",0,$P326)) -> 0 | R326: 2 | S326: =IF($O326="","",IF($Q326<=$R326,"⚠ REORDER","OK")) -> ⚠ REORDER | V326: 7117.19 | W326: Armenia | Z326: No | AA326: No | AB326: No | AC326: No | AD326: Active | AE326: =IFERROR(SUMIFS(Transactions!$F:$F,Transactions!$C:$C,$A326,Transactions!$D:$D,"Sale"),0) -> 0 | AF326: =IFERROR(SUMIFS(Transactions!$H:$H,Transactions!$C:$C,$A326,Transactions!$D:$D,"Sale"),0) -> 0 | AG326: =IFERROR(IF(maxifs(Transactions!$B:$B,Transactions!$C:$C,$A326,Transactions!$D:$D,"Sale")=0,"",maxifs(Transactions!$B:$B,Transactions!$C:$C,$A326,Transactions!$D:$D,"Sale")),"")
... A331: KARNI-EARRNG2-VISHABAREVAGORG-BLUE-BORDEAUX-WHITE | B331: DSGN-EARRNG2-VISHABAREVAGORG | C331: Արեւագորգի Վիշապ | D331: earrings 2 pcs. | E331: Vishab Arevagorg | H331: blue-bordeaux-white | I331: 36000 | J331: =IF($I331="","",ROUND($I331*Dropdowns!$K$5,2)) -> 93.6 | K331: =IF($I331="","",ROUND($I331*Dropdowns!$K$6,2)) -> 86.4 | L331: =IF($I331="","",ROUND($I331*Dropdowns!$K$7,2)) -> 7380 | M331: =IFERROR(IF($B331="","",VLOOKUP($B331,Designs!$A$3:$AP$165,27,FALSE())),"") | N331: =IFERROR(IF(OR($I331="",$M331="",$M331=0),"",($I331-$M331)/$I331),"") | O331: 0 | P331: 0 | Q331: =IF($O331="","",$O331-IF($P331="",0,$P331)) -> 0 | R331: 2 | S331: =IF($O331="","",IF($Q331<=$R331,"⚠ REORDER","OK")) -> ⚠ REORDER | V331: 7117.19 | W331: Armenia | Z331: No | AA331: No | AB331: No | AC331: No | AD331: Active | AE331: =IFERROR(SUMIFS(Transactions!$F:$F,Transactions!$C:$C,$A331,Transactions!$D:$D,"Sale"),0) -> 0 | AF331: =IFERROR(SUMIFS(Transactions!$H:$H,Transactions!$C:$C,$A331,Transactions!$D:$D,"Sale"),0) -> 0 | AG331: =IFERROR(IF(maxifs(Transactions!$B:$B,Transactions!$C:$C,$A331,Transactions!$D:$D,"Sale")=0,"",maxifs(Transactions!$B:$B,Transactions!$C:$C,$A331,Transactions!$D:$D,"Sale")),"")
A332: KARNI-EARRNG-MARASH-L-WHITE-BORDEAUX | B332: DSGN-EARRNG-MARASH-L | C332: Marash Earrings | D332: Earring | E332: Marash | G332: large | H332: white-bordeaux | I332: 44000 | J332: =IF($I332="","",ROUND($I332*Dropdowns!$K$5,2)) -> 114.4 | K332: =IF($I332="","",ROUND($I332*Dropdowns!$K$6,2)) -> 105.6 | L332: =IF($I332="","",ROUND($I332*Dropdowns!$K$7,2)) -> 9020 | M332: =IFERROR(IF($B332="","",VLOOKUP($B332,Designs!$A$3:$AP$165,27,FALSE())),"") | N332: =IFERROR(IF(OR($I332="",$M332="",$M332=0),"",($I332-$M332)/$I332),"") | O332: 0 | P332: 0 | Q332: =IF($O332="","",$O332-IF($P332="",0,$P332)) -> 0 | R332: 2 | S332: =IF($O332="","",IF($Q332<=$R332,"⚠ REORDER","OK")) -> ⚠ REORDER | V332: 7117.19 | W332: Armenia | Z332: No | AA332: No | AB332: No | AC332: No | AD332: Active | AE332: =IFERROR(SUMIFS(Transactions!$F:$F,Transactions!$C:$C,$A332,Transactions!$D:$D,"Sale"),0) -> 0 | AF332: =IFERROR(SUMIFS(Transactions!$H:$H,Transactions!$C:$C,$A332,Transactions!$D:$D,"Sale"),0) -> 0 | AG332: =IFERROR(IF(maxifs(Transactions!$B:$B,Transactions!$C:$C,$A332,Transactions!$D:$D,"Sale")=0,"",maxifs(Transactions!$B:$B,Transactions!$C:$C,$A332,Transactions!$D:$D,"Sale")),"")
A333: KARNI-EARRNG-MARASH-L-BLUE-WHITE | B333: DSGN-EARRNG-MARASH-L | C333: Marash Earrings | D333: Earring | E333: Marash | G333: large | H333: blue-white | I333: 44000 | J333: =IF($I333="","",ROUND($I333*Dropdowns!$K$5,2)) -> 114.4 | K333: =IF($I333="","",ROUND($I333*Dropdowns!$K$6,2)) -> 105.6 | L333: =IF($I333="","",ROUND($I333*Dropdowns!$K$7,2)) -> 9020 | M333: =IFERROR(IF($B333="","",VLOOKUP($B333,Designs!$A$3:$AP$165,27,FALSE())),"") | N333: =IFERROR(IF(OR($I333="",$M333="",$M333=0),"",($I333-$M333)/$I333),"") | O333: 0 | P333: 0 | Q333: =IF($O333="","",$O333-IF($P333="",0,$P333)) -> 0 | R333: 2 | S333: =IF($O333="","",IF($Q333<=$R333,"⚠ REORDER","OK")) -> ⚠ REORDER | V333: 7117.19 | W333: Armenia | Z333: No | AA333: No | AB333: No | AC333: No | AD333: Active | AE333: =IFERROR(SUMIFS(Transactions!$F:$F,Transactions!$C:$C,$A333,Transactions!$D:$D,"Sale"),0) -> 0 | AF333: =IFERROR(SUMIFS(Transactions!$H:$H,Transactions!$C:$C,$A333,Transactions!$D:$D,"Sale"),0) -> 0 | AG333: =IFERROR(IF(maxifs(Transactions!$B:$B,Transactions!$C:$C,$A333,Transactions!$D:$D,"Sale")=0,"",maxifs(Transactions!$B:$B,Transactions!$C:$C,$A333,Transactions!$D:$D,"Sale")),"")
A334: KARNI-EARRNG-MARASH-L-WHITE-GOLDEN | B334: DSGN-EARRNG-MARASH-L | C334: Marash Earrings | D334: Earring | E334: Marash | G334: large | H334: white-golden | I334: 44000 | J334: =IF($I334="","",ROUND($I334*Dropdowns!$K$5,2)) -> 114.4 | K334: =IF($I334="","",ROUND($I334*Dropdowns!$K$6,2)) -> 105.6 | L334: =IF($I334="","",ROUND($I334*Dropdowns!$K$7,2)) -> 9020 | M334: =IFERROR(IF($B334="","",VLOOKUP($B334,Designs!$A$3:$AP$165,27,FALSE())),"") | N334: =IFERROR(IF(OR($I334="",$M334="",$M334=0),"",($I334-$M334)/$I334),"") | O334: 0 | P334: 0 | Q334: =IF($O334="","",$O334-IF($P334="",0,$P334)) -> 0 | R334: 2 | S334: =IF($O334="","",IF($Q334<=$R334,"⚠ REORDER","OK")) -> ⚠ REORDER | V334: 7117.19 | W334: Armenia | Z334: No | AA334: No | AB334: No | AC334: No | AD334: Active | AE334: =IFERROR(SUMIFS(Transactions!$F:$F,Transactions!$C:$C,$A334,Transactions!$D:$D,"Sale"),0) -> 0 | AF334: =IFERROR(SUMIFS(Transactions!$H:$H,Transactions!$C:$C,$A334,Transactions!$D:$D,"Sale"),0) -> 0 | AG334: =IFERROR(IF(maxifs(Transactions!$B:$B,Transactions!$C:$C,$A334,Transactions!$D:$D,"Sale")=0,"",maxifs(Transactions!$B:$B,Transactions!$C:$C,$A334,Transactions!$D:$D,"Sale")),"")
A335: KARNI-RING-MARASH-S-BLUE | B335: DSGN-RING-MARASH-S | C335: Marash Ring | D335: Ring | E335: Marash | G335: small | H335: blue | I335: 13000 | J335: =IF($I335="","",ROUND($I335*Dropdowns!$K$5,2)) -> 33.8 | K335: =IF($I335="","",ROUND($I335*Dropdowns!$K$6,2)) -> 31.2 | L335: =IF($I335="","",ROUND($I335*Dropdowns!$K$7,2)) -> 2665 | M335: =IFERROR(IF($B335="","",VLOOKUP($B335,Designs!$A$3:$AP$165,27,FALSE())),"") | N335: =IFERROR(IF(OR($I335="",$M335="",$M335=0),"",($I335-$M335)/$I335),"") | O335: 0 | P335: 0 | Q335: =IF($O335="","",$O335-IF($P335="",0,$P335)) -> 0 | R335: 2 | S335: =IF($O335="","",IF($Q335<=$R335,"⚠ REORDER","OK")) -> ⚠ REORDER | V335: 7117.19 | W335: Armenia | Z335: No | AA335: No | AB335: No | AC335: No | AD335: Active | AE335: =IFERROR(SUMIFS(Transactions!$F:$F,Transactions!$C:$C,$A335,Transactions!$D:$D,"Sale"),0) -> 0 | AF335: =IFERROR(SUMIFS(Transactions!$H:$H,Transactions!$C:$C,$A335,Transactions!$D:$D,"Sale"),0) -> 0 | AG335: =IFERROR(IF(maxifs(Transactions!$B:$B,Transactions!$C:$C,$A335,Transactions!$D:$D,"Sale")=0,"",maxifs(Transactions!$B:$B,Transactions!$C:$C,$A335,Transactions!$D:$D,"Sale")),"")
A336: KARNI-RING-MARASH-S-WHITE | B336: DSGN-RING-MARASH-S | C336: Marash Ring | D336: Ring | E336: Marash | G336: small | H336: white | I336: 13000 | J336: =IF($I336="","",ROUND($I336*Dropdowns!$K$5,2)) -> 33.8 | K336: =IF($I336="","",ROUND($I336*Dropdowns!$K$6,2)) -> 31.2 | L336: =IF($I336="","",ROUND($I336*Dropdowns!$K$7,2)) -> 2665 | M336: =IFERROR(IF($B336="","",VLOOKUP($B336,Designs!$A$3:$AP$165,27,FALSE())),"") | N336: =IFERROR(IF(OR($I336="",$M336="",$M336=0),"",($I336-$M336)/$I336),"") | O336: 0 | P336: 0 | Q336: =IF($O336="","",$O336-IF($P336="",0,$P336)) -> 0 | R336: 2 | S336: =IF($O336="","",IF($Q336<=$R336,"⚠ REORDER","OK")) -> ⚠ REORDER | V336: 7117.19 | W336: Armenia | Z336: No | AA336: No | AB336: No | AC336: No | AD336: Active | AE336: =IFERROR(SUMIFS(Transactions!$F:$F,Transactions!$C:$C,$A336,Transactions!$D:$D,"Sale"),0) -> 0 | AF336: =IFERROR(SUMIFS(Transactions!$H:$H,Transactions!$C:$C,$A336,Transactions!$D:$D,"Sale"),0) -> 0 | AG336: =IFERROR(IF(maxifs(Transactions!$B:$B,Transactions!$C:$C,$A336,Transactions!$D:$D,"Sale")=0,"",maxifs(Transactions!$B:$B,Transactions!$C:$C,$A336,Transactions!$D:$D,"Sale")),"")
A337: KARNI-RING-MARASH-S-BORDEAUX | B337: DSGN-RING-MARASH-S | C337: Marash Ring | D337: Ring | E337: Marash | G337: small | H337: bordeaux | I337: 13000 | J337: =IF($I337="","",ROUND($I337*Dropdowns!$K$5,2)) -> 33.8 | K337: =IF($I337="","",ROUND($I337*Dropdowns!$K$6,2)) -> 31.2 | L337: =IF($I337="","",ROUND($I337*Dropdowns!$K$7,2)) -> 2665 | M337: =IFERROR(IF($B337="","",VLOOKUP($B337,Designs!$A$3:$AP$165,27,FALSE())),"") | N337: =IFERROR(IF(OR($I337="",$M337="",$M337=0),"",($I337-$M337)/$I337),"") | O337: 0 | P337: 0 | Q337: =IF($O337="","",$O337-IF($P337="",0,$P337)) -> 0 | R337: 2 | S337: =IF($O337="","",IF($Q337<=$R337,"⚠ REORDER","OK")) -> ⚠ REORDER | V337: 7117.19 | W337: Armenia | Z337: No | AA337: No | AB337: No | AC337: No | AD337: Active | AE337: =IFERROR(SUMIFS(Transactions!$F:$F,Transactions!$C:$C,$A337,Transactions!$D:$D,"Sale"),0) -> 0 | AF337: =IFERROR(SUMIFS(Transactions!$H:$H,Transactions!$C:$C,$A337,Transactions!$D:$D,"Sale"),0) -> 0 | AG337: =IFERROR(IF(maxifs(Transactions!$B:$B,Transactions!$C:$C,$A337,Transactions!$D:$D,"Sale")=0,"",maxifs(Transactions!$B:$B,Transactions!$C:$C,$A337,Transactions!$D:$D,"Sale")),"")
A338: KARNI-RING-MARASH-S-TURQUOISE | B338: DSGN-RING-MARASH-S | C338: Marash Ring | D338: Ring | E338: Marash | G338: small | H338: turquoise | I338: 13000 | J338: =IF($I338="","",ROUND($I338*Dropdowns!$K$5,2)) -> 33.8 | K338: =IF($I338="","",ROUND($I338*Dropdowns!$K$6,2)) -> 31.2 | L338: =IF($I338="","",ROUND($I338*Dropdowns!$K$7,2)) -> 2665 | M338: =IFERROR(IF($B338="","",VLOOKUP($B338,Designs!$A$3:$AP$165,27,FALSE())),"") | N338: =IFERROR(IF(OR($I338="",$M338="",$M338=0),"",($I338-$M338)/$I338),"") | O338: 0 | P338: 0 | Q338: =IF($O338="","",$O338-IF($P338="",0,$P338)) -> 0 | R338: 2 | S338: =IF($O338="","",IF($Q338<=$R338,"⚠ REORDER","OK")) -> ⚠ REORDER | V338: 7117.19 | W338: Armenia | Z338: No | AA338: No | AB338: No | AC338: No | AD338: Active | AE338: =IFERROR(SUMIFS(Transactions!$F:$F,Transactions!$C:$C,$A338,Transactions!$D:$D,"Sale"),0) -> 0 | AF338: =IFERROR(SUMIFS(Transactions!$H:$H,Transactions!$C:$C,$A338,Transactions!$D:$D,"Sale"),0) -> 0 | AG338: =IFERROR(IF(maxifs(Transactions!$B:$B,Transactions!$C:$C,$A338,Transactions!$D:$D,"Sale")=0,"",maxifs(Transactions!$B:$B,Transactions!$C:$C,$A338,Transactions!$D:$D,"Sale")),"")
A339: KARNI-RING-MARASH-S-GREEN | B339: DSGN-RING-MARASH-S | C339: Marash Ring | D339: Ring | E339: Marash | G339: small | H339: green | I339: 13000 | J339: =IF($I339="","",ROUND($I339*Dropdowns!$K$5,2)) -> 33.8 | K339: =IF($I339="","",ROUND($I339*Dropdowns!$K$6,2)) -> 31.2 | L339: =IF($I339="","",ROUND($I339*Dropdowns!$K$7,2)) -> 2665 | M339: =IFERROR(IF($B339="","",VLOOKUP($B339,Designs!$A$3:$AP$165,27,FALSE())),"") | N339: =IFERROR(IF(OR($I339="",$M339="",$M339=0),"",($I339-$M339)/$I339),"") | O339: 0 | P339: 0 | Q339: =IF($O339="","",$O339-IF($P339="",0,$P339)) -> 0 | R339: 2 | S339: =IF($O339="","",IF($Q339<=$R339,"⚠ REORDER","OK")) -> ⚠ REORDER | V339: 7117.19 | W339: Armenia | Z339: No | AA339: No | AB339: No | AC339: No | AD339: Active | AE339: =IFERROR(SUMIFS(Transactions!$F:$F,Transactions!$C:$C,$A339,Transactions!$D:$D,"Sale"),0) -> 0 | AF339: =IFERROR(SUMIFS(Transactions!$H:$H,Transactions!$C:$C,$A339,Transactions!$D:$D,"Sale"),0) -> 0 | AG339: =IFERROR(IF(maxifs(Transactions!$B:$B,Transactions!$C:$C,$A339,Transactions!$D:$D,"Sale")=0,"",maxifs(Transactions!$B:$B,Transactions!$C:$C,$A339,Transactions!$D:$D,"Sale")),"")
A340: KARNI-RING-VAN-S-BLUE | B340: DSGN-RING-VAN-S | C340: Van Ring | D340: Ring | E340: Van | G340: small | H340: blue | I340: 13000 | J340: =IF($I340="","",ROUND($I340*Dropdowns!$K$5,2)) -> 33.8 | K340: =IF($I340="","",ROUND($I340*Dropdowns!$K$6,2)) -> 31.2 | L340: =IF($I340="","",ROUND($I340*Dropdowns!$K$7,2)) -> 2665 | M340: =IFERROR(IF($B340="","",VLOOKUP($B340,Designs!$A$3:$AP$165,27,FALSE())),"") | N340: =IFERROR(IF(OR($I340="",$M340="",$M340=0),"",($I340-$M340)/$I340),"") | O340: 0 | P340: 0 | Q340: =IF($O340="","",$O340-IF($P340="",0,$P340)) -> 0 | R340: 2 | S340: =IF($O340="","",IF($Q340<=$R340,"⚠ REORDER","OK")) -> ⚠ REORDER | V340: 7117.19 | W340: Armenia | Z340: No | AA340: No | AB340: No | AC340: No | AD340: Active | AE340: =IFERROR(SUMIFS(Transactions!$F:$F,Transactions!$C:$C,$A340,Transactions!$D:$D,"Sale"),0) -> 0 | AF340: =IFERROR(SUMIFS(Transactions!$H:$H,Transactions!$C:$C,$A340,Transactions!$D:$D,"Sale"),0) -> 0 | AG340: =IFERROR(IF(maxifs(Transactions!$B:$B,Transactions!$C:$C,$A340,Transactions!$D:$D,"Sale")=0,"",maxifs(Transactions!$B:$B,Transactions!$C:$C,$A340,Transactions!$D:$D,"Sale")),"")
A341: KARNI-RING-VAN-S-WHITE | B341: DSGN-RING-VAN-S | C341: Van Ring | D341: Ring | E341: Van | G341: small | H341: white | I341: 13000 | J341: =IF($I341="","",ROUND($I341*Dropdowns!$K$5,2)) -> 33.8 | K341: =IF($I341="","",ROUND($I341*Dropdowns!$K$6,2)) -> 31.2 | L341: =IF($I341="","",ROUND($I341*Dropdowns!$K$7,2)) -> 2665 | M341: =IFERROR(IF($B341="","",VLOOKUP($B341,Designs!$A$3:$AP$165,27,FALSE())),"") | N341: =IFERROR(IF(OR($I341="",$M341="",$M341=0),"",($I341-$M341)/$I341),"") | O341: 0 | P341: 0 | Q341: =IF($O341="","",$O341-IF($P341="",0,$P341)) -> 0 | R341: 2 | S341: =IF($O341="","",IF($Q341<=$R341,"⚠ REORDER","OK")) -> ⚠ REORDER | V341: 7117.19 | W341: Armenia | Z341: No | AA341: No | AB341: No | AC341: No | AD341: Active | AE341: =IFERROR(SUMIFS(Transactions!$F:$F,Transactions!$C:$C,$A341,Transactions!$D:$D,"Sale"),0) -> 0 | AF341: =IFERROR(SUMIFS(Transactions!$H:$H,Transactions!$C:$C,$A341,Transactions!$D:$D,"Sale"),0) -> 0 | AG341: =IFERROR(IF(maxifs(Transactions!$B:$B,Transactions!$C:$C,$A341,Transactions!$D:$D,"Sale")=0,"",maxifs(Transactions!$B:$B,Transactions!$C:$C,$A341,Transactions!$D:$D,"Sale")),"")
A342: KARNI-RING-VAN-S-BORDEAUX | B342: DSGN-RING-VAN-S | C342: Van Ring | D342: Ring | E342: Van | G342: small | H342: bordeaux | I342: 13000 | J342: =IF($I342="","",ROUND($I342*Dropdowns!$K$5,2)) -> 33.8 | K342: =IF($I342="","",ROUND($I342*Dropdowns!$K$6,2)) -> 31.2 | L342: =IF($I342="","",ROUND($I342*Dropdowns!$K$7,2)) -> 2665 | M342: =IFERROR(IF($B342="","",VLOOKUP($B342,Designs!$A$3:$AP$165,27,FALSE())),"") | N342: =IFERROR(IF(OR($I342="",$M342="",$M342=0),"",($I342-$M342)/$I342),"") | O342: 0 | P342: 0 | Q342: =IF($O342="","",$O342-IF($P342="",0,$P342)) -> 0 | R342: 2 | S342: =IF($O342="","",IF($Q342<=$R342,"⚠ REORDER","OK")) -> ⚠ REORDER | V342: 7117.19 | W342: Armenia | Z342: No | AA342: No | AB342: No | AC342: No | AD342: Active | AE342: =IFERROR(SUMIFS(Transactions!$F:$F,Transactions!$C:$C,$A342,Transactions!$D:$D,"Sale"),0) -> 0 | AF342: =IFERROR(SUMIFS(Transactions!$H:$H,Transactions!$C:$C,$A342,Transactions!$D:$D,"Sale"),0) -> 0 | AG342: =IFERROR(IF(maxifs(Transactions!$B:$B,Transactions!$C:$C,$A342,Transactions!$D:$D,"Sale")=0,"",maxifs(Transactions!$B:$B,Transactions!$C:$C,$A342,Transactions!$D:$D,"Sale")),"")
A343: KARNI-RING-VAN-S-TURQUOISE | B343: DSGN-RING-VAN-S | C343: Van Ring | D343: Ring | E343: Van | G343: small | H343: turquoise | I343: 13000 | J343: =IF($I343="","",ROUND($I343*Dropdowns!$K$5,2)) -> 33.8 | K343: =IF($I343="","",ROUND($I343*Dropdowns!$K$6,2)) -> 31.2 | L343: =IF($I343="","",ROUND($I343*Dropdowns!$K$7,2)) -> 2665 | M343: =IFERROR(IF($B343="","",VLOOKUP($B343,Designs!$A$3:$AP$165,27,FALSE())),"") | N343: =IFERROR(IF(OR($I343="",$M343="",$M343=0),"",($I343-$M343)/$I343),"") | O343: 0 | P343: 0 | Q343: =IF($O343="","",$O343-IF($P343="",0,$P343)) -> 0 | R343: 2 | S343: =IF($O343="","",IF($Q343<=$R343,"⚠ REORDER","OK")) -> ⚠ REORDER | V343: 7117.19 | W343: Armenia | Z343: No | AA343: No | AB343: No | AC343: No | AD343: Active | AE343: =IFERROR(SUMIFS(Transactions!$F:$F,Transactions!$C:$C,$A343,Transactions!$D:$D,"Sale"),0) -> 0 | AF343: =IFERROR(SUMIFS(Transactions!$H:$H,Transactions!$C:$C,$A343,Transactions!$D:$D,"Sale"),0) -> 0 | AG343: =IFERROR(IF(maxifs(Transactions!$B:$B,Transactions!$C:$C,$A343,Transactions!$D:$D,"Sale")=0,"",maxifs(Transactions!$B:$B,Transactions!$C:$C,$A343,Transactions!$D:$D,"Sale")),"")
... A361: KARNI-RING-ARTSAKHIKHACHANAKHSH-S-WHITE-BLUE | B361: DSGN-RING-ARTSAKHIKHACHANAKHSH-S | C361: Artsakhi Khachanakhsh Ring | D361: Ring | E361: Artsakhi Khachanakhsh | G361: small | H361: white-blue | I361: 13000 | J361: =IF($I361="","",ROUND($I361*Dropdowns!$K$5,2)) -> 33.8 | K361: =IF($I361="","",ROUND($I361*Dropdowns!$K$6,2)) -> 31.2 | L361: =IF($I361="","",ROUND($I361*Dropdowns!$K$7,2)) -> 2665 | M361: =IFERROR(IF($B361="","",VLOOKUP($B361,Designs!$A$3:$AP$165,27,FALSE())),"") | N361: =IFERROR(IF(OR($I361="",$M361="",$M361=0),"",($I361-$M361)/$I361),"") | O361: 0 | P361: 0 | Q361: =IF($O361="","",$O361-IF($P361="",0,$P361)) -> 0 | R361: 2 | S361: =IF($O361="","",IF($Q361<=$R361,"⚠ REORDER","OK")) -> ⚠ REORDER | V361: 7117.19 | W361: Armenia | Z361: No | AA361: No | AB361: No | AC361: No | AD361: Active | AE361: =IFERROR(SUMIFS(Transactions!$F:$F,Transactions!$C:$C,$A361,Transactions!$D:$D,"Sale"),0) -> 0 | AF361: =IFERROR(SUMIFS(Transactions!$H:$H,Transactions!$C:$C,$A361,Transactions!$D:$D,"Sale"),0) -> 0 | AG361: =IFERROR(IF(maxifs(Transactions!$B:$B,Transactions!$C:$C,$A361,Transactions!$D:$D,"Sale")=0,"",maxifs(Transactions!$B:$B,Transactions!$C:$C,$A361,Transactions!$D:$D,"Sale")),"")
A362: KARNI-RINGTWIN-MARASH-WHITE-BLUE | B362: DSGN-RINGTWIN-MARASH | C362: Marash Twin Ring | D362: ring twin | E362: Marash | H362: white-blue | I362: 20000 | J362: =IF($I362="","",ROUND($I362*Dropdowns!$K$5,2)) -> 52 | K362: =IF($I362="","",ROUND($I362*Dropdowns!$K$6,2)) -> 48 | L362: =IF($I362="","",ROUND($I362*Dropdowns!$K$7,2)) -> 4100 | M362: =IFERROR(IF($B362="","",VLOOKUP($B362,Designs!$A$3:$AP$165,27,FALSE())),"") | N362: =IFERROR(IF(OR($I362="",$M362="",$M362=0),"",($I362-$M362)/$I362),"") | O362: 0 | P362: 0 | Q362: =IF($O362="","",$O362-IF($P362="",0,$P362)) -> 0 | R362: 2 | S362: =IF($O362="","",IF($Q362<=$R362,"⚠ REORDER","OK")) -> ⚠ REORDER | V362: 7117.19 | W362: Armenia | Z362: No | AA362: No | AB362: No | AC362: No | AD362: Active | AE362: =IFERROR(SUMIFS(Transactions!$F:$F,Transactions!$C:$C,$A362,Transactions!$D:$D,"Sale"),0) -> 0 | AF362: =IFERROR(SUMIFS(Transactions!$H:$H,Transactions!$C:$C,$A362,Transactions!$D:$D,"Sale"),0) -> 0 | AG362: =IFERROR(IF(maxifs(Transactions!$B:$B,Transactions!$C:$C,$A362,Transactions!$D:$D,"Sale")=0,"",maxifs(Transactions!$B:$B,Transactions!$C:$C,$A362,Transactions!$D:$D,"Sale")),"")
A363: KARNI-RINGTWIN-MARASH-WHITE-BORDEAUX | B363: DSGN-RINGTWIN-MARASH | C363: Marash Twin Ring | D363: ring twin | E363: Marash | H363: white-bordeaux | I363: 20000 | J363: =IF($I363="","",ROUND($I363*Dropdowns!$K$5,2)) -> 52 | K363: =IF($I363="","",ROUND($I363*Dropdowns!$K$6,2)) -> 48 | L363: =IF($I363="","",ROUND($I363*Dropdowns!$K$7,2)) -> 4100 | M363: =IFERROR(IF($B363="","",VLOOKUP($B363,Designs!$A$3:$AP$165,27,FALSE())),"") | N363: =IFERROR(IF(OR($I363="",$M363="",$M363=0),"",($I363-$M363)/$I363),"") | O363: 0 | P363: 0 | Q363: =IF($O363="","",$O363-IF($P363="",0,$P363)) -> 0 | R363: 2 | S363: =IF($O363="","",IF($Q363<=$R363,"⚠ REORDER","OK")) -> ⚠ REORDER | V363: 7117.19 | W363: Armenia | Z363: No | AA363: No | AB363: No | AC363: No | AD363: Active | AE363: =IFERROR(SUMIFS(Transactions!$F:$F,Transactions!$C:$C,$A363,Transactions!$D:$D,"Sale"),0) -> 0 | AF363: =IFERROR(SUMIFS(Transactions!$H:$H,Transactions!$C:$C,$A363,Transactions!$D:$D,"Sale"),0) -> 0 | AG363: =IFERROR(IF(maxifs(Transactions!$B:$B,Transactions!$C:$C,$A363,Transactions!$D:$D,"Sale")=0,"",maxifs(Transactions!$B:$B,Transactions!$C:$C,$A363,Transactions!$D:$D,"Sale")),"")
A364: KARNI-RINGTWIN-MARASH-WHITE-TURQUOISE | B364: DSGN-RINGTWIN-MARASH | C364: Marash Twin Ring | D364: ring twin | E364: Marash | H364: white-turquoise | I364: 20000 | J364: =IF($I364="","",ROUND($I364*Dropdowns!$K$5,2)) -> 52 | K364: =IF($I364="","",ROUND($I364*Dropdowns!$K$6,2)) -> 48 | L364: =IF($I364="","",ROUND($I364*Dropdowns!$K$7,2)) -> 4100 | M364: =IFERROR(IF($B364="","",VLOOKUP($B364,Designs!$A$3:$AP$165,27,FALSE())),"") | N364: =IFERROR(IF(OR($I364="",$M364="",$M364=0),"",($I364-$M364)/$I364),"") | O364: 0 | P364: 0 | Q364: =IF($O364="","",$O364-IF($P364="",0,$P364)) -> 0 | R364: 2 | S364: =IF($O364="","",IF($Q364<=$R364,"⚠ REORDER","OK")) -> ⚠ REORDER | V364: 7117.19 | W364: Armenia | Z364: No | AA364: No | AB364: No | AC364: No | AD364: Active | AE364: =IFERROR(SUMIFS(Transactions!$F:$F,Transactions!$C:$C,$A364,Transactions!$D:$D,"Sale"),0) -> 0 | AF364: =IFERROR(SUMIFS(Transactions!$H:$H,Transactions!$C:$C,$A364,Transactions!$D:$D,"Sale"),0) -> 0 | AG364: =IFERROR(IF(maxifs(Transactions!$B:$B,Transactions!$C:$C,$A364,Transactions!$D:$D,"Sale")=0,"",maxifs(Transactions!$B:$B,Transactions!$C:$C,$A364,Transactions!$D:$D,"Sale")),"")
A365: KARNI-RINGTWIN-MARASH-WHITE-GREEN | B365: DSGN-RINGTWIN-MARASH | C365: Marash Twin Ring | D365: ring twin | E365: Marash | H365: white-green | I365: 20000 | J365: =IF($I365="","",ROUND($I365*Dropdowns!$K$5,2)) -> 52 | K365: =IF($I365="","",ROUND($I365*Dropdowns!$K$6,2)) -> 48 | L365: =IF($I365="","",ROUND($I365*Dropdowns!$K$7,2)) -> 4100 | M365: =IFERROR(IF($B365="","",VLOOKUP($B365,Designs!$A$3:$AP$165,27,FALSE())),"") | N365: =IFERROR(IF(OR($I365="",$M365="",$M365=0),"",($I365-$M365)/$I365),"") | O365: 0 | P365: 0 | Q365: =IF($O365="","",$O365-IF($P365="",0,$P365)) -> 0 | R365: 2 | S365: =IF($O365="","",IF($Q365<=$R365,"⚠ REORDER","OK")) -> ⚠ REORDER | V365: 7117.19 | W365: Armenia | Z365: No | AA365: No | AB365: No | AC365: No | AD365: Active | AE365: =IFERROR(SUMIFS(Transactions!$F:$F,Transactions!$C:$C,$A365,Transactions!$D:$D,"Sale"),0) -> 0 | AF365: =IFERROR(SUMIFS(Transactions!$H:$H,Transactions!$C:$C,$A365,Transactions!$D:$D,"Sale"),0) -> 0 | AG365: =IFERROR(IF(maxifs(Transactions!$B:$B,Transactions!$C:$C,$A365,Transactions!$D:$D,"Sale")=0,"",maxifs(Transactions!$B:$B,Transactions!$C:$C,$A365,Transactions!$D:$D,"Sale")),"")
A366: KARNI-RINGTWIN-VAN-WHITE-BLUE | B366: DSGN-RINGTWIN-VAN | C366: Van Twin Ring | D366: ring twin | E366: Van | H366: white-blue | I366: 20000 | J366: =IF($I366="","",ROUND($I366*Dropdowns!$K$5,2)) -> 52 | K366: =IF($I366="","",ROUND($I366*Dropdowns!$K$6,2)) -> 48 | L366: =IF($I366="","",ROUND($I366*Dropdowns!$K$7,2)) -> 4100 | M366: =IFERROR(IF($B366="","",VLOOKUP($B366,Designs!$A$3:$AP$165,27,FALSE())),"") | N366: =IFERROR(IF(OR($I366="",$M366="",$M366=0),"",($I366-$M366)/$I366),"") | O366: 0 | P366: 0 | Q366: =IF($O366="","",$O366-IF($P366="",0,$P366)) -> 0 | R366: 2 | S366: =IF($O366="","",IF($Q366<=$R366,"⚠ REORDER","OK")) -> ⚠ REORDER | V366: 7117.19 | W366: Armenia | Z366: No | AA366: No | AB366: No | AC366: No | AD366: Active | AE366: =IFERROR(SUMIFS(Transactions!$F:$F,Transactions!$C:$C,$A366,Transactions!$D:$D,"Sale"),0) -> 0 | AF366: =IFERROR(SUMIFS(Transactions!$H:$H,Transactions!$C:$C,$A366,Transactions!$D:$D,"Sale"),0) -> 0 | AG366: =IFERROR(IF(maxifs(Transactions!$B:$B,Transactions!$C:$C,$A366,Transactions!$D:$D,"Sale")=0,"",maxifs(Transactions!$B:$B,Transactions!$C:$C,$A366,Transactions!$D:$D,"Sale")),"")
A367: KARNI-RINGTWIN-VAN-WHITE-BORDEAUX | B367: DSGN-RINGTWIN-VAN | C367: Van Twin Ring | D367: ring twin | E367: Van | H367: white-bordeaux | I367: 20000 | J367: =IF($I367="","",ROUND($I367*Dropdowns!$K$5,2)) -> 52 | K367: =IF($I367="","",ROUND($I367*Dropdowns!$K$6,2)) -> 48 | L367: =IF($I367="","",ROUND($I367*Dropdowns!$K$7,2)) -> 4100 | M367: =IFERROR(IF($B367="","",VLOOKUP($B367,Designs!$A$3:$AP$165,27,FALSE())),"") | N367: =IFERROR(IF(OR($I367="",$M367="",$M367=0),"",($I367-$M367)/$I367),"") | O367: 0 | P367: 0 | Q367: =IF($O367="","",$O367-IF($P367="",0,$P367)) -> 0 | R367: 2 | S367: =IF($O367="","",IF($Q367<=$R367,"⚠ REORDER","OK")) -> ⚠ REORDER | V367: 7117.19 | W367: Armenia | Z367: No | AA367: No | AB367: No | AC367: No | AD367: Active | AE367: =IFERROR(SUMIFS(Transactions!$F:$F,Transactions!$C:$C,$A367,Transactions!$D:$D,"Sale"),0) -> 0 | AF367: =IFERROR(SUMIFS(Transactions!$H:$H,Transactions!$C:$C,$A367,Transactions!$D:$D,"Sale"),0) -> 0 | AG367: =IFERROR(IF(maxifs(Transactions!$B:$B,Transactions!$C:$C,$A367,Transactions!$D:$D,"Sale")=0,"",maxifs(Transactions!$B:$B,Transactions!$C:$C,$A367,Transactions!$D:$D,"Sale")),"")
A368: KARNI-RINGTWIN-VAN-WHITE-TURQUOISE | B368: DSGN-RINGTWIN-VAN | C368: Van Twin Ring | D368: ring twin | E368: Van | H368: white-turquoise | I368: 20000 | J368: =IF($I368="","",ROUND($I368*Dropdowns!$K$5,2)) -> 52 | K368: =IF($I368="","",ROUND($I368*Dropdowns!$K$6,2)) -> 48 | L368: =IF($I368="","",ROUND($I368*Dropdowns!$K$7,2)) -> 4100 | M368: =IFERROR(IF($B368="","",VLOOKUP($B368,Designs!$A$3:$AP$165,27,FALSE())),"") | N368: =IFERROR(IF(OR($I368="",$M368="",$M368=0),"",($I368-$M368)/$I368),"") | O368: 0 | P368: 0 | Q368: =IF($O368="","",$O368-IF($P368="",0,$P368)) -> 0 | R368: 2 | S368: =IF($O368="","",IF($Q368<=$R368,"⚠ REORDER","OK")) -> ⚠ REORDER | V368: 7117.19 | W368: Armenia | Z368: No | AA368: No | AB368: No | AC368: No | AD368: Active | AE368: =IFERROR(SUMIFS(Transactions!$F:$F,Transactions!$C:$C,$A368,Transactions!$D:$D,"Sale"),0) -> 0 | AF368: =IFERROR(SUMIFS(Transactions!$H:$H,Transactions!$C:$C,$A368,Transactions!$D:$D,"Sale"),0) -> 0 | AG368: =IFERROR(IF(maxifs(Transactions!$B:$B,Transactions!$C:$C,$A368,Transactions!$D:$D,"Sale")=0,"",maxifs(Transactions!$B:$B,Transactions!$C:$C,$A368,Transactions!$D:$D,"Sale")),"")
A369: KARNI-RINGTWIN-VAN-WHITE-GREEN | B369: DSGN-RINGTWIN-VAN | C369: Van Twin Ring | D369: ring twin | E369: Van | H369: white-green | I369: 20000 | J369: =IF($I369="","",ROUND($I369*Dropdowns!$K$5,2)) -> 52 | K369: =IF($I369="","",ROUND($I369*Dropdowns!$K$6,2)) -> 48 | L369: =IF($I369="","",ROUND($I369*Dropdowns!$K$7,2)) -> 4100 | M369: =IFERROR(IF($B369="","",VLOOKUP($B369,Designs!$A$3:$AP$165,27,FALSE())),"") | N369: =IFERROR(IF(OR($I369="",$M369="",$M369=0),"",($I369-$M369)/$I369),"") | O369: 0 | P369: 0 | Q369: =IF($O369="","",$O369-IF($P369="",0,$P369)) -> 0 | R369: 2 | S369: =IF($O369="","",IF($Q369<=$R369,"⚠ REORDER","OK")) -> ⚠ REORDER | V369: 7117.19 | W369: Armenia | Z369: No | AA369: No | AB369: No | AC369: No | AD369: Active | AE369: =IFERROR(SUMIFS(Transactions!$F:$F,Transactions!$C:$C,$A369,Transactions!$D:$D,"Sale"),0) -> 0 | AF369: =IFERROR(SUMIFS(Transactions!$H:$H,Transactions!$C:$C,$A369,Transactions!$D:$D,"Sale"),0) -> 0 | AG369: =IFERROR(IF(maxifs(Transactions!$B:$B,Transactions!$C:$C,$A369,Transactions!$D:$D,"Sale")=0,"",maxifs(Transactions!$B:$B,Transactions!$C:$C,$A369,Transactions!$D:$D,"Sale")),"")
A370: KARNI-RINGTWIN-VISHAB-WHITE-BLUE | B370: DSGN-RINGTWIN-VISHAB | C370: Vishab Twin Ring | D370: ring twin | E370: Vishab | H370: white-blue | I370: 20000 | J370: =IF($I370="","",ROUND($I370*Dropdowns!$K$5,2)) -> 52 | K370: =IF($I370="","",ROUND($I370*Dropdowns!$K$6,2)) -> 48 | L370: =IF($I370="","",ROUND($I370*Dropdowns!$K$7,2)) -> 4100 | M370: =IFERROR(IF($B370="","",VLOOKUP($B370,Designs!$A$3:$AP$165,27,FALSE())),"") | N370: =IFERROR(IF(OR($I370="",$M370="",$M370=0),"",($I370-$M370)/$I370),"") | O370: 0 | P370: 0 | Q370: =IF($O370="","",$O370-IF($P370="",0,$P370)) -> 0 | R370: 2 | S370: =IF($O370="","",IF($Q370<=$R370,"⚠ REORDER","OK")) -> ⚠ REORDER | V370: 7117.19 | W370: Armenia | Z370: No | AA370: No | AB370: No | AC370: No | AD370: Active | AE370: =IFERROR(SUMIFS(Transactions!$F:$F,Transactions!$C:$C,$A370,Transactions!$D:$D,"Sale"),0) -> 0 | AF370: =IFERROR(SUMIFS(Transactions!$H:$H,Transactions!$C:$C,$A370,Transactions!$D:$D,"Sale"),0) -> 0 | AG370: =IFERROR(IF(maxifs(Transactions!$B:$B,Transactions!$C:$C,$A370,Transactions!$D:$D,"Sale")=0,"",maxifs(Transactions!$B:$B,Transactions!$C:$C,$A370,Transactions!$D:$D,"Sale")),"")
A371: KARNI-RINGTWIN-VISHAB-WHITE-BORDEAUX | B371: DSGN-RINGTWIN-VISHAB | C371: Vishab Twin Ring | D371: ring twin | E371: Vishab | H371: white-bordeaux | I371: 20000 | J371: =IF($I371="","",ROUND($I371*Dropdowns!$K$5,2)) -> 52 | K371: =IF($I371="","",ROUND($I371*Dropdowns!$K$6,2)) -> 48 | L371: =IF($I371="","",ROUND($I371*Dropdowns!$K$7,2)) -> 4100 | M371: =IFERROR(IF($B371="","",VLOOKUP($B371,Designs!$A$3:$AP$165,27,FALSE())),"") | N371: =IFERROR(IF(OR($I371="",$M371="",$M371=0),"",($I371-$M371)/$I371),"") | O371: 0 | P371: 0 | Q371: =IF($O371="","",$O371-IF($P371="",0,$P371)) -> 0 | R371: 2 | S371: =IF($O371="","",IF($Q371<=$R371,"⚠ REORDER","OK")) -> ⚠ REORDER | V371: 7117.19 | W371: Armenia | Z371: No | AA371: No | AB371: No | AC371: No | AD371: Active | AE371: =IFERROR(SUMIFS(Transactions!$F:$F,Transactions!$C:$C,$A371,Transactions!$D:$D,"Sale"),0) -> 0 | AF371: =IFERROR(SUMIFS(Transactions!$H:$H,Transactions!$C:$C,$A371,Transactions!$D:$D,"Sale"),0) -> 0 | AG371: =IFERROR(IF(maxifs(Transactions!$B:$B,Transactions!$C:$C,$A371,Transactions!$D:$D,"Sale")=0,"",maxifs(Transactions!$B:$B,Transactions!$C:$C,$A371,Transactions!$D:$D,"Sale")),"")
A372: KARNI-RINGTWIN-VISHAB-WHITE-TURQUOISE | B372: DSGN-RINGTWIN-VISHAB | C372: Vishab Twin Ring | D372: ring twin | E372: Vishab | H372: white-turquoise | I372: 20000 | J372: =IF($I372="","",ROUND($I372*Dropdowns!$K$5,2)) -> 52 | K372: =IF($I372="","",ROUND($I372*Dropdowns!$K$6,2)) -> 48 | L372: =IF($I372="","",ROUND($I372*Dropdowns!$K$7,2)) -> 4100 | M372: =IFERROR(IF($B372="","",VLOOKUP($B372,Designs!$A$3:$AP$165,27,FALSE())),"") | N372: =IFERROR(IF(OR($I372="",$M372="",$M372=0),"",($I372-$M372)/$I372),"") | O372: 0 | P372: 0 | Q372: =IF($O372="","",$O372-IF($P372="",0,$P372)) -> 0 | R372: 2 | S372: =IF($O372="","",IF($Q372<=$R372,"⚠ REORDER","OK")) -> ⚠ REORDER | V372: 7117.19 | W372: Armenia | Z372: No | AA372: No | AB372: No | AC372: No | AD372: Active | AE372: =IFERROR(SUMIFS(Transactions!$F:$F,Transactions!$C:$C,$A372,Transactions!$D:$D,"Sale"),0) -> 0 | AF372: =IFERROR(SUMIFS(Transactions!$H:$H,Transactions!$C:$C,$A372,Transactions!$D:$D,"Sale"),0) -> 0 | AG372: =IFERROR(IF(maxifs(Transactions!$B:$B,Transactions!$C:$C,$A372,Transactions!$D:$D,"Sale")=0,"",maxifs(Transactions!$B:$B,Transactions!$C:$C,$A372,Transactions!$D:$D,"Sale")),"")
A373: KARNI-RINGTWIN-VISHAB-WHITE-GREEN | B373: DSGN-RINGTWIN-VISHAB | C373: Vishab Twin Ring | D373: ring twin | E373: Vishab | H373: white-green | I373: 20000 | J373: =IF($I373="","",ROUND($I373*Dropdowns!$K$5,2)) -> 52 | K373: =IF($I373="","",ROUND($I373*Dropdowns!$K$6,2)) -> 48 | L373: =IF($I373="","",ROUND($I373*Dropdowns!$K$7,2)) -> 4100 | M373: =IFERROR(IF($B373="","",VLOOKUP($B373,Designs!$A$3:$AP$165,27,FALSE())),"") | N373: =IFERROR(IF(OR($I373="",$M373="",$M373=0),"",($I373-$M373)/$I373),"") | O373: 0 | P373: 0 | Q373: =IF($O373="","",$O373-IF($P373="",0,$P373)) -> 0 | R373: 2 | S373: =IF($O373="","",IF($Q373<=$R373,"⚠ REORDER","OK")) -> ⚠ REORDER | V373: 7117.19 | W373: Armenia | Z373: No | AA373: No | AB373: No | AC373: No | AD373: Active | AE373: =IFERROR(SUMIFS(Transactions!$F:$F,Transactions!$C:$C,$A373,Transactions!$D:$D,"Sale"),0) -> 0 | AF373: =IFERROR(SUMIFS(Transactions!$H:$H,Transactions!$C:$C,$A373,Transactions!$D:$D,"Sale"),0) -> 0 | AG373: =IFERROR(IF(maxifs(Transactions!$B:$B,Transactions!$C:$C,$A373,Transactions!$D:$D,"Sale")=0,"",maxifs(Transactions!$B:$B,Transactions!$C:$C,$A373,Transactions!$D:$D,"Sale")),"")
A374: KARNI-RING-VAN-M-BLUE | B374: DSGN-RING-VAN-M | C374: Van Ring | D374: Ring | E374: Van | G374: medium | H374: blue | I374: 20000 | J374: =IF($I374="","",ROUND($I374*Dropdowns!$K$5,2)) -> 52 | K374: =IF($I374="","",ROUND($I374*Dropdowns!$K$6,2)) -> 48 | L374: =IF($I374="","",ROUND($I374*Dropdowns!$K$7,2)) -> 4100 | M374: =IFERROR(IF($B374="","",VLOOKUP($B374,Designs!$A$3:$AP$165,27,FALSE())),"") | N374: =IFERROR(IF(OR($I374="",$M374="",$M374=0),"",($I374-$M374)/$I374),"") | O374: 0 | P374: 0 | Q374: =IF($O374="","",$O374-IF($P374="",0,$P374)) -> 0 | R374: 2 | S374: =IF($O374="","",IF($Q374<=$R374,"⚠ REORDER","OK")) -> ⚠ REORDER | V374: 7117.19 | W374: Armenia | Z374: No | AA374: No | AB374: No | AC374: No | AD374: Active | AE374: =IFERROR(SUMIFS(Transactions!$F:$F,Transactions!$C:$C,$A374,Transactions!$D:$D,"Sale"),0) -> 0 | AF374: =IFERROR(SUMIFS(Transactions!$H:$H,Transactions!$C:$C,$A374,Transactions!$D:$D,"Sale"),0) -> 0 | AG374: =IFERROR(IF(maxifs(Transactions!$B:$B,Transactions!$C:$C,$A374,Transactions!$D:$D,"Sale")=0,"",maxifs(Transactions!$B:$B,Transactions!$C:$C,$A374,Transactions!$D:$D,"Sale")),"")
A375: KARNI-RING-VAN-M-WHITE | B375: DSGN-RING-VAN-M | C375: Van Ring | D375: Ring | E375: Van | G375: medium | H375: white | I375: 20000 | J375: =IF($I375="","",ROUND($I375*Dropdowns!$K$5,2)) -> 52 | K375: =IF($I375="","",ROUND($I375*Dropdowns!$K$6,2)) -> 48 | L375: =IF($I375="","",ROUND($I375*Dropdowns!$K$7,2)) -> 4100 | M375: =IFERROR(IF($B375="","",VLOOKUP($B375,Designs!$A$3:$AP$165,27,FALSE())),"") | N375: =IFERROR(IF(OR($I375="",$M375="",$M375=0),"",($I375-$M375)/$I375),"") | O375: 0 | P375: 0 | Q375: =IF($O375="","",$O375-IF($P375="",0,$P375)) -> 0 | R375: 2 | S375: =IF($O375="","",IF($Q375<=$R375,"⚠ REORDER","OK")) -> ⚠ REORDER | V375: 7117.19 | W375: Armenia | Z375: No | AA375: No | AB375: No | AC375: No | AD375: Active | AE375: =IFERROR(SUMIFS(Transactions!$F:$F,Transactions!$C:$C,$A375,Transactions!$D:$D,"Sale"),0) -> 0 | AF375: =IFERROR(SUMIFS(Transactions!$H:$H,Transactions!$C:$C,$A375,Transactions!$D:$D,"Sale"),0) -> 0 | AG375: =IFERROR(IF(maxifs(Transactions!$B:$B,Transactions!$C:$C,$A375,Transactions!$D:$D,"Sale")=0,"",maxifs(Transactions!$B:$B,Transactions!$C:$C,$A375,Transactions!$D:$D,"Sale")),"")
A376: KARNI-RING-VAN-M-CAMEL | B376: DSGN-RING-VAN-M | C376: Van Ring | D376: Ring | E376: Van | G376: medium | H376: camel | I376: 20000 | J376: =IF($I376="","",ROUND($I376*Dropdowns!$K$5,2)) -> 52 | K376: =IF($I376="","",ROUND($I376*Dropdowns!$K$6,2)) -> 48 | L376: =IF($I376="","",ROUND($I376*Dropdowns!$K$7,2)) -> 4100 | M376: =IFERROR(IF($B376="","",VLOOKUP($B376,Designs!$A$3:$AP$165,27,FALSE())),"") | N376: =IFERROR(IF(OR($I376="",$M376="",$M376=0),"",($I376-$M376)/$I376),"") | O376: 0 | P376: 0 | Q376: =IF($O376="","",$O376-IF($P376="",0,$P376)) -> 0 | R376: 2 | S376: =IF($O376="","",IF($Q376<=$R376,"⚠ REORDER","OK")) -> ⚠ REORDER | V376: 7117.19 | W376: Armenia | Z376: No | AA376: No | AB376: No | AC376: No | AD376: Active | AE376: =IFERROR(SUMIFS(Transactions!$F:$F,Transactions!$C:$C,$A376,Transactions!$D:$D,"Sale"),0) -> 0 | AF376: =IFERROR(SUMIFS(Transactions!$H:$H,Transactions!$C:$C,$A376,Transactions!$D:$D,"Sale"),0) -> 0 | AG376: =IFERROR(IF(maxifs(Transactions!$B:$B,Transactions!$C:$C,$A376,Transactions!$D:$D,"Sale")=0,"",maxifs(Transactions!$B:$B,Transactions!$C:$C,$A376,Transactions!$D:$D,"Sale")),"")
A377: KARNI-RING-VAN-M-TURQUOISE | B377: DSGN-RING-VAN-M | C377: Van Ring | D377: Ring | E377: Van | G377: medium | H377: turquoise | I377: 20000 | J377: =IF($I377="","",ROUND($I377*Dropdowns!$K$5,2)) -> 52 | K377: =IF($I377="","",ROUND($I377*Dropdowns!$K$6,2)) -> 48 | L377: =IF($I377="","",ROUND($I377*Dropdowns!$K$7,2)) -> 4100 | M377: =IFERROR(IF($B377="","",VLOOKUP($B377,Designs!$A$3:$AP$165,27,FALSE())),"") | N377: =IFERROR(IF(OR($I377="",$M377="",$M377=0),"",($I377-$M377)/$I377),"") | O377: 0 | P377: 0 | Q377: =IF($O377="","",$O377-IF($P377="",0,$P377)) -> 0 | R377: 2 | S377: =IF($O377="","",IF($Q377<=$R377,"⚠ REORDER","OK")) -> ⚠ REORDER | V377: 7117.19 | W377: Armenia | Z377: No | AA377: No | AB377: No | AC377: No | AD377: Active | AE377: =IFERROR(SUMIFS(Transactions!$F:$F,Transactions!$C:$C,$A377,Transactions!$D:$D,"Sale"),0) -> 0 | AF377: =IFERROR(SUMIFS(Transactions!$H:$H,Transactions!$C:$C,$A377,Transactions!$D:$D,"Sale"),0) -> 0 | AG377: =IFERROR(IF(maxifs(Transactions!$B:$B,Transactions!$C:$C,$A377,Transactions!$D:$D,"Sale")=0,"",maxifs(Transactions!$B:$B,Transactions!$C:$C,$A377,Transactions!$D:$D,"Sale")),"")
A378: KARNI-RING-MARASH-M-BLUE-WHITE | B378: DSGN-RING-MARASH-M | C378: Marash Ring | D378: Ring | E378: Marash | G378: medium | H378: blue-white | I378: 20000 | J378: =IF($I378="","",ROUND($I378*Dropdowns!$K$5,2)) -> 52 | K378: =IF($I378="","",ROUND($I378*Dropdowns!$K$6,2)) -> 48 | L378: =IF($I378="","",ROUND($I378*Dropdowns!$K$7,2)) -> 4100 | M378: =IFERROR(IF($B378="","",VLOOKUP($B378,Designs!$A$3:$AP$165,27,FALSE())),"") | N378: =IFERROR(IF(OR($I378="",$M378="",$M378=0),"",($I378-$M378)/$I378),"") | O378: 0 | P378: 0 | Q378: =IF($O378="","",$O378-IF($P378="",0,$P378)) -> 0 | R378: 2 | S378: =IF($O378="","",IF($Q378<=$R378,"⚠ REORDER","OK")) -> ⚠ REORDER | V378: 7117.19 | W378: Armenia | Z378: No | AA378: No | AB378: No | AC378: No | AD378: Active | AE378: =IFERROR(SUMIFS(Transactions!$F:$F,Transactions!$C:$C,$A378,Transactions!$D:$D,"Sale"),0) -> 0 | AF378: =IFERROR(SUMIFS(Transactions!$H:$H,Transactions!$C:$C,$A378,Transactions!$D:$D,"Sale"),0) -> 0 | AG378: =IFERROR(IF(maxifs(Transactions!$B:$B,Transactions!$C:$C,$A378,Transactions!$D:$D,"Sale")=0,"",maxifs(Transactions!$B:$B,Transactions!$C:$C,$A378,Transactions!$D:$D,"Sale")),"")
A379: KARNI-RING-MARASH-M-WHITE-BLUE | B379: DSGN-RING-MARASH-M | C379: Marash Ring | D379: Ring | E379: Marash | G379: medium | H379: white-blue | I379: 20000 | J379: =IF($I379="","",ROUND($I379*Dropdowns!$K$5,2)) -> 52 | K379: =IF($I379="","",ROUND($I379*Dropdowns!$K$6,2)) -> 48 | L379: =IF($I379="","",ROUND($I379*Dropdowns!$K$7,2)) -> 4100 | M379: =IFERROR(IF($B379="","",VLOOKUP($B379,Designs!$A$3:$AP$165,27,FALSE())),"") | N379: =IFERROR(IF(OR($I379="",$M379="",$M379=0),"",($I379-$M379)/$I379),"") | O379: 0 | P379: 0 | Q379: =IF($O379="","",$O379-IF($P379="",0,$P379)) -> 0 | R379: 2 | S379: =IF($O379="","",IF($Q379<=$R379,"⚠ REORDER","OK")) -> ⚠ REORDER | V379: 7117.19 | W379: Armenia | Z379: No | AA379: No | AB379: No | AC379: No | AD379: Active | AE379: =IFERROR(SUMIFS(Transactions!$F:$F,Transactions!$C:$C,$A379,Transactions!$D:$D,"Sale"),0) -> 0 | AF379: =IFERROR(SUMIFS(Transactions!$H:$H,Transactions!$C:$C,$A379,Transactions!$D:$D,"Sale"),0) -> 0 | AG379: =IFERROR(IF(maxifs(Transactions!$B:$B,Transactions!$C:$C,$A379,Transactions!$D:$D,"Sale")=0,"",maxifs(Transactions!$B:$B,Transactions!$C:$C,$A379,Transactions!$D:$D,"Sale")),"")
A380: KARNI-RING-MARASH-M-WHITE-BORDEAUX | B380: DSGN-RING-MARASH-M | C380: Marash Ring | D380: Ring | E380: Marash | G380: medium | H380: white-bordeaux | I380: 20000 | J380: =IF($I380="","",ROUND($I380*Dropdowns!$K$5,2)) -> 52 | K380: =IF($I380="","",ROUND($I380*Dropdowns!$K$6,2)) -> 48 | L380: =IF($I380="","",ROUND($I380*Dropdowns!$K$7,2)) -> 4100 | M380: =IFERROR(IF($B380="","",VLOOKUP($B380,Designs!$A$3:$AP$165,27,FALSE())),"") | N380: =IFERROR(IF(OR($I380="",$M380="",$M380=0),"",($I380-$M380)/$I380),"") | O380: 0 | P380: 0 | Q380: =IF($O380="","",$O380-IF($P380="",0,$P380)) -> 0 | R380: 2 | S380: =IF($O380="","",IF($Q380<=$R380,"⚠ REORDER","OK")) -> ⚠ REORDER | V380: 7117.19 | W380: Armenia | Z380: No | AA380: No | AB380: No | AC380: No | AD380: Active | AE380: =IFERROR(SUMIFS(Transactions!$F:$F,Transactions!$C:$C,$A380,Transactions!$D:$D,"Sale"),0) -> 0 | AF380: =IFERROR(SUMIFS(Transactions!$H:$H,Transactions!$C:$C,$A380,Transactions!$D:$D,"Sale"),0) -> 0 | AG380: =IFERROR(IF(maxifs(Transactions!$B:$B,Transactions!$C:$C,$A380,Transactions!$D:$D,"Sale")=0,"",maxifs(Transactions!$B:$B,Transactions!$C:$C,$A380,Transactions!$D:$D,"Sale")),"")
A381: KARNI-RING-MARASH-M-TURQUOISE-BLUE | B381: DSGN-RING-MARASH-M | C381: Marash Ring | D381: Ring | E381: Marash | G381: medium | H381: turquoise-blue | I381: 20000 | J381: =IF($I381="","",ROUND($I381*Dropdowns!$K$5,2)) -> 52 | K381: =IF($I381="","",ROUND($I381*Dropdowns!$K$6,2)) -> 48 | L381: =IF($I381="","",ROUND($I381*Dropdowns!$K$7,2)) -> 4100 | M381: =IFERROR(IF($B381="","",VLOOKUP($B381,Designs!$A$3:$AP$165,27,FALSE())),"") | N381: =IFERROR(IF(OR($I381="",$M381="",$M381=0),"",($I381-$M381)/$I381),"") | O381: 0 | P381: 0 | Q381: =IF($O381="","",$O381-IF($P381="",0,$P381)) -> 0 | R381: 2 | S381: =IF($O381="","",IF($Q381<=$R381,"⚠ REORDER","OK")) -> ⚠ REORDER | V381: 7117.19 | W381: Armenia | Z381: No | AA381: No | AB381: No | AC381: No | AD381: Active | AE381: =IFERROR(SUMIFS(Transactions!$F:$F,Transactions!$C:$C,$A381,Transactions!$D:$D,"Sale"),0) -> 0 | AF381: =IFERROR(SUMIFS(Transactions!$H:$H,Transactions!$C:$C,$A381,Transactions!$D:$D,"Sale"),0) -> 0 | AG381: =IFERROR(IF(maxifs(Transactions!$B:$B,Transactions!$C:$C,$A381,Transactions!$D:$D,"Sale")=0,"",maxifs(Transactions!$B:$B,Transactions!$C:$C,$A381,Transactions!$D:$D,"Sale")),"")
A382: KARNI-RING-ARTSAKHIKHACHANAKHSH-M-BLUE-WHITE | B382: DSGN-RING-ARTSAKHIKHACHANAKHSH-M | C382: Artsakhi Khachanakhsh Ring | D382: Ring | E382: Artsakhi Khachanakhsh | G382: medium | H382: blue-white | I382: 20000 | J382: =IF($I382="","",ROUND($I382*Dropdowns!$K$5,2)) -> 52 | K382: =IF($I382="","",ROUND($I382*Dropdowns!$K$6,2)) -> 48 | L382: =IF($I382="","",ROUND($I382*Dropdowns!$K$7,2)) -> 4100 | M382: =IFERROR(IF($B382="","",VLOOKUP($B382,Designs!$A$3:$AP$165,27,FALSE())),"") | N382: =IFERROR(IF(OR($I382="",$M382="",$M382=0),"",($I382-$M382)/$I382),"") | O382: 0 | P382: 0 | Q382: =IF($O382="","",$O382-IF($P382="",0,$P382)) -> 0 | R382: 2 | S382: =IF($O382="","",IF($Q382<=$R382,"⚠ REORDER","OK")) -> ⚠ REORDER | V382: 7117.19 | W382: Armenia | Z382: No | AA382: No | AB382: No | AC382: No | AD382: Active | AE382: =IFERROR(SUMIFS(Transactions!$F:$F,Transactions!$C:$C,$A382,Transactions!$D:$D,"Sale"),0) -> 0 | AF382: =IFERROR(SUMIFS(Transactions!$H:$H,Transactions!$C:$C,$A382,Transactions!$D:$D,"Sale"),0) -> 0 | AG382: =IFERROR(IF(maxifs(Transactions!$B:$B,Transactions!$C:$C,$A382,Transactions!$D:$D,"Sale")=0,"",maxifs(Transactions!$B:$B,Transactions!$C:$C,$A382,Transactions!$D:$D,"Sale")),"")
A383: KARNI-RING-ARTSAKHIKHACHANAKHSH-M-WHITE-BLUE | B383: DSGN-RING-ARTSAKHIKHACHANAKHSH-M | C383: Artsakhi Khachanakhsh Ring | D383: Ring | E383: Artsakhi Khachanakhsh | G383: medium | H383: white-blue | I383: 20000 | J383: =IF($I383="","",ROUND($I383*Dropdowns!$K$5,2)) -> 52 | K383: =IF($I383="","",ROUND($I383*Dropdowns!$K$6,2)) -> 48 | L383: =IF($I383="","",ROUND($I383*Dropdowns!$K$7,2)) -> 4100 | M383: =IFERROR(IF($B383="","",VLOOKUP($B383,Designs!$A$3:$AP$165,27,FALSE())),"") | N383: =IFERROR(IF(OR($I383="",$M383="",$M383=0),"",($I383-$M383)/$I383),"") | O383: 0 | P383: 0 | Q383: =IF($O383="","",$O383-IF($P383="",0,$P383)) -> 0 | R383: 2 | S383: =IF($O383="","",IF($Q383<=$R383,"⚠ REORDER","OK")) -> ⚠ REORDER | V383: 7117.19 | W383: Armenia | Z383: No | AA383: No | AB383: No | AC383: No | AD383: Active | AE383: =IFERROR(SUMIFS(Transactions!$F:$F,Transactions!$C:$C,$A383,Transactions!$D:$D,"Sale"),0) -> 0 | AF383: =IFERROR(SUMIFS(Transactions!$H:$H,Transactions!$C:$C,$A383,Transactions!$D:$D,"Sale"),0) -> 0 | AG383: =IFERROR(IF(maxifs(Transactions!$B:$B,Transactions!$C:$C,$A383,Transactions!$D:$D,"Sale")=0,"",maxifs(Transactions!$B:$B,Transactions!$C:$C,$A383,Transactions!$D:$D,"Sale")),"")
A384: KARNI-RING-ARTSAKHIKHACHANAKHSH-M-BLUE-BORDEAUX | B384: DSGN-RING-ARTSAKHIKHACHANAKHSH-M | C384: Artsakhi Khachanakhsh Ring | D384: Ring | E384: Artsakhi Khachanakhsh | G384: medium | H384: blue-bordeaux | I384: 20000 | J384: =IF($I384="","",ROUND($I384*Dropdowns!$K$5,2)) -> 52 | K384: =IF($I384="","",ROUND($I384*Dropdowns!$K$6,2)) -> 48 | L384: =IF($I384="","",ROUND($I384*Dropdowns!$K$7,2)) -> 4100 | M384: =IFERROR(IF($B384="","",VLOOKUP($B384,Designs!$A$3:$AP$165,27,FALSE())),"") | N384: =IFERROR(IF(OR($I384="",$M384="",$M384=0),"",($I384-$M384)/$I384),"") | O384: 0 | P384: 0 | Q384: =IF($O384="","",$O384-IF($P384="",0,$P384)) -> 0 | R384: 2 | S384: =IF($O384="","",IF($Q384<=$R384,"⚠ REORDER","OK")) -> ⚠ REORDER | V384: 7117.19 | W384: Armenia | Z384: No | AA384: No | AB384: No | AC384: No | AD384: Active | AE384: =IFERROR(SUMIFS(Transactions!$F:$F,Transactions!$C:$C,$A384,Transactions!$D:$D,"Sale"),0) -> 0 | AF384: =IFERROR(SUMIFS(Transactions!$H:$H,Transactions!$C:$C,$A384,Transactions!$D:$D,"Sale"),0) -> 0 | AG384: =IFERROR(IF(maxifs(Transactions!$B:$B,Transactions!$C:$C,$A384,Transactions!$D:$D,"Sale")=0,"",maxifs(Transactions!$B:$B,Transactions!$C:$C,$A384,Transactions!$D:$D,"Sale")),"")
A385: KARNI-RING-ARTSAKHIKHACHANAKHSH-M-TURQUOISE | B385: DSGN-RING-ARTSAKHIKHACHANAKHSH-M | C385: Artsakhi Khachanakhsh Ring | D385: Ring | E385: Artsakhi Khachanakhsh | G385: medium | H385: turquoise | I385: 20000 | J385: =IF($I385="","",ROUND($I385*Dropdowns!$K$5,2)) -> 52 | K385: =IF($I385="","",ROUND($I385*Dropdowns!$K$6,2)) -> 48 | L385: =IF($I385="","",ROUND($I385*Dropdowns!$K$7,2)) -> 4100 | M385: =IFERROR(IF($B385="","",VLOOKUP($B385,Designs!$A$3:$AP$165,27,FALSE())),"") | N385: =IFERROR(IF(OR($I385="",$M385="",$M385=0),"",($I385-$M385)/$I385),"") | O385: 0 | P385: 0 | Q385: =IF($O385="","",$O385-IF($P385="",0,$P385)) -> 0 | R385: 2 | S385: =IF($O385="","",IF($Q385<=$R385,"⚠ REORDER","OK")) -> ⚠ REORDER | V385: 7117.19 | W385: Armenia | Z385: No | AA385: No | AB385: No | AC385: No | AD385: Active | AE385: =IFERROR(SUMIFS(Transactions!$F:$F,Transactions!$C:$C,$A385,Transactions!$D:$D,"Sale"),0) -> 0 | AF385: =IFERROR(SUMIFS(Transactions!$H:$H,Transactions!$C:$C,$A385,Transactions!$D:$D,"Sale"),0) -> 0 | AG385: =IFERROR(IF(maxifs(Transactions!$B:$B,Transactions!$C:$C,$A385,Transactions!$D:$D,"Sale")=0,"",maxifs(Transactions!$B:$B,Transactions!$C:$C,$A385,Transactions!$D:$D,"Sale")),"")
... A426: KARNI-PEND-VISHABAREVAGORG-L-TURQUOISE | B426: DSGN-PEND-VISHABAREVAGORG-L | C426: Արեւագորգի Վիշապ | D426: Pendant | E426: Vishab Arevagorg | G426: large | H426: turquoise | I426: 29500 | J426: =IF($I426="","",ROUND($I426*Dropdowns!$K$5,2)) -> 76.7 | K426: =IF($I426="","",ROUND($I426*Dropdowns!$K$6,2)) -> 70.8 | L426: =IF($I426="","",ROUND($I426*Dropdowns!$K$7,2)) -> 6047.5 | M426: =IFERROR(IF($B426="","",VLOOKUP($B426,Designs!$A$3:$AP$165,27,FALSE())),"") | N426: =IFERROR(IF(OR($I426="",$M426="",$M426=0),"",($I426-$M426)/$I426),"") | O426: 0 | P426: 0 | Q426: =IF($O426="","",$O426-IF($P426="",0,$P426)) -> 0 | R426: 2 | S426: =IF($O426="","",IF($Q426<=$R426,"⚠ REORDER","OK")) -> ⚠ REORDER | V426: 7117.19 | W426: Armenia | Z426: No | AA426: No | AB426: No | AC426: No | AD426: Active | AE426: =IFERROR(SUMIFS(Transactions!$F:$F,Transactions!$C:$C,$A426,Transactions!$D:$D,"Sale"),0) -> 0 | AF426: =IFERROR(SUMIFS(Transactions!$H:$H,Transactions!$C:$C,$A426,Transactions!$D:$D,"Sale"),0) -> 0 | AG426: =IFERROR(IF(maxifs(Transactions!$B:$B,Transactions!$C:$C,$A426,Transactions!$D:$D,"Sale")=0,"",maxifs(Transactions!$B:$B,Transactions!$C:$C,$A426,Transactions!$D:$D,"Sale")),"")
A427: KARNI-CHNECK-MARASH-BLUE | B427: DSGN-CHNECK-MARASH | C427: Marash Chain Necklace | D427: chain necklace | E427: Marash | H427: blue | I427: 20000 | J427: =IF($I427="","",ROUND($I427*Dropdowns!$K$5,2)) -> 52 | K427: =IF($I427="","",ROUND($I427*Dropdowns!$K$6,2)) -> 48 | L427: =IF($I427="","",ROUND($I427*Dropdowns!$K$7,2)) -> 4100 | M427: =IFERROR(IF($B427="","",VLOOKUP($B427,Designs!$A$3:$AP$165,27,FALSE())),"") | N427: =IFERROR(IF(OR($I427="",$M427="",$M427=0),"",($I427-$M427)/$I427),"") | O427: 0 | P427: 0 | Q427: =IF($O427="","",$O427-IF($P427="",0,$P427)) -> 0 | R427: 2 | S427: =IF($O427="","",IF($Q427<=$R427,"⚠ REORDER","OK")) -> ⚠ REORDER | V427: 7117.19 | W427: Armenia | Z427: No | AA427: No | AB427: No | AC427: No | AD427: Active | AE427: =IFERROR(SUMIFS(Transactions!$F:$F,Transactions!$C:$C,$A427,Transactions!$D:$D,"Sale"),0) -> 0 | AF427: =IFERROR(SUMIFS(Transactions!$H:$H,Transactions!$C:$C,$A427,Transactions!$D:$D,"Sale"),0) -> 0 | AG427: =IFERROR(IF(maxifs(Transactions!$B:$B,Transactions!$C:$C,$A427,Transactions!$D:$D,"Sale")=0,"",maxifs(Transactions!$B:$B,Transactions!$C:$C,$A427,Transactions!$D:$D,"Sale")),"")
A428: KARNI-CHNECK-MARASH-WHITE | B428: DSGN-CHNECK-MARASH | C428: Marash Chain Necklace | D428: chain necklace | E428: Marash | H428: white | I428: 20000 | J428: =IF($I428="","",ROUND($I428*Dropdowns!$K$5,2)) -> 52 | K428: =IF($I428="","",ROUND($I428*Dropdowns!$K$6,2)) -> 48 | L428: =IF($I428="","",ROUND($I428*Dropdowns!$K$7,2)) -> 4100 | M428: =IFERROR(IF($B428="","",VLOOKUP($B428,Designs!$A$3:$AP$165,27,FALSE())),"") | N428: =IFERROR(IF(OR($I428="",$M428="",$M428=0),"",($I428-$M428)/$I428),"") | O428: 0 | P428: 0 | Q428: =IF($O428="","",$O428-IF($P428="",0,$P428)) -> 0 | R428: 2 | S428: =IF($O428="","",IF($Q428<=$R428,"⚠ REORDER","OK")) -> ⚠ REORDER | V428: 7117.19 | W428: Armenia | Z428: No | AA428: No | AB428: No | AC428: No | AD428: Active | AE428: =IFERROR(SUMIFS(Transactions!$F:$F,Transactions!$C:$C,$A428,Transactions!$D:$D,"Sale"),0) -> 0 | AF428: =IFERROR(SUMIFS(Transactions!$H:$H,Transactions!$C:$C,$A428,Transactions!$D:$D,"Sale"),0) -> 0 | AG428: =IFERROR(IF(maxifs(Transactions!$B:$B,Transactions!$C:$C,$A428,Transactions!$D:$D,"Sale")=0,"",maxifs(Transactions!$B:$B,Transactions!$C:$C,$A428,Transactions!$D:$D,"Sale")),"")
A429: KARNI-CHNECK-MARASH-BORDEAUX | B429: DSGN-CHNECK-MARASH | C429: Marash Chain Necklace | D429: chain necklace | E429: Marash | H429: bordeaux | I429: 20000 | J429: =IF($I429="","",ROUND($I429*Dropdowns!$K$5,2)) -> 52 | K429: =IF($I429="","",ROUND($I429*Dropdowns!$K$6,2)) -> 48 | L429: =IF($I429="","",ROUND($I429*Dropdowns!$K$7,2)) -> 4100 | M429: =IFERROR(IF($B429="","",VLOOKUP($B429,Designs!$A$3:$AP$165,27,FALSE())),"") | N429: =IFERROR(IF(OR($I429="",$M429="",$M429=0),"",($I429-$M429)/$I429),"") | O429: 0 | P429: 0 | Q429: =IF($O429="","",$O429-IF($P429="",0,$P429)) -> 0 | R429: 2 | S429: =IF($O429="","",IF($Q429<=$R429,"⚠ REORDER","OK")) -> ⚠ REORDER | V429: 7117.19 | W429: Armenia | Z429: No | AA429: No | AB429: No | AC429: No | AD429: Active | AE429: =IFERROR(SUMIFS(Transactions!$F:$F,Transactions!$C:$C,$A429,Transactions!$D:$D,"Sale"),0) -> 0 | AF429: =IFERROR(SUMIFS(Transactions!$H:$H,Transactions!$C:$C,$A429,Transactions!$D:$D,"Sale"),0) -> 0 | AG429: =IFERROR(IF(maxifs(Transactions!$B:$B,Transactions!$C:$C,$A429,Transactions!$D:$D,"Sale")=0,"",maxifs(Transactions!$B:$B,Transactions!$C:$C,$A429,Transactions!$D:$D,"Sale")),"")
A430: KARNI-CHNECK-MARASH-TURQUOISE | B430: DSGN-CHNECK-MARASH | C430: Marash Chain Necklace | D430: chain necklace | E430: Marash | H430: turquoise | I430: 20000 | J430: =IF($I430="","",ROUND($I430*Dropdowns!$K$5,2)) -> 52 | K430: =IF($I430="","",ROUND($I430*Dropdowns!$K$6,2)) -> 48 | L430: =IF($I430="","",ROUND($I430*Dropdowns!$K$7,2)) -> 4100 | M430: =IFERROR(IF($B430="","",VLOOKUP($B430,Designs!$A$3:$AP$165,27,FALSE())),"") | N430: =IFERROR(IF(OR($I430="",$M430="",$M430=0),"",($I430-$M430)/$I430),"") | O430: 0 | P430: 0 | Q430: =IF($O430="","",$O430-IF($P430="",0,$P430)) -> 0 | R430: 2 | S430: =IF($O430="","",IF($Q430<=$R430,"⚠ REORDER","OK")) -> ⚠ REORDER | V430: 7117.19 | W430: Armenia | Z430: No | AA430: No | AB430: No | AC430: No | AD430: Active | AE430: =IFERROR(SUMIFS(Transactions!$F:$F,Transactions!$C:$C,$A430,Transactions!$D:$D,"Sale"),0) -> 0 | AF430: =IFERROR(SUMIFS(Transactions!$H:$H,Transactions!$C:$C,$A430,Transactions!$D:$D,"Sale"),0) -> 0 | AG430: =IFERROR(IF(maxifs(Transactions!$B:$B,Transactions!$C:$C,$A430,Transactions!$D:$D,"Sale")=0,"",maxifs(Transactions!$B:$B,Transactions!$C:$C,$A430,Transactions!$D:$D,"Sale")),"")
A431: KARNI-CHNECK-MARASH-GREEN | B431: DSGN-CHNECK-MARASH | C431: Marash Chain Necklace | D431: chain necklace | E431: Marash | H431: green | I431: 20000 | J431: =IF($I431="","",ROUND($I431*Dropdowns!$K$5,2)) -> 52 | K431: =IF($I431="","",ROUND($I431*Dropdowns!$K$6,2)) -> 48 | L431: =IF($I431="","",ROUND($I431*Dropdowns!$K$7,2)) -> 4100 | M431: =IFERROR(IF($B431="","",VLOOKUP($B431,Designs!$A$3:$AP$165,27,FALSE())),"") | N431: =IFERROR(IF(OR($I431="",$M431="",$M431=0),"",($I431-$M431)/$I431),"") | O431: 0 | P431: 0 | Q431: =IF($O431="","",$O431-IF($P431="",0,$P431)) -> 0 | R431: 2 | S431: =IF($O431="","",IF($Q431<=$R431,"⚠ REORDER","OK")) -> ⚠ REORDER | V431: 7117.19 | W431: Armenia | Z431: No | AA431: No | AB431: No | AC431: No | AD431: Active | AE431: =IFERROR(SUMIFS(Transactions!$F:$F,Transactions!$C:$C,$A431,Transactions!$D:$D,"Sale"),0) -> 0 | AF431: =IFERROR(SUMIFS(Transactions!$H:$H,Transactions!$C:$C,$A431,Transactions!$D:$D,"Sale"),0) -> 0 | AG431: =IFERROR(IF(maxifs(Transactions!$B:$B,Transactions!$C:$C,$A431,Transactions!$D:$D,"Sale")=0,"",maxifs(Transactions!$B:$B,Transactions!$C:$C,$A431,Transactions!$D:$D,"Sale")),"")
A432: KARNI-CHNECK-VAN-BLUE | B432: DSGN-CHNECK-VAN | C432: Van Chain Necklace | D432: chain necklace | E432: Van | H432: blue | I432: 20000 | J432: =IF($I432="","",ROUND($I432*Dropdowns!$K$5,2)) -> 52 | K432: =IF($I432="","",ROUND($I432*Dropdowns!$K$6,2)) -> 48 | L432: =IF($I432="","",ROUND($I432*Dropdowns!$K$7,2)) -> 4100 | M432: =IFERROR(IF($B432="","",VLOOKUP($B432,Designs!$A$3:$AP$165,27,FALSE())),"") | N432: =IFERROR(IF(OR($I432="",$M432="",$M432=0),"",($I432-$M432)/$I432),"") | O432: 0 | P432: 0 | Q432: =IF($O432="","",$O432-IF($P432="",0,$P432)) -> 0 | R432: 2 | S432: =IF($O432="","",IF($Q432<=$R432,"⚠ REORDER","OK")) -> ⚠ REORDER | V432: 7117.19 | W432: Armenia | Z432: No | AA432: No | AB432: No | AC432: No | AD432: Active | AE432: =IFERROR(SUMIFS(Transactions!$F:$F,Transactions!$C:$C,$A432,Transactions!$D:$D,"Sale"),0) -> 0 | AF432: =IFERROR(SUMIFS(Transactions!$H:$H,Transactions!$C:$C,$A432,Transactions!$D:$D,"Sale"),0) -> 0 | AG432: =IFERROR(IF(maxifs(Transactions!$B:$B,Transactions!$C:$C,$A432,Transactions!$D:$D,"Sale")=0,"",maxifs(Transactions!$B:$B,Transactions!$C:$C,$A432,Transactions!$D:$D,"Sale")),"")
A433: KARNI-CHNECK-VAN-WHITE | B433: DSGN-CHNECK-VAN | C433: Van Chain Necklace | D433: chain necklace | E433: Van | H433: white | I433: 20000 | J433: =IF($I433="","",ROUND($I433*Dropdowns!$K$5,2)) -> 52 | K433: =IF($I433="","",ROUND($I433*Dropdowns!$K$6,2)) -> 48 | L433: =IF($I433="","",ROUND($I433*Dropdowns!$K$7,2)) -> 4100 | M433: =IFERROR(IF($B433="","",VLOOKUP($B433,Designs!$A$3:$AP$165,27,FALSE())),"") | N433: =IFERROR(IF(OR($I433="",$M433="",$M433=0),"",($I433-$M433)/$I433),"") | O433: 0 | P433: 0 | Q433: =IF($O433="","",$O433-IF($P433="",0,$P433)) -> 0 | R433: 2 | S433: =IF($O433="","",IF($Q433<=$R433,"⚠ REORDER","OK")) -> ⚠ REORDER | V433: 7117.19 | W433: Armenia | Z433: No | AA433: No | AB433: No | AC433: No | AD433: Active | AE433: =IFERROR(SUMIFS(Transactions!$F:$F,Transactions!$C:$C,$A433,Transactions!$D:$D,"Sale"),0) -> 0 | AF433: =IFERROR(SUMIFS(Transactions!$H:$H,Transactions!$C:$C,$A433,Transactions!$D:$D,"Sale"),0) -> 0 | AG433: =IFERROR(IF(maxifs(Transactions!$B:$B,Transactions!$C:$C,$A433,Transactions!$D:$D,"Sale")=0,"",maxifs(Transactions!$B:$B,Transactions!$C:$C,$A433,Transactions!$D:$D,"Sale")),"")
A434: KARNI-CHNECK-VAN-BORDEAUX | B434: DSGN-CHNECK-VAN | C434: Van Chain Necklace | D434: chain necklace | E434: Van | H434: bordeaux | I434: 20000 | J434: =IF($I434="","",ROUND($I434*Dropdowns!$K$5,2)) -> 52 | K434: =IF($I434="","",ROUND($I434*Dropdowns!$K$6,2)) -> 48 | L434: =IF($I434="","",ROUND($I434*Dropdowns!$K$7,2)) -> 4100 | M434: =IFERROR(IF($B434="","",VLOOKUP($B434,Designs!$A$3:$AP$165,27,FALSE())),"") | N434: =IFERROR(IF(OR($I434="",$M434="",$M434=0),"",($I434-$M434)/$I434),"") | O434: 0 | P434: 0 | Q434: =IF($O434="","",$O434-IF($P434="",0,$P434)) -> 0 | R434: 2 | S434: =IF($O434="","",IF($Q434<=$R434,"⚠ REORDER","OK")) -> ⚠ REORDER | V434: 7117.19 | W434: Armenia | Z434: No | AA434: No | AB434: No | AC434: No | AD434: Active | AE434: =IFERROR(SUMIFS(Transactions!$F:$F,Transactions!$C:$C,$A434,Transactions!$D:$D,"Sale"),0) -> 0 | AF434: =IFERROR(SUMIFS(Transactions!$H:$H,Transactions!$C:$C,$A434,Transactions!$D:$D,"Sale"),0) -> 0 | AG434: =IFERROR(IF(maxifs(Transactions!$B:$B,Transactions!$C:$C,$A434,Transactions!$D:$D,"Sale")=0,"",maxifs(Transactions!$B:$B,Transactions!$C:$C,$A434,Transactions!$D:$D,"Sale")),"")
A435: KARNI-CHNECK-VAN-TURQUOISE | B435: DSGN-CHNECK-VAN | C435: Van Chain Necklace | D435: chain necklace | E435: Van | H435: turquoise | I435: 20000 | J435: =IF($I435="","",ROUND($I435*Dropdowns!$K$5,2)) -> 52 | K435: =IF($I435="","",ROUND($I435*Dropdowns!$K$6,2)) -> 48 | L435: =IF($I435="","",ROUND($I435*Dropdowns!$K$7,2)) -> 4100 | M435: =IFERROR(IF($B435="","",VLOOKUP($B435,Designs!$A$3:$AP$165,27,FALSE())),"") | N435: =IFERROR(IF(OR($I435="",$M435="",$M435=0),"",($I435-$M435)/$I435),"") | O435: 0 | P435: 0 | Q435: =IF($O435="","",$O435-IF($P435="",0,$P435)) -> 0 | R435: 2 | S435: =IF($O435="","",IF($Q435<=$R435,"⚠ REORDER","OK")) -> ⚠ REORDER | V435: 7117.19 | W435: Armenia | Z435: No | AA435: No | AB435: No | AC435: No | AD435: Active | AE435: =IFERROR(SUMIFS(Transactions!$F:$F,Transactions!$C:$C,$A435,Transactions!$D:$D,"Sale"),0) -> 0 | AF435: =IFERROR(SUMIFS(Transactions!$H:$H,Transactions!$C:$C,$A435,Transactions!$D:$D,"Sale"),0) -> 0 | AG435: =IFERROR(IF(maxifs(Transactions!$B:$B,Transactions!$C:$C,$A435,Transactions!$D:$D,"Sale")=0,"",maxifs(Transactions!$B:$B,Transactions!$C:$C,$A435,Transactions!$D:$D,"Sale")),"")
A436: KARNI-CHNECK-VAN-GREEN | B436: DSGN-CHNECK-VAN | C436: Van Chain Necklace | D436: chain necklace | E436: Van | H436: green | I436: 20000 | J436: =IF($I436="","",ROUND($I436*Dropdowns!$K$5,2)) -> 52 | K436: =IF($I436="","",ROUND($I436*Dropdowns!$K$6,2)) -> 48 | L436: =IF($I436="","",ROUND($I436*Dropdowns!$K$7,2)) -> 4100 | M436: =IFERROR(IF($B436="","",VLOOKUP($B436,Designs!$A$3:$AP$165,27,FALSE())),"") | N436: =IFERROR(IF(OR($I436="",$M436="",$M436=0),"",($I436-$M436)/$I436),"") | O436: 0 | P436: 0 | Q436: =IF($O436="","",$O436-IF($P436="",0,$P436)) -> 0 | R436: 2 | S436: =IF($O436="","",IF($Q436<=$R436,"⚠ REORDER","OK")) -> ⚠ REORDER | V436: 7117.19 | W436: Armenia | Z436: No | AA436: No | AB436: No | AC436: No | AD436: Active | AE436: =IFERROR(SUMIFS(Transactions!$F:$F,Transactions!$C:$C,$A436,Transactions!$D:$D,"Sale"),0) -> 0 | AF436: =IFERROR(SUMIFS(Transactions!$H:$H,Transactions!$C:$C,$A436,Transactions!$D:$D,"Sale"),0) -> 0 | AG436: =IFERROR(IF(maxifs(Transactions!$B:$B,Transactions!$C:$C,$A436,Transactions!$D:$D,"Sale")=0,"",maxifs(Transactions!$B:$B,Transactions!$C:$C,$A436,Transactions!$D:$D,"Sale")),"")
A437: KARNI-CHNECK-VISHAB-BLUE | B437: DSGN-CHNECK-VISHAB | C437: Vishab Chain Necklace | D437: chain necklace | E437: Vishab | H437: blue | I437: 20000 | J437: =IF($I437="","",ROUND($I437*Dropdowns!$K$5,2)) -> 52 | K437: =IF($I437="","",ROUND($I437*Dropdowns!$K$6,2)) -> 48 | L437: =IF($I437="","",ROUND($I437*Dropdowns!$K$7,2)) -> 4100 | M437: =IFERROR(IF($B437="","",VLOOKUP($B437,Designs!$A$3:$AP$165,27,FALSE())),"") | N437: =IFERROR(IF(OR($I437="",$M437="",$M437=0),"",($I437-$M437)/$I437),"") | O437: 0 | P437: 0 | Q437: =IF($O437="","",$O437-IF($P437="",0,$P437)) -> 0 | R437: 2 | S437: =IF($O437="","",IF($Q437<=$R437,"⚠ REORDER","OK")) -> ⚠ REORDER | V437: 7117.19 | W437: Armenia | Z437: No | AA437: No | AB437: No | AC437: No | AD437: Active | AE437: =IFERROR(SUMIFS(Transactions!$F:$F,Transactions!$C:$C,$A437,Transactions!$D:$D,"Sale"),0) -> 0 | AF437: =IFERROR(SUMIFS(Transactions!$H:$H,Transactions!$C:$C,$A437,Transactions!$D:$D,"Sale"),0) -> 0 | AG437: =IFERROR(IF(maxifs(Transactions!$B:$B,Transactions!$C:$C,$A437,Transactions!$D:$D,"Sale")=0,"",maxifs(Transactions!$B:$B,Transactions!$C:$C,$A437,Transactions!$D:$D,"Sale")),"")
A438: KARNI-CHNECK-VISHAB-WHITE | B438: DSGN-CHNECK-VISHAB | C438: Vishab Chain Necklace | D438: chain necklace | E438: Vishab | H438: white | I438: 20000 | J438: =IF($I438="","",ROUND($I438*Dropdowns!$K$5,2)) -> 52 | K438: =IF($I438="","",ROUND($I438*Dropdowns!$K$6,2)) -> 48 | L438: =IF($I438="","",ROUND($I438*Dropdowns!$K$7,2)) -> 4100 | M438: =IFERROR(IF($B438="","",VLOOKUP($B438,Designs!$A$3:$AP$165,27,FALSE())),"") | N438: =IFERROR(IF(OR($I438="",$M438="",$M438=0),"",($I438-$M438)/$I438),"") | O438: 0 | P438: 0 | Q438: =IF($O438="","",$O438-IF($P438="",0,$P438)) -> 0 | R438: 2 | S438: =IF($O438="","",IF($Q438<=$R438,"⚠ REORDER","OK")) -> ⚠ REORDER | V438: 7117.19 | W438: Armenia | Z438: No | AA438: No | AB438: No | AC438: No | AD438: Active | AE438: =IFERROR(SUMIFS(Transactions!$F:$F,Transactions!$C:$C,$A438,Transactions!$D:$D,"Sale"),0) -> 0 | AF438: =IFERROR(SUMIFS(Transactions!$H:$H,Transactions!$C:$C,$A438,Transactions!$D:$D,"Sale"),0) -> 0 | AG438: =IFERROR(IF(maxifs(Transactions!$B:$B,Transactions!$C:$C,$A438,Transactions!$D:$D,"Sale")=0,"",maxifs(Transactions!$B:$B,Transactions!$C:$C,$A438,Transactions!$D:$D,"Sale")),"")
... A476: KARNI-CHBRAC-VISHABAREVAGORG-GREEN | B476: DSGN-CHBRAC-VISHABAREVAGORG | C476: Արեւագորգի Վիշապ | D476: chain bracelet | E476: Vishab Arevagorg | H476: green | I476: 17000 | J476: =IF($I476="","",ROUND($I476*Dropdowns!$K$5,2)) -> 44.2 | K476: =IF($I476="","",ROUND($I476*Dropdowns!$K$6,2)) -> 40.8 | L476: =IF($I476="","",ROUND($I476*Dropdowns!$K$7,2)) -> 3485 | M476: =IFERROR(IF($B476="","",VLOOKUP($B476,Designs!$A$3:$AP$165,27,FALSE())),"") | N476: =IFERROR(IF(OR($I476="",$M476="",$M476=0),"",($I476-$M476)/$I476),"") | O476: 0 | P476: 0 | Q476: =IF($O476="","",$O476-IF($P476="",0,$P476)) -> 0 | R476: 2 | S476: =IF($O476="","",IF($Q476<=$R476,"⚠ REORDER","OK")) -> ⚠ REORDER | V476: 7117.19 | W476: Armenia | Z476: No | AA476: No | AB476: No | AC476: No | AD476: Active | AE476: =IFERROR(SUMIFS(Transactions!$F:$F,Transactions!$C:$C,$A476,Transactions!$D:$D,"Sale"),0) -> 0 | AF476: =IFERROR(SUMIFS(Transactions!$H:$H,Transactions!$C:$C,$A476,Transactions!$D:$D,"Sale"),0) -> 0 | AG476: =IFERROR(IF(maxifs(Transactions!$B:$B,Transactions!$C:$C,$A476,Transactions!$D:$D,"Sale")=0,"",maxifs(Transactions!$B:$B,Transactions!$C:$C,$A476,Transactions!$D:$D,"Sale")),"")

Sheet Transactions
A1: Txn ID | B1: Date | C1: SKU | D1: Type | E1: Channel | F1: Qty | G1: Unit price (AMD) | H1: Line total (AMD) | I1: Customer | J1: Order ref | K1: Notes
A2: T0001 | B2: 46152 | C2: KARNI-PEND-ALPHA-AYB-RED | D2: Sale | E2: Instagram DM | F2: 1 | G2: 19000 | H2: =IF(OR($F2="",$G2=""),"",$F2*$G2) -> 19000 | I2: @customer1 | J2: IG-2210
A3: T0002 | B3: 46154 | C3: KARNI-EARRNG-VAN-M-CAMEL | D3: Sale | E3: Cafesjian Center | F3: 1 | G3: 27000 | H3: =IF(OR($F3="",$G3=""),"",$F3*$G3) -> 27000
A4: T0003 | B4: 46157 | C4: KARNI-PEND-ALPHA-AYB-RED | D4: Restock | F4: 10 | G4: 0 | H4: =IF(OR($F4="",$G4=""),"",$F4*$G4) -> 0 | K4: Atelier batch
H5: =IF(OR($F5="",$G5=""),"",$F5*$G5)
H6: =IF(OR($F6="",$G6=""),"",$F6*$G6)
H7: =IF(OR($F7="",$G7=""),"",$F7*$G7)
H8: =IF(OR($F8="",$G8=""),"",$F8*$G8)
H9: =IF(OR($F9="",$G9=""),"",$F9*$G9)
H10: =IF(OR($F10="",$G10=""),"",$F10*$G10)
H11: =IF(OR($F11="",$G11=""),"",$F11*$G11)
H12: =IF(OR($F12="",$G12=""),"",$F12*$G12)
H13: =IF(OR($F13="",$G13=""),"",$F13*$G13)
H14: =IF(OR($F14="",$G14=""),"",$F14*$G14)
H15: =IF(OR($F15="",$G15=""),"",$F15*$G15)
H16: =IF(OR($F16="",$G16=""),"",$F16*$G16)
... H400: =IF(OR($F400="",$G400=""),"",$F400*$G400)

Sheet Dashboard
A1: Karni Jewellery — Analytics Dashboard
A2: Live metrics. Update as Variants & Transactions fill in.
A4: INVENTORY HEALTH
A5: Total SKUs | B5: =COUNTA(Variants!$A$3:$A$476) -> 474
A6: Active SKUs | B6: =COUNTIF(Variants!$AD$3:$AD$476,"Active") -> 474
A7: Total units in stock | B7: =SUM(Variants!$O$3:$O$476) -> 0
A8: Stock value at retail (AMD) | B8: =SUMPRODUCT(Variants!$O$3:$O$476,Variants!$I$3:$I$476) -> 0
A9: Stock value at cost (AMD) | B9: =IF(SUM(Variants!$M$3:$M$476)=0,"— (add costs)",SUMPRODUCT(Variants!$O$3:$O$476,IF(ISNUMBER(Variants!$M$3:$M$476),Variants!$M$3:$M$476,0))) -> — (add costs)
A10: SKUs needing reorder | B10: =COUNTIF(Variants!$S$3:$S$476,"⚠ REORDER") -> 474
A11: Out-of-stock SKUs | B11: =COUNTIF(Variants!$O$3:$O$476,0) -> 474
A13: SALES PERFORMANCE
A14: Total units sold | B14: =SUMIF(Transactions!$D:$D,"Sale",Transactions!$F:$F) -> 2
A15: Total revenue (AMD) | B15: =SUMIF(Transactions!$D:$D,"Sale",Transactions!$H:$H) -> 46000
A16: Total revenue (USD) | B16: =SUMIF(Transactions!$D:$D,"Sale",Transactions!$H:$H)*Dropdowns!$K$5 -> 119.6
A17: Avg order value (AMD) | B17: =IFERROR(SUMIF(Transactions!$D:$D,"Sale",Transactions!$H:$H)/COUNTIF(Transactions!$D:$D,"Sale"),0) -> 23000
A18: # of sales transactions | B18: =COUNTIF(Transactions!$D:$D,"Sale") -> 2
A20: PROFITABILITY
A21: Avg gross margin % | B21: =IFERROR(AVERAGEIF(Designs!$AB$3:$AB$165,"<>",Designs!$AB$3:$AB$165),"— (add costs)") -> — (add costs)
A22: Designs with cost data | B22: =COUNT(Designs!$AA$3:$AA$165) -> 0
A24: REVENUE BY CHANNEL (AMD)
A25: Website | B25: =SUMIFS(Transactions!$H:$H,Transactions!$D:$D,"Sale",Transactions!$E:$E,"Website") -> 0
A26: Instagram DM | B26: =SUMIFS(Transactions!$H:$H,Transactions!$D:$D,"Sale",Transactions!$E:$E,"Instagram DM") -> 19000
A27: Cafesjian Center | B27: =SUMIFS(Transactions!$H:$H,Transactions!$D:$D,"Sale",Transactions!$E:$E,"Cafesjian Center") -> 27000
A28: Made By Armenia | B28: =SUMIFS(Transactions!$H:$H,Transactions!$D:$D,"Sale",Transactions!$E:$E,"Made By Armenia") -> 0
A29: Matenadaran | B29: =SUMIFS(Transactions!$H:$H,Transactions!$D:$D,"Sale",Transactions!$E:$E,"Matenadaran") -> 0
A30: UMA | B30: =SUMIFS(Transactions!$H:$H,Transactions!$D:$D,"Sale",Transactions!$E:$E,"UMA") -> 0
A31: Megamall | B31: =SUMIFS(Transactions!$H:$H,Transactions!$D:$D,"Sale",Transactions!$E:$E,"Megamall") -> 0
A32: Etsy | B32: =SUMIFS(Transactions!$H:$H,Transactions!$D:$D,"Sale",Transactions!$E:$E,"Etsy") -> 0
A33: Wholesale | B33: =SUMIFS(Transactions!$H:$H,Transactions!$D:$D,"Sale",Transactions!$E:$E,"Wholesale") -> 0
A35: CATALOG BREAKDOWN
A36: Category | B36: # SKUs | C36: Units sold | D36: Revenue
A37: Pendant | B37: =COUNTIF(Variants!$D$3:$D$476,"Pendant") -> 147 | C37: =SUMPRODUCT((Variants!$D$3:$D$476="Pendant")*Variants!$AE$3:$AE$476) -> 1 | D37: =SUMPRODUCT((Variants!$D$3:$D$476="Pendant")*Variants!$AF$3:$AF$476) -> 19000
A38: Bracelet | B38: =COUNTIF(Variants!$D$3:$D$476,"Bracelet") -> 114 | C38: =SUMPRODUCT((Variants!$D$3:$D$476="Bracelet")*Variants!$AE$3:$AE$476) -> 0 | D38: =SUMPRODUCT((Variants!$D$3:$D$476="Bracelet")*Variants!$AF$3:$AF$476) -> 0
A39: Brooch | B39: =COUNTIF(Variants!$D$3:$D$476,"Brooch") -> 38 | C39: =SUMPRODUCT((Variants!$D$3:$D$476="Brooch")*Variants!$AE$3:$AE$476) -> 0 | D39: =SUMPRODUCT((Variants!$D$3:$D$476="Brooch")*Variants!$AF$3:$AF$476) -> 0
A40: Earring | B40: =COUNTIF(Variants!$D$3:$D$476,"Earring") -> 49 | C40: =SUMPRODUCT((Variants!$D$3:$D$476="Earring")*Variants!$AE$3:$AE$476) -> 1 | D40: =SUMPRODUCT((Variants!$D$3:$D$476="Earring")*Variants!$AF$3:$AF$476) -> 27000
A41: earrings 2 pcs. | B41: =COUNTIF(Variants!$D$3:$D$476,"earrings 2 pcs.") -> 17 | C41: =SUMPRODUCT((Variants!$D$3:$D$476="earrings 2 pcs.")*Variants!$AE$3:$AE$476) -> 0 | D41: =SUMPRODUCT((Variants!$D$3:$D$476="earrings 2 pcs.")*Variants!$AF$3:$AF$476) -> 0
A42: Ring | B42: =COUNTIF(Variants!$D$3:$D$476,"Ring") -> 47 | C42: =SUMPRODUCT((Variants!$D$3:$D$476="Ring")*Variants!$AE$3:$AE$476) -> 0 | D42: =SUMPRODUCT((Variants!$D$3:$D$476="Ring")*Variants!$AF$3:$AF$476) -> 0
A43: ring twin | B43: =COUNTIF(Variants!$D$3:$D$476,"ring twin") -> 12 | C43: =SUMPRODUCT((Variants!$D$3:$D$476="ring twin")*Variants!$AE$3:$AE$476) -> 0 | D43: =SUMPRODUCT((Variants!$D$3:$D$476="ring twin")*Variants!$AF$3:$AF$476) -> 0
A44: chain necklace | B44: =COUNTIF(Variants!$D$3:$D$476,"chain necklace") -> 25 | C44: =SUMPRODUCT((Variants!$D$3:$D$476="chain necklace")*Variants!$AE$3:$AE$476) -> 0 | D44: =SUMPRODUCT((Variants!$D$3:$D$476="chain necklace")*Variants!$AF$3:$AF$476) -> 0
A45: chain bracelet | B45: =COUNTIF(Variants!$D$3:$D$476,"chain bracelet") -> 25 | C45: =SUMPRODUCT((Variants!$D$3:$D$476="chain bracelet")*Variants!$AE$3:$AE$476) -> 0 | D45: =SUMPRODUCT((Variants!$D$3:$D$476="chain bracelet")*Variants!$AF$3:$AF$476) -> 0

Sheet Shopify Export
A1: Handle | B1: Title | C1: Body (HTML) | D1: Vendor | E1: Product Category | F1: Type | G1: Tags | H1: Published | I1: Option1 Name | J1: Option1 Value | K1: Option2 Name | L1: Option2 Value | M1: Variant SKU | N1: Variant Grams | O1: Variant Inventory Qty | P1: Variant Price | Q1: Variant Barcode | R1: Image Src | S1: SEO Title | T1: SEO Description | U1: Status
A2: =IF(Variants!$B3="","",LOWER(Variants!$B3)) -> dsgn-pend-alpha-ayb | B2: =IF(Variants!$B3="","",Variants!$C3&IF(Variants!$F3="",""," "&Variants!$F3)) -> Bird Letter Pendant Ա | C2: =IFERROR(IF(Variants!$B3="","","<p>"&VLOOKUP(Variants!$B3,Designs!$A$3:$AP$165,9,FALSE())&"</p>"),"") -> <p>Bird letters are an ornamental medieval Armenian script where each letter is formed from stylised birds, used in illuminated manuscripts.</p> | D2: =IF(Variants!$B3="","","Karni Jewellery") -> Karni Jewellery | E2: =IF(Variants!$B3="","","Apparel & Accessories > Jewelry") -> Apparel & Accessories > Jewelry | F2: =IF(Variants!$D3="","",Variants!$D3) -> Pendant | G2: =IF(Variants!$E3="","",Variants!$E3&", Armenian jewellery, handmade") -> Alphabet, Armenian jewellery, handmade | H2: =IF(Variants!$AD3="Active","TRUE","FALSE") -> TRUE | I2: =IF(Variants!$H3="","","Color") -> Color | J2: =IF(Variants!$H3="","",Variants!$H3) -> red | K2: =IF(Variants!$G3="","","Size") | L2: =IF(Variants!$G3="","",Variants!$G3) | M2: =Variants!$A3 -> KARNI-PEND-ALPHA-AYB-RED | N2: =IF(Variants!$X3="","",Variants!$X3) | O2: =IF(Variants!$O3="","",Variants!$O3) -> 0 | P2: =IF(Variants!$J3="","",Variants!$J3) -> 49.4 | Q2: =IF(Variants!$U3="","",Variants!$U3) | R2: =IF(Variants!$Y3="","",Variants!$Y3) | S2: =IFERROR(VLOOKUP(Variants!$B3,Designs!$A$3:$AP$165,37,FALSE()),"") -> 0 | T2: =IFERROR(VLOOKUP(Variants!$B3,Designs!$A$3:$AP$165,38,FALSE()),"") -> No | U2: =IF(Variants!$AD3="Active","active","draft") -> active
A3: =IF(Variants!$B4="","",LOWER(Variants!$B4)) -> dsgn-pend-alpha-ayb | B3: =IF(Variants!$B4="","",Variants!$C4&IF(Variants!$F4="",""," "&Variants!$F4)) -> Bird Letter Pendant Ա | C3: =IFERROR(IF(Variants!$B4="","","<p>"&VLOOKUP(Variants!$B4,Designs!$A$3:$AP$165,9,FALSE())&"</p>"),"") -> <p>Bird letters are an ornamental medieval Armenian script where each letter is formed from stylised birds, used in illuminated manuscripts.</p> | D3: =IF(Variants!$B4="","","Karni Jewellery") -> Karni Jewellery | E3: =IF(Variants!$B4="","","Apparel & Accessories > Jewelry") -> Apparel & Accessories > Jewelry | F3: =IF(Variants!$D4="","",Variants!$D4) -> Pendant | G3: =IF(Variants!$E4="","",Variants!$E4&", Armenian jewellery, handmade") -> Alphabet, Armenian jewellery, handmade | H3: =IF(Variants!$AD4="Active","TRUE","FALSE") -> TRUE | I3: =IF(Variants!$H4="","","Color") -> Color | J3: =IF(Variants!$H4="","",Variants!$H4) -> turquoise | K3: =IF(Variants!$G4="","","Size") | L3: =IF(Variants!$G4="","",Variants!$G4) | M3: =Variants!$A4 -> KARNI-PEND-ALPHA-AYB-TURQUOISE | N3: =IF(Variants!$X4="","",Variants!$X4) | O3: =IF(Variants!$O4="","",Variants!$O4) -> 0 | P3: =IF(Variants!$J4="","",Variants!$J4) -> 49.4 | Q3: =IF(Variants!$U4="","",Variants!$U4) | R3: =IF(Variants!$Y4="","",Variants!$Y4) | S3: =IFERROR(VLOOKUP(Variants!$B4,Designs!$A$3:$AP$165,37,FALSE()),"") -> 0 | T3: =IFERROR(VLOOKUP(Variants!$B4,Designs!$A$3:$AP$165,38,FALSE()),"") -> No | U3: =IF(Variants!$AD4="Active","active","draft") -> active
A4: =IF(Variants!$B5="","",LOWER(Variants!$B5)) -> dsgn-pend-alpha-ayb | B4: =IF(Variants!$B5="","",Variants!$C5&IF(Variants!$F5="",""," "&Variants!$F5)) -> Bird Letter Pendant Ա | C4: =IFERROR(IF(Variants!$B5="","","<p>"&VLOOKUP(Variants!$B5,Designs!$A$3:$AP$165,9,FALSE())&"</p>"),"") -> <p>Bird letters are an ornamental medieval Armenian script where each letter is formed from stylised birds, used in illuminated manuscripts.</p> | D4: =IF(Variants!$B5="","","Karni Jewellery") -> Karni Jewellery | E4: =IF(Variants!$B5="","","Apparel & Accessories > Jewelry") -> Apparel & Accessories > Jewelry | F4: =IF(Variants!$D5="","",Variants!$D5) -> Pendant | G4: =IF(Variants!$E5="","",Variants!$E5&", Armenian jewellery, handmade") -> Alphabet, Armenian jewellery, handmade | H4: =IF(Variants!$AD5="Active","TRUE","FALSE") -> TRUE | I4: =IF(Variants!$H5="","","Color") -> Color | J4: =IF(Variants!$H5="","",Variants!$H5) -> white | K4: =IF(Variants!$G5="","","Size") | L4: =IF(Variants!$G5="","",Variants!$G5) | M4: =Variants!$A5 -> KARNI-PEND-ALPHA-AYB-WHITE | N4: =IF(Variants!$X5="","",Variants!$X5) | O4: =IF(Variants!$O5="","",Variants!$O5) -> 0 | P4: =IF(Variants!$J5="","",Variants!$J5) -> 49.4 | Q4: =IF(Variants!$U5="","",Variants!$U5) | R4: =IF(Variants!$Y5="","",Variants!$Y5) | S4: =IFERROR(VLOOKUP(Variants!$B5,Designs!$A$3:$AP$165,37,FALSE()),"") -> 0 | T4: =IFERROR(VLOOKUP(Variants!$B5,Designs!$A$3:$AP$165,38,FALSE()),"") -> No | U4: =IF(Variants!$AD5="Active","active","draft") -> active
A5: =IF(Variants!$B6="","",LOWER(Variants!$B6)) -> dsgn-pend-alpha-ben | B5: =IF(Variants!$B6="","",Variants!$C6&IF(Variants!$F6="",""," "&Variants!$F6)) -> Bird Letter Pendant Բ | C5: =IFERROR(IF(Variants!$B6="","","<p>"&VLOOKUP(Variants!$B6,Designs!$A$3:$AP$165,9,FALSE())&"</p>"),"") -> <p>Bird letters are an ornamental medieval Armenian script where each letter is formed from stylised birds, used in illuminated manuscripts.</p> | D5: =IF(Variants!$B6="","","Karni Jewellery") -> Karni Jewellery | E5: =IF(Variants!$B6="","","Apparel & Accessories > Jewelry") -> Apparel & Accessories > Jewelry | F5: =IF(Variants!$D6="","",Variants!$D6) -> Pendant | G5: =IF(Variants!$E6="","",Variants!$E6&", Armenian jewellery, handmade") -> Alphabet, Armenian jewellery, handmade | H5: =IF(Variants!$AD6="Active","TRUE","FALSE") -> TRUE | I5: =IF(Variants!$H6="","","Color") -> Color | J5: =IF(Variants!$H6="","",Variants!$H6) -> red | K5: =IF(Variants!$G6="","","Size") | L5: =IF(Variants!$G6="","",Variants!$G6) | M5: =Variants!$A6 -> KARNI-PEND-ALPHA-BEN-RED | N5: =IF(Variants!$X6="","",Variants!$X6) | O5: =IF(Variants!$O6="","",Variants!$O6) -> 0 | P5: =IF(Variants!$J6="","",Variants!$J6) -> 49.4 | Q5: =IF(Variants!$U6="","",Variants!$U6) | R5: =IF(Variants!$Y6="","",Variants!$Y6) | S5: =IFERROR(VLOOKUP(Variants!$B6,Designs!$A$3:$AP$165,37,FALSE()),"") -> 0 | T5: =IFERROR(VLOOKUP(Variants!$B6,Designs!$A$3:$AP$165,38,FALSE()),"") -> No | U5: =IF(Variants!$AD6="Active","active","draft") -> active
A6: =IF(Variants!$B7="","",LOWER(Variants!$B7)) -> dsgn-pend-alpha-ben | B6: =IF(Variants!$B7="","",Variants!$C7&IF(Variants!$F7="",""," "&Variants!$F7)) -> Bird Letter Pendant Բ | C6: =IFERROR(IF(Variants!$B7="","","<p>"&VLOOKUP(Variants!$B7,Designs!$A$3:$AP$165,9,FALSE())&"</p>"),"") -> <p>Bird letters are an ornamental medieval Armenian script where each letter is formed from stylised birds, used in illuminated manuscripts.</p> | D6: =IF(Variants!$B7="","","Karni Jewellery") -> Karni Jewellery | E6: =IF(Variants!$B7="","","Apparel & Accessories > Jewelry") -> Apparel & Accessories > Jewelry | F6: =IF(Variants!$D7="","",Variants!$D7) -> Pendant | G6: =IF(Variants!$E7="","",Variants!$E7&", Armenian jewellery, handmade") -> Alphabet, Armenian jewellery, handmade | H6: =IF(Variants!$AD7="Active","TRUE","FALSE") -> TRUE | I6: =IF(Variants!$H7="","","Color") -> Color | J6: =IF(Variants!$H7="","",Variants!$H7) -> turquoise | K6: =IF(Variants!$G7="","","Size") | L6: =IF(Variants!$G7="","",Variants!$G7) | M6: =Variants!$A7 -> KARNI-PEND-ALPHA-BEN-TURQUOISE | N6: =IF(Variants!$X7="","",Variants!$X7) | O6: =IF(Variants!$O7="","",Variants!$O7) -> 0 | P6: =IF(Variants!$J7="","",Variants!$J7) -> 49.4 | Q6: =IF(Variants!$U7="","",Variants!$U7) | R6: =IF(Variants!$Y7="","",Variants!$Y7) | S6: =IFERROR(VLOOKUP(Variants!$B7,Designs!$A$3:$AP$165,37,FALSE()),"") -> 0 | T6: =IFERROR(VLOOKUP(Variants!$B7,Designs!$A$3:$AP$165,38,FALSE()),"") -> No | U6: =IF(Variants!$AD7="Active","active","draft") -> active
A7: =IF(Variants!$B8="","",LOWER(Variants!$B8)) -> dsgn-pend-alpha-ben | B7: =IF(Variants!$B8="","",Variants!$C8&IF(Variants!$F8="",""," "&Variants!$F8)) -> Bird Letter Pendant Բ | C7: =IFERROR(IF(Variants!$B8="","","<p>"&VLOOKUP(Variants!$B8,Designs!$A$3:$AP$165,9,FALSE())&"</p>"),"") -> <p>Bird letters are an ornamental medieval Armenian script where each letter is formed from stylised birds, used in illuminated manuscripts.</p> | D7: =IF(Variants!$B8="","","Karni Jewellery") -> Karni Jewellery | E7: =IF(Variants!$B8="","","Apparel & Accessories > Jewelry") -> Apparel & Accessories > Jewelry | F7: =IF(Variants!$D8="","",Variants!$D8) -> Pendant | G7: =IF(Variants!$E8="","",Variants!$E8&", Armenian jewellery, handmade") -> Alphabet, Armenian jewellery, handmade | H7: =IF(Variants!$AD8="Active","TRUE","FALSE") -> TRUE | I7: =IF(Variants!$H8="","","Color") -> Color | J7: =IF(Variants!$H8="","",Variants!$H8) -> white | K7: =IF(Variants!$G8="","","Size") | L7: =IF(Variants!$G8="","",Variants!$G8) | M7: =Variants!$A8 -> KARNI-PEND-ALPHA-BEN-WHITE | N7: =IF(Variants!$X8="","",Variants!$X8) | O7: =IF(Variants!$O8="","",Variants!$O8) -> 0 | P7: =IF(Variants!$J8="","",Variants!$J8) -> 49.4 | Q7: =IF(Variants!$U8="","",Variants!$U8) | R7: =IF(Variants!$Y8="","",Variants!$Y8) | S7: =IFERROR(VLOOKUP(Variants!$B8,Designs!$A$3:$AP$165,37,FALSE()),"") -> 0 | T7: =IFERROR(VLOOKUP(Variants!$B8,Designs!$A$3:$AP$165,38,FALSE()),"") -> No | U7: =IF(Variants!$AD8="Active","active","draft") -> active
A8: =IF(Variants!$B9="","",LOWER(Variants!$B9)) -> dsgn-pend-alpha-gim | B8: =IF(Variants!$B9="","",Variants!$C9&IF(Variants!$F9="",""," "&Variants!$F9)) -> Bird Letter Pendant Գ | C8: =IFERROR(IF(Variants!$B9="","","<p>"&VLOOKUP(Variants!$B9,Designs!$A$3:$AP$165,9,FALSE())&"</p>"),"") -> <p>Bird letters are an ornamental medieval Armenian script where each letter is formed from stylised birds, used in illuminated manuscripts.</p> | D8: =IF(Variants!$B9="","","Karni Jewellery") -> Karni Jewellery | E8: =IF(Variants!$B9="","","Apparel & Accessories > Jewelry") -> Apparel & Accessories > Jewelry | F8: =IF(Variants!$D9="","",Variants!$D9) -> Pendant | G8: =IF(Variants!$E9="","",Variants!$E9&", Armenian jewellery, handmade") -> Alphabet, Armenian jewellery, handmade | H8: =IF(Variants!$AD9="Active","TRUE","FALSE") -> TRUE | I8: =IF(Variants!$H9="","","Color") -> Color | J8: =IF(Variants!$H9="","",Variants!$H9) -> red | K8: =IF(Variants!$G9="","","Size") | L8: =IF(Variants!$G9="","",Variants!$G9) | M8: =Variants!$A9 -> KARNI-PEND-ALPHA-GIM-RED | N8: =IF(Variants!$X9="","",Variants!$X9) | O8: =IF(Variants!$O9="","",Variants!$O9) -> 0 | P8: =IF(Variants!$J9="","",Variants!$J9) -> 49.4 | Q8: =IF(Variants!$U9="","",Variants!$U9) | R8: =IF(Variants!$Y9="","",Variants!$Y9) | S8: =IFERROR(VLOOKUP(Variants!$B9,Designs!$A$3:$AP$165,37,FALSE()),"") -> 0 | T8: =IFERROR(VLOOKUP(Variants!$B9,Designs!$A$3:$AP$165,38,FALSE()),"") -> No | U8: =IF(Variants!$AD9="Active","active","draft") -> active
A9: =IF(Variants!$B10="","",LOWER(Variants!$B10)) -> dsgn-pend-alpha-gim | B9: =IF(Variants!$B10="","",Variants!$C10&IF(Variants!$F10="",""," "&Variants!$F10)) -> Bird Letter Pendant Գ | C9: =IFERROR(IF(Variants!$B10="","","<p>"&VLOOKUP(Variants!$B10,Designs!$A$3:$AP$165,9,FALSE())&"</p>"),"") -> <p>Bird letters are an ornamental medieval Armenian script where each letter is formed from stylised birds, used in illuminated manuscripts.</p> | D9: =IF(Variants!$B10="","","Karni Jewellery") -> Karni Jewellery | E9: =IF(Variants!$B10="","","Apparel & Accessories > Jewelry") -> Apparel & Accessories > Jewelry | F9: =IF(Variants!$D10="","",Variants!$D10) -> Pendant | G9: =IF(Variants!$E10="","",Variants!$E10&", Armenian jewellery, handmade") -> Alphabet, Armenian jewellery, handmade | H9: =IF(Variants!$AD10="Active","TRUE","FALSE") -> TRUE | I9: =IF(Variants!$H10="","","Color") -> Color | J9: =IF(Variants!$H10="","",Variants!$H10) -> turquoise | K9: =IF(Variants!$G10="","","Size") | L9: =IF(Variants!$G10="","",Variants!$G10) | M9: =Variants!$A10 -> KARNI-PEND-ALPHA-GIM-TURQUOISE | N9: =IF(Variants!$X10="","",Variants!$X10) | O9: =IF(Variants!$O10="","",Variants!$O10) -> 0 | P9: =IF(Variants!$J10="","",Variants!$J10) -> 49.4 | Q9: =IF(Variants!$U10="","",Variants!$U10) | R9: =IF(Variants!$Y10="","",Variants!$Y10) | S9: =IFERROR(VLOOKUP(Variants!$B10,Designs!$A$3:$AP$165,37,FALSE()),"") -> 0 | T9: =IFERROR(VLOOKUP(Variants!$B10,Designs!$A$3:$AP$165,38,FALSE()),"") -> No | U9: =IF(Variants!$AD10="Active","active","draft") -> active
A10: =IF(Variants!$B11="","",LOWER(Variants!$B11)) -> dsgn-pend-alpha-gim | B10: =IF(Variants!$B11="","",Variants!$C11&IF(Variants!$F11="",""," "&Variants!$F11)) -> Bird Letter Pendant Գ | C10: =IFERROR(IF(Variants!$B11="","","<p>"&VLOOKUP(Variants!$B11,Designs!$A$3:$AP$165,9,FALSE())&"</p>"),"") -> <p>Bird letters are an ornamental medieval Armenian script where each letter is formed from stylised birds, used in illuminated manuscripts.</p> | D10: =IF(Variants!$B11="","","Karni Jewellery") -> Karni Jewellery | E10: =IF(Variants!$B11="","","Apparel & Accessories > Jewelry") -> Apparel & Accessories > Jewelry | F10: =IF(Variants!$D11="","",Variants!$D11) -> Pendant | G10: =IF(Variants!$E11="","",Variants!$E11&", Armenian jewellery, handmade") -> Alphabet, Armenian jewellery, handmade | H10: =IF(Variants!$AD11="Active","TRUE","FALSE") -> TRUE | I10: =IF(Variants!$H11="","","Color") -> Color | J10: =IF(Variants!$H11="","",Variants!$H11) -> white | K10: =IF(Variants!$G11="","","Size") | L10: =IF(Variants!$G11="","",Variants!$G11) | M10: =Variants!$A11 -> KARNI-PEND-ALPHA-GIM-WHITE | N10: =IF(Variants!$X11="","",Variants!$X11) | O10: =IF(Variants!$O11="","",Variants!$O11) -> 0 | P10: =IF(Variants!$J11="","",Variants!$J11) -> 49.4 | Q10: =IF(Variants!$U11="","",Variants!$U11) | R10: =IF(Variants!$Y11="","",Variants!$Y11) | S10: =IFERROR(VLOOKUP(Variants!$B11,Designs!$A$3:$AP$165,37,FALSE()),"") -> 0 | T10: =IFERROR(VLOOKUP(Variants!$B11,Designs!$A$3:$AP$165,38,FALSE()),"") -> No | U10: =IF(Variants!$AD11="Active","active","draft") -> active
A11: =IF(Variants!$B12="","",LOWER(Variants!$B12)) -> dsgn-pend-alpha-da | B11: =IF(Variants!$B12="","",Variants!$C12&IF(Variants!$F12="",""," "&Variants!$F12)) -> Bird Letter Pendant Դ | C11: =IFERROR(IF(Variants!$B12="","","<p>"&VLOOKUP(Variants!$B12,Designs!$A$3:$AP$165,9,FALSE())&"</p>"),"") -> <p>Bird letters are an ornamental medieval Armenian script where each letter is formed from stylised birds, used in illuminated manuscripts.</p> | D11: =IF(Variants!$B12="","","Karni Jewellery") -> Karni Jewellery | E11: =IF(Variants!$B12="","","Apparel & Accessories > Jewelry") -> Apparel & Accessories > Jewelry | F11: =IF(Variants!$D12="","",Variants!$D12) -> Pendant | G11: =IF(Variants!$E12="","",Variants!$E12&", Armenian jewellery, handmade") -> Alphabet, Armenian jewellery, handmade | H11: =IF(Variants!$AD12="Active","TRUE","FALSE") -> TRUE | I11: =IF(Variants!$H12="","","Color") -> Color | J11: =IF(Variants!$H12="","",Variants!$H12) -> red | K11: =IF(Variants!$G12="","","Size") | L11: =IF(Variants!$G12="","",Variants!$G12) | M11: =Variants!$A12 -> KARNI-PEND-ALPHA-DA-RED | N11: =IF(Variants!$X12="","",Variants!$X12) | O11: =IF(Variants!$O12="","",Variants!$O12) -> 0 | P11: =IF(Variants!$J12="","",Variants!$J12) -> 49.4 | Q11: =IF(Variants!$U12="","",Variants!$U12) | R11: =IF(Variants!$Y12="","",Variants!$Y12) | S11: =IFERROR(VLOOKUP(Variants!$B12,Designs!$A$3:$AP$165,37,FALSE()),"") -> 0 | T11: =IFERROR(VLOOKUP(Variants!$B12,Designs!$A$3:$AP$165,38,FALSE()),"") -> No | U11: =IF(Variants!$AD12="Active","active","draft") -> active
A12: =IF(Variants!$B13="","",LOWER(Variants!$B13)) -> dsgn-pend-alpha-da | B12: =IF(Variants!$B13="","",Variants!$C13&IF(Variants!$F13="",""," "&Variants!$F13)) -> Bird Letter Pendant Դ | C12: =IFERROR(IF(Variants!$B13="","","<p>"&VLOOKUP(Variants!$B13,Designs!$A$3:$AP$165,9,FALSE())&"</p>"),"") -> <p>Bird letters are an ornamental medieval Armenian script where each letter is formed from stylised birds, used in illuminated manuscripts.</p> | D12: =IF(Variants!$B13="","","Karni Jewellery") -> Karni Jewellery | E12: =IF(Variants!$B13="","","Apparel & Accessories > Jewelry") -> Apparel & Accessories > Jewelry | F12: =IF(Variants!$D13="","",Variants!$D13) -> Pendant | G12: =IF(Variants!$E13="","",Variants!$E13&", Armenian jewellery, handmade") -> Alphabet, Armenian jewellery, handmade | H12: =IF(Variants!$AD13="Active","TRUE","FALSE") -> TRUE | I12: =IF(Variants!$H13="","","Color") -> Color | J12: =IF(Variants!$H13="","",Variants!$H13) -> turquoise | K12: =IF(Variants!$G13="","","Size") | L12: =IF(Variants!$G13="","",Variants!$G13) | M12: =Variants!$A13 -> KARNI-PEND-ALPHA-DA-TURQUOISE | N12: =IF(Variants!$X13="","",Variants!$X13) | O12: =IF(Variants!$O13="","",Variants!$O13) -> 0 | P12: =IF(Variants!$J13="","",Variants!$J13) -> 49.4 | Q12: =IF(Variants!$U13="","",Variants!$U13) | R12: =IF(Variants!$Y13="","",Variants!$Y13) | S12: =IFERROR(VLOOKUP(Variants!$B13,Designs!$A$3:$AP$165,37,FALSE()),"") -> 0 | T12: =IFERROR(VLOOKUP(Variants!$B13,Designs!$A$3:$AP$165,38,FALSE()),"") -> No | U12: =IF(Variants!$AD13="Active","active","draft") -> active
A13: =IF(Variants!$B14="","",LOWER(Variants!$B14)) -> dsgn-pend-alpha-da | B13: =IF(Variants!$B14="","",Variants!$C14&IF(Variants!$F14="",""," "&Variants!$F14)) -> Bird Letter Pendant Դ | C13: =IFERROR(IF(Variants!$B14="","","<p>"&VLOOKUP(Variants!$B14,Designs!$A$3:$AP$165,9,FALSE())&"</p>"),"") -> <p>Bird letters are an ornamental medieval Armenian script where each letter is formed from stylised birds, used in illuminated manuscripts.</p> | D13: =IF(Variants!$B14="","","Karni Jewellery") -> Karni Jewellery | E13: =IF(Variants!$B14="","","Apparel & Accessories > Jewelry") -> Apparel & Accessories > Jewelry | F13: =IF(Variants!$D14="","",Variants!$D14) -> Pendant | G13: =IF(Variants!$E14="","",Variants!$E14&", Armenian jewellery, handmade") -> Alphabet, Armenian jewellery, handmade | H13: =IF(Variants!$AD14="Active","TRUE","FALSE") -> TRUE | I13: =IF(Variants!$H14="","","Color") -> Color | J13: =IF(Variants!$H14="","",Variants!$H14) -> white | K13: =IF(Variants!$G14="","","Size") | L13: =IF(Variants!$G14="","",Variants!$G14) | M13: =Variants!$A14 -> KARNI-PEND-ALPHA-DA-WHITE | N13: =IF(Variants!$X14="","",Variants!$X14) | O13: =IF(Variants!$O14="","",Variants!$O14) -> 0 | P13: =IF(Variants!$J14="","",Variants!$J14) -> 49.4 | Q13: =IF(Variants!$U14="","",Variants!$U14) | R13: =IF(Variants!$Y14="","",Variants!$Y14) | S13: =IFERROR(VLOOKUP(Variants!$B14,Designs!$A$3:$AP$165,37,FALSE()),"") -> 0 | T13: =IFERROR(VLOOKUP(Variants!$B14,Designs!$A$3:$AP$165,38,FALSE()),"") -> No | U13: =IF(Variants!$AD14="Active","active","draft") -> active
... A475: =IF(Variants!$B476="","",LOWER(Variants!$B476)) -> dsgn-chbrac-vishabarevagorg | B475: =IF(Variants!$B476="","",Variants!$C476&IF(Variants!$F476="",""," "&Variants!$F476)) -> Արեւագորգի Վիշապ | C475: =IFERROR(IF(Variants!$B476="","","<p>"&VLOOKUP(Variants!$B476,Designs!$A$3:$AP$165,9,FALSE())&"</p>"),"") -> <p>Combines the vishap (dragon) motif with the arevagorg (sun-carpet) — an Armenian solar ornament symbolising life and eternity.</p> | D475: =IF(Variants!$B476="","","Karni Jewellery") -> Karni Jewellery | E475: =IF(Variants!$B476="","","Apparel & Accessories > Jewelry") -> Apparel & Accessories > Jewelry | F475: =IF(Variants!$D476="","",Variants!$D476) -> chain bracelet | G475: =IF(Variants!$E476="","",Variants!$E476&", Armenian jewellery, handmade") -> Vishab Arevagorg, Armenian jewellery, handmade | H475: =IF(Variants!$AD476="Active","TRUE","FALSE") -> TRUE | I475: =IF(Variants!$H476="","","Color") -> Color | J475: =IF(Variants!$H476="","",Variants!$H476) -> green | K475: =IF(Variants!$G476="","","Size") | L475: =IF(Variants!$G476="","",Variants!$G476) | M475: =Variants!$A476 -> KARNI-CHBRAC-VISHABAREVAGORG-GREEN | N475: =IF(Variants!$X476="","",Variants!$X476) | O475: =IF(Variants!$O476="","",Variants!$O476) -> 0 | P475: =IF(Variants!$J476="","",Variants!$J476) -> 44.2 | Q475: =IF(Variants!$U476="","",Variants!$U476) | R475: =IF(Variants!$Y476="","",Variants!$Y476) | S475: =IFERROR(VLOOKUP(Variants!$B476,Designs!$A$3:$AP$165,37,FALSE()),"") -> 0 | T475: =IFERROR(VLOOKUP(Variants!$B476,Designs!$A$3:$AP$165,38,FALSE()),"") -> No | U475: =IF(Variants!$AD476="Active","active","draft") -> active

Sheet Etsy Export
A1: Title | B1: Description | C1: Price (USD) | D1: Quantity | E1: SKU | F1: Tags | G1: Materials | H1: Who made it | I1: When made | J1: Category | K1: Image URL | L1: Variation 1 (Color) | M1: Variation 2 (Size)
A2: =IF(Variants!$B3="","",Variants!$C3&" — "&Variants!$E3&IF(Variants!$F3=""," "," "&Variants!$F3)&" — "&Variants!$H3) -> Bird Letter Pendant — Alphabet Ա — red | B2: =IFERROR(IF(Variants!$B3="","",VLOOKUP(Variants!$B3,Designs!$A$3:$AP$165,9,FALSE())&" Handmade in Armenia."),"") -> Bird letters are an ornamental medieval Armenian script where each letter is formed from stylised birds, used in illuminated manuscripts. Handmade in Armenia. | C2: =IF(Variants!$J3="","",Variants!$J3) -> 49.4 | D2: =IF(Variants!$O3="","",Variants!$O3) -> 0 | E2: =Variants!$A3 -> KARNI-PEND-ALPHA-AYB-RED | F2: =IF(Variants!$E3="","",Variants!$E3&", Armenian, handmade, enamel, "&Variants!$D3) -> Alphabet, Armenian, handmade, enamel, Pendant | G2: =IFERROR(VLOOKUP(Variants!$B3,Designs!$A$3:$AP$165,12,FALSE())&", enamel","") -> 925 Silver Gold-Plated, enamel | H2: =IF(Variants!$B3="","","I did") -> I did | I2: =IF(Variants!$B3="","","Made to order") -> Made to order | J2: =IF(Variants!$D3="","",Variants!$D3) -> Pendant | K2: =IF(Variants!$Y3="","",Variants!$Y3) | L2: =IF(Variants!$H3="","",Variants!$H3) -> red | M2: =IF(Variants!$G3="","",Variants!$G3)
A3: =IF(Variants!$B4="","",Variants!$C4&" — "&Variants!$E4&IF(Variants!$F4=""," "," "&Variants!$F4)&" — "&Variants!$H4) -> Bird Letter Pendant — Alphabet Ա — turquoise | B3: =IFERROR(IF(Variants!$B4="","",VLOOKUP(Variants!$B4,Designs!$A$3:$AP$165,9,FALSE())&" Handmade in Armenia."),"") -> Bird letters are an ornamental medieval Armenian script where each letter is formed from stylised birds, used in illuminated manuscripts. Handmade in Armenia. | C3: =IF(Variants!$J4="","",Variants!$J4) -> 49.4 | D3: =IF(Variants!$O4="","",Variants!$O4) -> 0 | E3: =Variants!$A4 -> KARNI-PEND-ALPHA-AYB-TURQUOISE | F3: =IF(Variants!$E4="","",Variants!$E4&", Armenian, handmade, enamel, "&Variants!$D4) -> Alphabet, Armenian, handmade, enamel, Pendant | G3: =IFERROR(VLOOKUP(Variants!$B4,Designs!$A$3:$AP$165,12,FALSE())&", enamel","") -> 925 Silver Gold-Plated, enamel | H3: =IF(Variants!$B4="","","I did") -> I did | I3: =IF(Variants!$B4="","","Made to order") -> Made to order | J3: =IF(Variants!$D4="","",Variants!$D4) -> Pendant | K3: =IF(Variants!$Y4="","",Variants!$Y4) | L3: =IF(Variants!$H4="","",Variants!$H4) -> turquoise | M3: =IF(Variants!$G4="","",Variants!$G4)
A4: =IF(Variants!$B5="","",Variants!$C5&" — "&Variants!$E5&IF(Variants!$F5=""," "," "&Variants!$F5)&" — "&Variants!$H5) -> Bird Letter Pendant — Alphabet Ա — white | B4: =IFERROR(IF(Variants!$B5="","",VLOOKUP(Variants!$B5,Designs!$A$3:$AP$165,9,FALSE())&" Handmade in Armenia."),"") -> Bird letters are an ornamental medieval Armenian script where each letter is formed from stylised birds, used in illuminated manuscripts. Handmade in Armenia. | C4: =IF(Variants!$J5="","",Variants!$J5) -> 49.4 | D4: =IF(Variants!$O5="","",Variants!$O5) -> 0 | E4: =Variants!$A5 -> KARNI-PEND-ALPHA-AYB-WHITE | F4: =IF(Variants!$E5="","",Variants!$E5&", Armenian, handmade, enamel, "&Variants!$D5) -> Alphabet, Armenian, handmade, enamel, Pendant | G4: =IFERROR(VLOOKUP(Variants!$B5,Designs!$A$3:$AP$165,12,FALSE())&", enamel","") -> 925 Silver Gold-Plated, enamel | H4: =IF(Variants!$B5="","","I did") -> I did | I4: =IF(Variants!$B5="","","Made to order") -> Made to order | J4: =IF(Variants!$D5="","",Variants!$D5) -> Pendant | K4: =IF(Variants!$Y5="","",Variants!$Y5) | L4: =IF(Variants!$H5="","",Variants!$H5) -> white | M4: =IF(Variants!$G5="","",Variants!$G5)
A5: =IF(Variants!$B6="","",Variants!$C6&" — "&Variants!$E6&IF(Variants!$F6=""," "," "&Variants!$F6)&" — "&Variants!$H6) -> Bird Letter Pendant — Alphabet Բ — red | B5: =IFERROR(IF(Variants!$B6="","",VLOOKUP(Variants!$B6,Designs!$A$3:$AP$165,9,FALSE())&" Handmade in Armenia."),"") -> Bird letters are an ornamental medieval Armenian script where each letter is formed from stylised birds, used in illuminated manuscripts. Handmade in Armenia. | C5: =IF(Variants!$J6="","",Variants!$J6) -> 49.4 | D5: =IF(Variants!$O6="","",Variants!$O6) -> 0 | E5: =Variants!$A6 -> KARNI-PEND-ALPHA-BEN-RED | F5: =IF(Variants!$E6="","",Variants!$E6&", Armenian, handmade, enamel, "&Variants!$D6) -> Alphabet, Armenian, handmade, enamel, Pendant | G5: =IFERROR(VLOOKUP(Variants!$B6,Designs!$A$3:$AP$165,12,FALSE())&", enamel","") -> 925 Silver Gold-Plated, enamel | H5: =IF(Variants!$B6="","","I did") -> I did | I5: =IF(Variants!$B6="","","Made to order") -> Made to order | J5: =IF(Variants!$D6="","",Variants!$D6) -> Pendant | K5: =IF(Variants!$Y6="","",Variants!$Y6) | L5: =IF(Variants!$H6="","",Variants!$H6) -> red | M5: =IF(Variants!$G6="","",Variants!$G6)
A6: =IF(Variants!$B7="","",Variants!$C7&" — "&Variants!$E7&IF(Variants!$F7=""," "," "&Variants!$F7)&" — "&Variants!$H7) -> Bird Letter Pendant — Alphabet Բ — turquoise | B6: =IFERROR(IF(Variants!$B7="","",VLOOKUP(Variants!$B7,Designs!$A$3:$AP$165,9,FALSE())&" Handmade in Armenia."),"") -> Bird letters are an ornamental medieval Armenian script where each letter is formed from stylised birds, used in illuminated manuscripts. Handmade in Armenia. | C6: =IF(Variants!$J7="","",Variants!$J7) -> 49.4 | D6: =IF(Variants!$O7="","",Variants!$O7) -> 0 | E6: =Variants!$A7 -> KARNI-PEND-ALPHA-BEN-TURQUOISE | F6: =IF(Variants!$E7="","",Variants!$E7&", Armenian, handmade, enamel, "&Variants!$D7) -> Alphabet, Armenian, handmade, enamel, Pendant | G6: =IFERROR(VLOOKUP(Variants!$B7,Designs!$A$3:$AP$165,12,FALSE())&", enamel","") -> 925 Silver Gold-Plated, enamel | H6: =IF(Variants!$B7="","","I did") -> I did | I6: =IF(Variants!$B7="","","Made to order") -> Made to order | J6: =IF(Variants!$D7="","",Variants!$D7) -> Pendant | K6: =IF(Variants!$Y7="","",Variants!$Y7) | L6: =IF(Variants!$H7="","",Variants!$H7) -> turquoise | M6: =IF(Variants!$G7="","",Variants!$G7)
A7: =IF(Variants!$B8="","",Variants!$C8&" — "&Variants!$E8&IF(Variants!$F8=""," "," "&Variants!$F8)&" — "&Variants!$H8) -> Bird Letter Pendant — Alphabet Բ — white | B7: =IFERROR(IF(Variants!$B8="","",VLOOKUP(Variants!$B8,Designs!$A$3:$AP$165,9,FALSE())&" Handmade in Armenia."),"") -> Bird letters are an ornamental medieval Armenian script where each letter is formed from stylised birds, used in illuminated manuscripts. Handmade in Armenia. | C7: =IF(Variants!$J8="","",Variants!$J8) -> 49.4 | D7: =IF(Variants!$O8="","",Variants!$O8) -> 0 | E7: =Variants!$A8 -> KARNI-PEND-ALPHA-BEN-WHITE | F7: =IF(Variants!$E8="","",Variants!$E8&", Armenian, handmade, enamel, "&Variants!$D8) -> Alphabet, Armenian, handmade, enamel, Pendant | G7: =IFERROR(VLOOKUP(Variants!$B8,Designs!$A$3:$AP$165,12,FALSE())&", enamel","") -> 925 Silver Gold-Plated, enamel | H7: =IF(Variants!$B8="","","I did") -> I did | I7: =IF(Variants!$B8="","","Made to order") -> Made to order | J7: =IF(Variants!$D8="","",Variants!$D8) -> Pendant | K7: =IF(Variants!$Y8="","",Variants!$Y8) | L7: =IF(Variants!$H8="","",Variants!$H8) -> white | M7: =IF(Variants!$G8="","",Variants!$G8)
A8: =IF(Variants!$B9="","",Variants!$C9&" — "&Variants!$E9&IF(Variants!$F9=""," "," "&Variants!$F9)&" — "&Variants!$H9) -> Bird Letter Pendant — Alphabet Գ — red | B8: =IFERROR(IF(Variants!$B9="","",VLOOKUP(Variants!$B9,Designs!$A$3:$AP$165,9,FALSE())&" Handmade in Armenia."),"") -> Bird letters are an ornamental medieval Armenian script where each letter is formed from stylised birds, used in illuminated manuscripts. Handmade in Armenia. | C8: =IF(Variants!$J9="","",Variants!$J9) -> 49.4 | D8: =IF(Variants!$O9="","",Variants!$O9) -> 0 | E8: =Variants!$A9 -> KARNI-PEND-ALPHA-GIM-RED | F8: =IF(Variants!$E9="","",Variants!$E9&", Armenian, handmade, enamel, "&Variants!$D9) -> Alphabet, Armenian, handmade, enamel, Pendant | G8: =IFERROR(VLOOKUP(Variants!$B9,Designs!$A$3:$AP$165,12,FALSE())&", enamel","") -> 925 Silver Gold-Plated, enamel | H8: =IF(Variants!$B9="","","I did") -> I did | I8: =IF(Variants!$B9="","","Made to order") -> Made to order | J8: =IF(Variants!$D9="","",Variants!$D9) -> Pendant | K8: =IF(Variants!$Y9="","",Variants!$Y9) | L8: =IF(Variants!$H9="","",Variants!$H9) -> red | M8: =IF(Variants!$G9="","",Variants!$G9)
A9: =IF(Variants!$B10="","",Variants!$C10&" — "&Variants!$E10&IF(Variants!$F10=""," "," "&Variants!$F10)&" — "&Variants!$H10) -> Bird Letter Pendant — Alphabet Գ — turquoise | B9: =IFERROR(IF(Variants!$B10="","",VLOOKUP(Variants!$B10,Designs!$A$3:$AP$165,9,FALSE())&" Handmade in Armenia."),"") -> Bird letters are an ornamental medieval Armenian script where each letter is formed from stylised birds, used in illuminated manuscripts. Handmade in Armenia. | C9: =IF(Variants!$J10="","",Variants!$J10) -> 49.4 | D9: =IF(Variants!$O10="","",Variants!$O10) -> 0 | E9: =Variants!$A10 -> KARNI-PEND-ALPHA-GIM-TURQUOISE | F9: =IF(Variants!$E10="","",Variants!$E10&", Armenian, handmade, enamel, "&Variants!$D10) -> Alphabet, Armenian, handmade, enamel, Pendant | G9: =IFERROR(VLOOKUP(Variants!$B10,Designs!$A$3:$AP$165,12,FALSE())&", enamel","") -> 925 Silver Gold-Plated, enamel | H9: =IF(Variants!$B10="","","I did") -> I did | I9: =IF(Variants!$B10="","","Made to order") -> Made to order | J9: =IF(Variants!$D10="","",Variants!$D10) -> Pendant | K9: =IF(Variants!$Y10="","",Variants!$Y10) | L9: =IF(Variants!$H10="","",Variants!$H10) -> turquoise | M9: =IF(Variants!$G10="","",Variants!$G10)
A10: =IF(Variants!$B11="","",Variants!$C11&" — "&Variants!$E11&IF(Variants!$F11=""," "," "&Variants!$F11)&" — "&Variants!$H11) -> Bird Letter Pendant — Alphabet Գ — white | B10: =IFERROR(IF(Variants!$B11="","",VLOOKUP(Variants!$B11,Designs!$A$3:$AP$165,9,FALSE())&" Handmade in Armenia."),"") -> Bird letters are an ornamental medieval Armenian script where each letter is formed from stylised birds, used in illuminated manuscripts. Handmade in Armenia. | C10: =IF(Variants!$J11="","",Variants!$J11) -> 49.4 | D10: =IF(Variants!$O11="","",Variants!$O11) -> 0 | E10: =Variants!$A11 -> KARNI-PEND-ALPHA-GIM-WHITE | F10: =IF(Variants!$E11="","",Variants!$E11&", Armenian, handmade, enamel, "&Variants!$D11) -> Alphabet, Armenian, handmade, enamel, Pendant | G10: =IFERROR(VLOOKUP(Variants!$B11,Designs!$A$3:$AP$165,12,FALSE())&", enamel","") -> 925 Silver Gold-Plated, enamel | H10: =IF(Variants!$B11="","","I did") -> I did | I10: =IF(Variants!$B11="","","Made to order") -> Made to order | J10: =IF(Variants!$D11="","",Variants!$D11) -> Pendant | K10: =IF(Variants!$Y11="","",Variants!$Y11) | L10: =IF(Variants!$H11="","",Variants!$H11) -> white | M10: =IF(Variants!$G11="","",Variants!$G11)
A11: =IF(Variants!$B12="","",Variants!$C12&" — "&Variants!$E12&IF(Variants!$F12=""," "," "&Variants!$F12)&" — "&Variants!$H12) -> Bird Letter Pendant — Alphabet Դ — red | B11: =IFERROR(IF(Variants!$B12="","",VLOOKUP(Variants!$B12,Designs!$A$3:$AP$165,9,FALSE())&" Handmade in Armenia."),"") -> Bird letters are an ornamental medieval Armenian script where each letter is formed from stylised birds, used in illuminated manuscripts. Handmade in Armenia. | C11: =IF(Variants!$J12="","",Variants!$J12) -> 49.4 | D11: =IF(Variants!$O12="","",Variants!$O12) -> 0 | E11: =Variants!$A12 -> KARNI-PEND-ALPHA-DA-RED | F11: =IF(Variants!$E12="","",Variants!$E12&", Armenian, handmade, enamel, "&Variants!$D12) -> Alphabet, Armenian, handmade, enamel, Pendant | G11: =IFERROR(VLOOKUP(Variants!$B12,Designs!$A$3:$AP$165,12,FALSE())&", enamel","") -> 925 Silver Gold-Plated, enamel | H11: =IF(Variants!$B12="","","I did") -> I did | I11: =IF(Variants!$B12="","","Made to order") -> Made to order | J11: =IF(Variants!$D12="","",Variants!$D12) -> Pendant | K11: =IF(Variants!$Y12="","",Variants!$Y12) | L11: =IF(Variants!$H12="","",Variants!$H12) -> red | M11: =IF(Variants!$G12="","",Variants!$G12)
A12: =IF(Variants!$B13="","",Variants!$C13&" — "&Variants!$E13&IF(Variants!$F13=""," "," "&Variants!$F13)&" — "&Variants!$H13) -> Bird Letter Pendant — Alphabet Դ — turquoise | B12: =IFERROR(IF(Variants!$B13="","",VLOOKUP(Variants!$B13,Designs!$A$3:$AP$165,9,FALSE())&" Handmade in Armenia."),"") -> Bird letters are an ornamental medieval Armenian script where each letter is formed from stylised birds, used in illuminated manuscripts. Handmade in Armenia. | C12: =IF(Variants!$J13="","",Variants!$J13) -> 49.4 | D12: =IF(Variants!$O13="","",Variants!$O13) -> 0 | E12: =Variants!$A13 -> KARNI-PEND-ALPHA-DA-TURQUOISE | F12: =IF(Variants!$E13="","",Variants!$E13&", Armenian, handmade, enamel, "&Variants!$D13) -> Alphabet, Armenian, handmade, enamel, Pendant | G12: =IFERROR(VLOOKUP(Variants!$B13,Designs!$A$3:$AP$165,12,FALSE())&", enamel","") -> 925 Silver Gold-Plated, enamel | H12: =IF(Variants!$B13="","","I did") -> I did | I12: =IF(Variants!$B13="","","Made to order") -> Made to order | J12: =IF(Variants!$D13="","",Variants!$D13) -> Pendant | K12: =IF(Variants!$Y13="","",Variants!$Y13) | L12: =IF(Variants!$H13="","",Variants!$H13) -> turquoise | M12: =IF(Variants!$G13="","",Variants!$G13)
A13: =IF(Variants!$B14="","",Variants!$C14&" — "&Variants!$E14&IF(Variants!$F14=""," "," "&Variants!$F14)&" — "&Variants!$H14) -> Bird Letter Pendant — Alphabet Դ — white | B13: =IFERROR(IF(Variants!$B14="","",VLOOKUP(Variants!$B14,Designs!$A$3:$AP$165,9,FALSE())&" Handmade in Armenia."),"") -> Bird letters are an ornamental medieval Armenian script where each letter is formed from stylised birds, used in illuminated manuscripts. Handmade in Armenia. | C13: =IF(Variants!$J14="","",Variants!$J14) -> 49.4 | D13: =IF(Variants!$O14="","",Variants!$O14) -> 0 | E13: =Variants!$A14 -> KARNI-PEND-ALPHA-DA-WHITE | F13: =IF(Variants!$E14="","",Variants!$E14&", Armenian, handmade, enamel, "&Variants!$D14) -> Alphabet, Armenian, handmade, enamel, Pendant | G13: =IFERROR(VLOOKUP(Variants!$B14,Designs!$A$3:$AP$165,12,FALSE())&", enamel","") -> 925 Silver Gold-Plated, enamel | H13: =IF(Variants!$B14="","","I did") -> I did | I13: =IF(Variants!$B14="","","Made to order") -> Made to order | J13: =IF(Variants!$D14="","",Variants!$D14) -> Pendant | K13: =IF(Variants!$Y14="","",Variants!$Y14) | L13: =IF(Variants!$H14="","",Variants!$H14) -> white | M13: =IF(Variants!$G14="","",Variants!$G14)
... A475: =IF(Variants!$B476="","",Variants!$C476&" — "&Variants!$E476&IF(Variants!$F476=""," "," "&Variants!$F476)&" — "&Variants!$H476) -> Արեւագորգի Վիշապ — Vishab Arevagorg — green | B475: =IFERROR(IF(Variants!$B476="","",VLOOKUP(Variants!$B476,Designs!$A$3:$AP$165,9,FALSE())&" Handmade in Armenia."),"") -> Combines the vishap (dragon) motif with the arevagorg (sun-carpet) — an Armenian solar ornament symbolising life and eternity. Handmade in Armenia. | C475: =IF(Variants!$J476="","",Variants!$J476) -> 44.2 | D475: =IF(Variants!$O476="","",Variants!$O476) -> 0 | E475: =Variants!$A476 -> KARNI-CHBRAC-VISHABAREVAGORG-GREEN | F475: =IF(Variants!$E476="","",Variants!$E476&", Armenian, handmade, enamel, "&Variants!$D476) -> Vishab Arevagorg, Armenian, handmade, enamel, chain bracelet | G475: =IFERROR(VLOOKUP(Variants!$B476,Designs!$A$3:$AP$165,12,FALSE())&", enamel","") -> 925 Silver Gold-Plated, enamel | H475: =IF(Variants!$B476="","","I did") -> I did | I475: =IF(Variants!$B476="","","Made to order") -> Made to order | J475: =IF(Variants!$D476="","",Variants!$D476) -> chain bracelet | K475: =IF(Variants!$Y476="","",Variants!$Y476) | L475: =IF(Variants!$H476="","",Variants!$H476) -> green | M475: =IF(Variants!$G476="","",Variants!$G476)

Sheet Dropdowns
A1: Control lists, FX rates, channels & cleanup log
A2: Edit these to drive dropdowns & conversions across the workbook.
A4: Status | B4: Metal | C4: Plating | D4: Enamel type | E4: Handmade | F4: Made to order | G4: Txn type | H4: Channel | J4: FX | K4: 1 AMD = | M4: Cleanup log — field | N4: From | O4: To | P4: Detail
A5: Active | B5: 925 Sterling Silver | C5: None | D5: Hot / Vitreous | E5: Yes | F5: Yes | G5: Sale | H5: Website | J5: USD | K5: 0.0026 | M5: Collection | N5: Artsakhi khachanakhsh | O5: Artsakhi Khachanakhsh | P5: 10 rows — standardized capitalization
A6: Out of stock | B6: 925 Silver Gold-Plated | C6: 24k Gold Plate | D6: Cold | E6: No | F6: No | G6: Restock | H6: Instagram DM | J6: EUR | K6: 0.0024 | M6: Design name | N6: (blank) | O6: derived from Category + Collection | P6: 170 rows — auto-filled
A7: Made to order | B7: 14k Gold | C7: 18k Gold Plate | D7: Cloisonné | E7: Mixed | G7: Return | H7: Cafesjian Center | J7: RUB | K7: 0.205
A8: Seasonal | B8: 18k Gold | C8: Rose Gold Plate | D8: Champlevé | G8: Adjustment | H8: Made By Armenia | J8: Updated | K8: 2026-05-18
A9: Archived | B9: Brass | C9: Rhodium | D9: None | G9: Sample/Gift | H9: Matenadaran | J9: Edit blue rate cells when FX moves
A10: Coming soon | B10: Brass Gold-Plated | C10: Oxidized / Antique | G10: Damage/Loss | H10: UMA
B11: Mixed | C11: Polished | H11: Megamall
C12: Matte | H12: Etsy
H13: Wholesale
H14: Other
